Workbook

Sheet Lisez-moi
B1: Inventaire des données pour instancier MAELIA en Guadeloupe
B2: Généré le 14/10/2026 à partir des tables MOSAICA (année 2017, scénario RESTIT) et de la documentation MAELIA.
B4: L'échelle
A5: 0 | B5: Absente et difficile à obtenir | C5: Ni dans MOSAICA ni dans un référentiel : expérimentation, calibration ou enquête lourde.
A6: 1 | B6: Absente mais accessible | C6: Pas dans MOSAICA, mais publiée ou récupérable vite : littérature, base publique, dire d'expert.
A7: 2 | B7: Disponible, à retravailler | C7: Une valeur existe : proxy, valeur par famille, autre unité ou définition, niveau discutable.
A8: 3 | B8: Disponible et utilisable | C8: Dans les tables de MOSAICA, à la bonne maille : une simple mise en forme suffit.
A9: – | B9: Sans objet | C9: Le paramètre ne concerne pas cette culture (pas d'irrigation, pas de travail du sol, prairie simulée par HerbSim, jachère sans ITK).
B11: Les feuilles
B12: Synthèse | C12: Score moyen par famille de cultures et par thème, et les verrous qui ne tiennent pas aux données.
B13: Cultures | C13: 75 cultures fines de MOSAICA × 50 paramètres MAELIA. Survoler un en-tête de colonne affiche le sens du paramètre et la règle de notation.
B14: Paramètres | C14: Le dictionnaire des colonnes : ce que MOSAICA a, comment la note est donnée, où chercher, et la surface concernée par chaque manque.
B15: Autres données | C15: 48 jeux de données hors cultures (climat, sols, parcellaire, exploitations, hydrologie…), avec leurs sources et leurs liens.
B17: Comment les notes sont données
B18: Notes calculées | C18: Quand la donnée se lit dans les tables de MOSAICA (rendement, opérations, temps de travail, doses, prix, aides, charges), la note est calculée culture par culture. Elle est plafonnée à 2 quand la valeur est un proxy ou que son niveau est discuté.
B19: Notes appréciées | C19: Quand la donnée manque (phénologie, Kc, réponse à l'eau, besoins en azote, calendrier), la note dit seulement si une référence publiée existe pour la plante : 1 si oui, 0 sinon. C'est une appréciation à faire valider par les agronomes ; les pistes de sources n'ont pas été vérifiées une à une.
B20: Variantes d'une même plante | C20: Les paramètres d'espèce sont communs à toutes les variantes d'une plante (les 18 cannes à sucre, les 4 bananes) : seuls l'ITK, le rendement et l'économie les distinguent.
B21: Surface 2017 | C21: Surface observée, ventilée sur les cultures fines par les règles GAMS d'attribution des ITK. Elle sert à pondérer : un manque sur la canne pèse plus qu'un manque sur le melon.
B22: Corriger une note | C22: Les notes se modifient dans la feuille Cultures (liste déroulante) ; couleurs, moyennes et Synthèse suivent. Relancer le script écrase ces corrections : pour les garder, les reporter dans le script.
B24: Sources MAELIA et versions
B25: Guide de l'utilisateur | C25: Version d'août 2026 : structure des fichiers, application ITK. Tables parfois tronquées.
B26: Note de 2022 | C26: Note d'accompagnement à la préparation des données d'entrée : champs obligatoires des sols, couples de règles de déclenchement.
B27: Formation de septembre 2026 | C27: Supports, grille d'enquête ITK (version 1.4.22) et deux jeux d'exemple : terrainTest et le jeu du TD, simulé avec MAELIA 1.4.31.
B28: Quand les sources divergent | C28: Le jeu 1.4.31 fait foi, parce qu'il a tourné : dossier parametres/, lignes d'ITK renommées, prairies simulées avec l'azote, économie facultative. Les points douteux sont listés en bas de la feuille Synthèse.
B30: Liens utiles
B31: Documentation MAELIA | C31: https://maelia.pages-forge.inrae.fr/documentation
B32: Documentation MAELIA — données d'entrée | C32: https://maelia.pages-forge.inrae.fr/documentation/04-donnees_entree.html
B33: Application ITK (compte : Renaud Misslin, MAELAB) | C33: https://analytics.huma-num.fr/Renaud.Misslin/maelia_itk/
B34: Forum MAELIA | C34: https://forum-maelia.discourse.group/
B35: Site MAELIA | C35: https://www.maelia-iam.fr/
B37: Régénérer | C37: .venv/Scripts/python clement/maelia/build_inventaire_donnees_maelia.py
C38: Pour aller plus loin : docs/maelia/README.md, crop-parameters.md et coupling-todo.md dans le dépôt MOSAICA.

Sheet Synthèse
A1: Synthèse : où en sont les données pour MAELIA en Guadeloupe
A2: Moyenne des notes (0 à 3) ; les cellules sans objet ne comptent pas. Tout est recalculé depuis les feuilles Cultures et Autres données.
A4: Par famille de cultures
A5: Famille | B5: Variantes | C5: Surface 2017 (ha) | D5: Espèce : eau, phéno | E5: Espèce : N et C | F5: ITK | G5: Fertilisation | H5: Économie | I5: Score global
A6: Canne à sucre et canne fibre | B6: =COUNTIF(Cultures!$A$5:$A$79,$A6) -> 28 | C6: =SUMIF(Cultures!$A$5:$A$79,$A6,Cultures!$D$5:$D$79) -> 12812.93 | D6: =IFERROR(AVERAGEIFS(Cultures!$BG$5:$BG$79,Cultures!$A$5:$A$79,$A6),"–") -> 1.2433036 | E6: =IFERROR(AVERAGEIFS(Cultures!$BH$5:$BH$79,Cultures!$A$5:$A$79,$A6),"–") -> 1.2142857 | F6: =IFERROR(AVERAGEIFS(Cultures!$BI$5:$BI$79,Cultures!$A$5:$A$79,$A6),"–") -> 1.6996753 | G6: =IFERROR(AVERAGEIFS(Cultures!$BJ$5:$BJ$79,Cultures!$A$5:$A$79,$A6),"–") -> 2 | H6: =IFERROR(AVERAGEIFS(Cultures!$BK$5:$BK$79,Cultures!$A$5:$A$79,$A6),"–") -> 1.5285714 | I6: =IFERROR(AVERAGEIFS(Cultures!$BL$5:$BL$79,Cultures!$A$5:$A$79,$A6),"–") -> 1.3828869
A7: Banane dessert | B7: =COUNTIF(Cultures!$A$5:$A$79,$A7) -> 4 | C7: =SUMIF(Cultures!$A$5:$A$79,$A7,Cultures!$D$5:$D$79) -> 1920.8 | D7: =IFERROR(AVERAGEIFS(Cultures!$BG$5:$BG$79,Cultures!$A$5:$A$79,$A7),"–") -> 1.25 | E7: =IFERROR(AVERAGEIFS(Cultures!$BH$5:$BH$79,Cultures!$A$5:$A$79,$A7),"–") -> 1.2884615 | F7: =IFERROR(AVERAGEIFS(Cultures!$BI$5:$BI$79,Cultures!$A$5:$A$79,$A7),"–") -> 1.3159091 | G7: =IFERROR(AVERAGEIFS(Cultures!$BJ$5:$BJ$79,Cultures!$A$5:$A$79,$A7),"–") -> 2 | H7: =IFERROR(AVERAGEIFS(Cultures!$BK$5:$BK$79,Cultures!$A$5:$A$79,$A7),"–") -> 1.6 | I7: =IFERROR(AVERAGEIFS(Cultures!$BL$5:$BL$79,Cultures!$A$5:$A$79,$A7),"–") -> 1.3458603
A8: Plantain | B8: =COUNTIF(Cultures!$A$5:$A$79,$A8) -> 2 | C8: =SUMIF(Cultures!$A$5:$A$79,$A8,Cultures!$D$5:$D$79) -> 147.21 | D8: =IFERROR(AVERAGEIFS(Cultures!$BG$5:$BG$79,Cultures!$A$5:$A$79,$A8),"–") -> 1.25 | E8: =IFERROR(AVERAGEIFS(Cultures!$BH$5:$BH$79,Cultures!$A$5:$A$79,$A8),"–") -> 1.3846154 | F8: =IFERROR(AVERAGEIFS(Cultures!$BI$5:$BI$79,Cultures!$A$5:$A$79,$A8),"–") -> 1.4272727 | G8: =IFERROR(AVERAGEIFS(Cultures!$BJ$5:$BJ$79,Cultures!$A$5:$A$79,$A8),"–") -> 2 | H8: =IFERROR(AVERAGEIFS(Cultures!$BK$5:$BK$79,Cultures!$A$5:$A$79,$A8),"–") -> 1.6 | I8: =IFERROR(AVERAGEIFS(Cultures!$BL$5:$BL$79,Cultures!$A$5:$A$79,$A8),"–") -> 1.3977798
A9: Prairies | B9: =COUNTIF(Cultures!$A$5:$A$79,$A9) -> 2 | C9: =SUMIF(Cultures!$A$5:$A$79,$A9,Cultures!$D$5:$D$79) -> 6109.43 | D9: =IFERROR(AVERAGEIFS(Cultures!$BG$5:$BG$79,Cultures!$A$5:$A$79,$A9),"–") -> 0 | E9: =IFERROR(AVERAGEIFS(Cultures!$BH$5:$BH$79,Cultures!$A$5:$A$79,$A9),"–") -> – | F9: =IFERROR(AVERAGEIFS(Cultures!$BI$5:$BI$79,Cultures!$A$5:$A$79,$A9),"–") -> 0.91964286 | G9: =IFERROR(AVERAGEIFS(Cultures!$BJ$5:$BJ$79,Cultures!$A$5:$A$79,$A9),"–") -> 1.5 | H9: =IFERROR(AVERAGEIFS(Cultures!$BK$5:$BK$79,Cultures!$A$5:$A$79,$A9),"–") -> 1.6 | I9: =IFERROR(AVERAGEIFS(Cultures!$BL$5:$BL$79,Cultures!$A$5:$A$79,$A9),"–") -> 1.125
A10: Maraîchage (dont tomate) | B10: =COUNTIF(Cultures!$A$5:$A$79,$A10) -> 30 | C10: =SUMIF(Cultures!$A$5:$A$79,$A10,Cultures!$D$5:$D$79) -> 1086.97 | D10: =IFERROR(AVERAGEIFS(Cultures!$BG$5:$BG$79,Cultures!$A$5:$A$79,$A10),"–") -> 0.82708333 | E10: =IFERROR(AVERAGEIFS(Cultures!$BH$5:$BH$79,Cultures!$A$5:$A$79,$A10),"–") -> 1.1717949 | F10: =IFERROR(AVERAGEIFS(Cultures!$BI$5:$BI$79,Cultures!$A$5:$A$79,$A10),"–") -> 1.3381145 | G10: =IFERROR(AVERAGEIFS(Cultures!$BJ$5:$BJ$79,Cultures!$A$5:$A$79,$A10),"–") -> 1.5166667 | H10: =IFERROR(AVERAGEIFS(Cultures!$BK$5:$BK$79,Cultures!$A$5:$A$79,$A10),"–") -> 1.6 | I10: =IFERROR(AVERAGEIFS(Cultures!$BL$5:$BL$79,Cultures!$A$5:$A$79,$A10),"–") -> 1.1458325
A11: Melon | B11: =COUNTIF(Cultures!$A$5:$A$79,$A11) -> 1 | C11: =SUMIF(Cultures!$A$5:$A$79,$A11,Cultures!$D$5:$D$79) -> 189.36 | D11: =IFERROR(AVERAGEIFS(Cultures!$BG$5:$BG$79,Cultures!$A$5:$A$79,$A11),"–") -> 1.25 | E11: =IFERROR(AVERAGEIFS(Cultures!$BH$5:$BH$79,Cultures!$A$5:$A$79,$A11),"–") -> 1.3846154 | F11: =IFERROR(AVERAGEIFS(Cultures!$BI$5:$BI$79,Cultures!$A$5:$A$79,$A11),"–") -> 1.5454545 | G11: =IFERROR(AVERAGEIFS(Cultures!$BJ$5:$BJ$79,Cultures!$A$5:$A$79,$A11),"–") -> 2 | H11: =IFERROR(AVERAGEIFS(Cultures!$BK$5:$BK$79,Cultures!$A$5:$A$79,$A11),"–") -> 1.6 | I11: =IFERROR(AVERAGEIFS(Cultures!$BL$5:$BL$79,Cultures!$A$5:$A$79,$A11),"–") -> 1.4255319
A12: Igname | B12: =COUNTIF(Cultures!$A$5:$A$79,$A12) -> 2 | C12: =SUMIF(Cultures!$A$5:$A$79,$A12,Cultures!$D$5:$D$79) -> 145.42 | D12: =IFERROR(AVERAGEIFS(Cultures!$BG$5:$BG$79,Cultures!$A$5:$A$79,$A12),"–") -> 1.1875 | E12: =IFERROR(AVERAGEIFS(Cultures!$BH$5:$BH$79,Cultures!$A$5:$A$79,$A12),"–") -> 1.3076923 | F12: =IFERROR(AVERAGEIFS(Cultures!$BI$5:$BI$79,Cultures!$A$5:$A$79,$A12),"–") -> 1.5681818 | G12: =IFERROR(AVERAGEIFS(Cultures!$BJ$5:$BJ$79,Cultures!$A$5:$A$79,$A12),"–") -> 2 | H12: =IFERROR(AVERAGEIFS(Cultures!$BK$5:$BK$79,Cultures!$A$5:$A$79,$A12),"–") -> 1.6 | I12: =IFERROR(AVERAGEIFS(Cultures!$BL$5:$BL$79,Cultures!$A$5:$A$79,$A12),"–") -> 1.3869103
A13: Ananas | B13: =COUNTIF(Cultures!$A$5:$A$79,$A13) -> 2 | C13: =SUMIF(Cultures!$A$5:$A$79,$A13,Cultures!$D$5:$D$79) -> 132.67 | D13: =IFERROR(AVERAGEIFS(Cultures!$BG$5:$BG$79,Cultures!$A$5:$A$79,$A13),"–") -> 1.1875 | E13: =IFERROR(AVERAGEIFS(Cultures!$BH$5:$BH$79,Cultures!$A$5:$A$79,$A13),"–") -> 1.2307692 | F13: =IFERROR(AVERAGEIFS(Cultures!$BI$5:$BI$79,Cultures!$A$5:$A$79,$A13),"–") -> 1.9375 | G13: =IFERROR(AVERAGEIFS(Cultures!$BJ$5:$BJ$79,Cultures!$A$5:$A$79,$A13),"–") -> 2 | H13: =IFERROR(AVERAGEIFS(Cultures!$BK$5:$BK$79,Cultures!$A$5:$A$79,$A13),"–") -> 1.6 | I13: =IFERROR(AVERAGEIFS(Cultures!$BL$5:$BL$79,Cultures!$A$5:$A$79,$A13),"–") -> 1.4204545
A14: Agrumes | B14: =COUNTIF(Cultures!$A$5:$A$79,$A14) -> 1 | C14: =SUMIF(Cultures!$A$5:$A$79,$A14,Cultures!$D$5:$D$79) -> 100.84 | D14: =IFERROR(AVERAGEIFS(Cultures!$BG$5:$BG$79,Cultures!$A$5:$A$79,$A14),"–") -> 0.9375 | E14: =IFERROR(AVERAGEIFS(Cultures!$BH$5:$BH$79,Cultures!$A$5:$A$79,$A14),"–") -> 1.1538462 | F14: =IFERROR(AVERAGEIFS(Cultures!$BI$5:$BI$79,Cultures!$A$5:$A$79,$A14),"–") -> 1.5454545 | G14: =IFERROR(AVERAGEIFS(Cultures!$BJ$5:$BJ$79,Cultures!$A$5:$A$79,$A14),"–") -> 2 | H14: =IFERROR(AVERAGEIFS(Cultures!$BK$5:$BK$79,Cultures!$A$5:$A$79,$A14),"–") -> 1.6 | I14: =IFERROR(AVERAGEIFS(Cultures!$BL$5:$BL$79,Cultures!$A$5:$A$79,$A14),"–") -> 1.2553191
A15: Vergers | B15: =COUNTIF(Cultures!$A$5:$A$79,$A15) -> 2 | C15: =SUMIF(Cultures!$A$5:$A$79,$A15,Cultures!$D$5:$D$79) -> 310.89 | D15: =IFERROR(AVERAGEIFS(Cultures!$BG$5:$BG$79,Cultures!$A$5:$A$79,$A15),"–") -> 0.8125 | E15: =IFERROR(AVERAGEIFS(Cultures!$BH$5:$BH$79,Cultures!$A$5:$A$79,$A15),"–") -> 1 | F15: =IFERROR(AVERAGEIFS(Cultures!$BI$5:$BI$79,Cultures!$A$5:$A$79,$A15),"–") -> 1.5 | G15: =IFERROR(AVERAGEIFS(Cultures!$BJ$5:$BJ$79,Cultures!$A$5:$A$79,$A15),"–") -> 1.5 | H15: =IFERROR(AVERAGEIFS(Cultures!$BK$5:$BK$79,Cultures!$A$5:$A$79,$A15),"–") -> 1.6 | I15: =IFERROR(AVERAGEIFS(Cultures!$BL$5:$BL$79,Cultures!$A$5:$A$79,$A15),"–") -> 1.1382979
A16: Jachère | B16: =COUNTIF(Cultures!$A$5:$A$79,$A16) -> 1 | C16: =SUMIF(Cultures!$A$5:$A$79,$A16,Cultures!$D$5:$D$79) -> 621.47 | D16: =IFERROR(AVERAGEIFS(Cultures!$BG$5:$BG$79,Cultures!$A$5:$A$79,$A16),"–") -> – | E16: =IFERROR(AVERAGEIFS(Cultures!$BH$5:$BH$79,Cultures!$A$5:$A$79,$A16),"–") -> – | F16: =IFERROR(AVERAGEIFS(Cultures!$BI$5:$BI$79,Cultures!$A$5:$A$79,$A16),"–") -> 2 | G16: =IFERROR(AVERAGEIFS(Cultures!$BJ$5:$BJ$79,Cultures!$A$5:$A$79,$A16),"–") -> – | H16: =IFERROR(AVERAGEIFS(Cultures!$BK$5:$BK$79,Cultures!$A$5:$A$79,$A16),"–") -> 1.5 | I16: =IFERROR(AVERAGEIFS(Cultures!$BL$5:$BL$79,Cultures!$A$5:$A$79,$A16),"–") -> 1.6
A19: Par thème, hors cultures
A20: Thème | B20: Données | C20: Qualité moyenne | D20: Données à 0
A21: Climat | B21: =COUNTIF('Autres données'!$A$5:$A$52,$A21) -> 7 | C21: =IFERROR(AVERAGEIFS('Autres données'!$G$5:$G$52,'Autres données'!$A$5:$A$52,$A21),"–") -> 1.1428571 | D21: =COUNTIFS('Autres données'!$A$5:$A$52,$A21,'Autres données'!$G$5:$G$52,0) -> 0
A22: Sols | B22: =COUNTIF('Autres données'!$A$5:$A$52,$A22) -> 9 | C22: =IFERROR(AVERAGEIFS('Autres données'!$G$5:$G$52,'Autres données'!$A$5:$A$52,$A22),"–") -> 1.3333333 | D22: =COUNTIFS('Autres données'!$A$5:$A$52,$A22,'Autres données'!$G$5:$G$52,0) -> 1
A23: Parcellaire | B23: =COUNTIF('Autres données'!$A$5:$A$52,$A23) -> 5 | C23: =IFERROR(AVERAGEIFS('Autres données'!$G$5:$G$52,'Autres données'!$A$5:$A$52,$A23),"–") -> 2 | D23: =COUNTIFS('Autres données'!$A$5:$A$52,$A23,'Autres données'!$G$5:$G$52,0) -> 0
A24: Exploitations | B24: =COUNTIF('Autres données'!$A$5:$A$52,$A24) -> 5 | C24: =IFERROR(AVERAGEIFS('Autres données'!$G$5:$G$52,'Autres données'!$A$5:$A$52,$A24),"–") -> 1.4 | D24: =COUNTIFS('Autres données'!$A$5:$A$52,$A24,'Autres données'!$G$5:$G$52,0) -> 1
A25: Engrais et PRO | B25: =COUNTIF('Autres données'!$A$5:$A$52,$A25) -> 3 | C25: =IFERROR(AVERAGEIFS('Autres données'!$G$5:$G$52,'Autres données'!$A$5:$A$52,$A25),"–") -> 1.3333333 | D25: =COUNTIFS('Autres données'!$A$5:$A$52,$A25,'Autres données'!$G$5:$G$52,0) -> 0
A26: Économie | B26: =COUNTIF('Autres données'!$A$5:$A$52,$A26) -> 3 | C26: =IFERROR(AVERAGEIFS('Autres données'!$G$5:$G$52,'Autres données'!$A$5:$A$52,$A26),"–") -> 1 | D26: =COUNTIFS('Autres données'!$A$5:$A$52,$A26,'Autres données'!$G$5:$G$52,0) -> 0
A27: Validation | B27: =COUNTIF('Autres données'!$A$5:$A$52,$A27) -> 2 | C27: =IFERROR(AVERAGEIFS('Autres données'!$G$5:$G$52,'Autres données'!$A$5:$A$52,$A27),"–") -> 0.5 | D27: =COUNTIFS('Autres données'!$A$5:$A$52,$A27,'Autres données'!$G$5:$G$52,0) -> 1
A28: Référentiels | B28: =COUNTIF('Autres données'!$A$5:$A$52,$A28) -> 3 | C28: =IFERROR(AVERAGEIFS('Autres données'!$G$5:$G$52,'Autres données'!$A$5:$A$52,$A28),"–") -> 2 | D28: =COUNTIFS('Autres données'!$A$5:$A$52,$A28,'Autres données'!$G$5:$G$52,0) -> 0
A29: Hydrologie | B29: =COUNTIF('Autres données'!$A$5:$A$52,$A29) -> 7 | C29: =IFERROR(AVERAGEIFS('Autres données'!$G$5:$G$52,'Autres données'!$A$5:$A$52,$A29),"–") -> 1.4285714 | D29: =COUNTIFS('Autres données'!$A$5:$A$52,$A29,'Autres données'!$G$5:$G$52,0) -> 0
A30: Normatif | B30: =COUNTIF('Autres données'!$A$5:$A$52,$A30) -> 1 | C30: =IFERROR(AVERAGEIFS('Autres données'!$G$5:$G$52,'Autres données'!$A$5:$A$52,$A30),"–") -> 2 | D30: =COUNTIFS('Autres données'!$A$5:$A$52,$A30,'Autres données'!$G$5:$G$52,0) -> 0
A31: Indicateurs | B31: =COUNTIF('Autres données'!$A$5:$A$52,$A31) -> 2 | C31: =IFERROR(AVERAGEIFS('Autres données'!$G$5:$G$52,'Autres données'!$A$5:$A$52,$A31),"–") -> 1.5 | D31: =COUNTIFS('Autres données'!$A$5:$A$52,$A31,'Autres données'!$G$5:$G$52,0) -> 0
A32: Filières | B32: =COUNTIF('Autres données'!$A$5:$A$52,$A32) -> 1 | C32: =IFERROR(AVERAGEIFS('Autres données'!$G$5:$G$52,'Autres données'!$A$5:$A$52,$A32),"–") -> 1 | D32: =COUNTIFS('Autres données'!$A$5:$A$52,$A32,'Autres données'!$G$5:$G$52,0) -> 0
A35: Ce qu'une meilleure donnée ne réglera pas
A36: Cultures tropicales | B36: Hors la jachère (« gel »), aucune culture de MOSAICA n'existe dans la base d'espèces de MAELIA. Chacune est à créer, avec le référent thématique : une colonne complète dans le fichier des espèces (la formation le fait avec « mon_espece »).
A37: Plantations pluriannuelles | B37: Canne (3 à 7 ans), banane (8 à 15 ans), agrumes et vergers (15 ans), ananas (18 mois) : la séquence MAELIA est annuelle et un ITK décrit une année, semis et récolte compris. Aucun mécanisme documenté ; vergers et vignes ne figurent pas dans le référentiel d'espèces de la grille d'enquête.
A38: Plafonds d'un ITK | B38: La grille d'enquête ITK prévoit un semis et une récolte par ITK, 4 apports, 8 traitements, 5 désherbages, 4 préparations du sol (les apports s'entendent par stratégie de fertilisation). 21 cultures sur 75 en sortent, soit 3614 ha observés en 2017, jusqu'à 34 passages de récolte par an pour BA_INT : colonne Dépassements de la feuille Cultures.
A39: Récolte | B39: La récolte attend la maturité en degrés-jours, puis elle est forcée en fin de fenêtre. Une campagne fixée par l'usine (canne) ou une récolte continue (banane, maraîchage) ne se décrivent pas ainsi.
A40: Prairies | B40: HerbSim ne connaît que 7 espèces tempérées et 5 types de graminées : les prairies naturelles tropicales, un quart de la surface observée, n'ont pas de paramètres. L'azote n'est plus un obstacle : le jeu de la formation fait tourner des prairies fauchées et pâturées avec AqYieldNC (HerbSimNC).
A41: Rendement potentiel | B41: RENDEMENT_OPTIMAL reste une entrée : le remplir avec Rdt_Cult reporterait la surestimation des rendements (vigilance C.1) dans MAELIA.
A42: Opérations sans type MAELIA | B42: Effeuillage, tuteurage, ensachage, emballage, soins aux animaux : jusqu'à 85 % des heures de la banane disparaissent à la traduction.
A43: Choix de l'ITK | B43: MOSAICA choisit la variante d'ITK, MAELIA la déduit de la situation. Deux pistes pour imposer une variante par parcelle sans créer une espèce par variante : la séquence de référence (ID_SDC de la parcelle, IDS_SDCS de l'ITK) et le critère libre CRIT_SPAT_ADHOC. À vérifier avec l'équipe.
A44: Calendrier tempéré | B44: La première année démarre en août ; un frein hivernal, un drapeau « culture d'hiver » et une fauche de fin d'été au 1er août sont dans le modèle. À passer en revue pour un climat sans hiver.
A45: Mécanisation | B45: D'après la note de 2022, les entrées OUTIL, PASSAGES et AGRIW n'ont pas d'effet sur la simulation : aucun conflit de matériel n'est simulé. À revérifier en 1.4.31.
A46: Fichiers | B46: Les csv et dbf de MAELIA ne se modifient pas dans Excel (séparateurs, décimales). Ce classeur sert à piloter la collecte, pas à saisir les données.
A49: À confirmer avec l'équipe MAELIA
A50: Format des fichiers | B50: Le guide (août 2026) place especesCultivees.csv et Engrais.csv dans culture/ et Engrais/. Le jeu de la formation (MAELIA 1.4.31) lit un dossier parametres/ : une case vide prend la valeur de la base MAELIA, une espèce nouvelle demande une colonne complète. Les lignes d'ITK y sont renommées (TRAVAIL_SOL, DESHERBAGE_MECA, PATURE). Quel format viser ?
A51: Variante d'ITK par parcelle | B51: ID_SDC et CRIT_SPAT_ADHOC permettent-ils d'imposer la variante choisie par MOSAICA sans créer une espèce par variante ?
A52: Plafonds et récoltes multiples | B52: Nombre maximal d'opérations par ITK dans la version courante ; comment décrire 34 passages de récolte par an.
A53: Main-d'œuvre | B53: Où déclarer le nombre d'unités de main-d'œuvre par exploitation ; les chantiers faits par un tiers (coupe de la canne) consomment-ils le temps de l'agriculteur ?
A54: Module économique | B54: Quels fichiers la version courante lit-elle : prixVentes, primes, chargesOp et chargesDePassage du guide, ou les prix unitaires de la grille d'enquête ? Unité de prixVentes (le guide imprime €/ha).
A55: Zone hydrographique | B55: Faut-il au moins une zone hydrographique et un contour quand le module hydrologique est coupé ?
A56: Géographie | B56: Système de coordonnées attendu hors métropole ; POSX et POSY de la grille météo sont décrits en Lambert II étendu.
A57: Météo | B57: Unité du rayonnement (MJ/m²/j ou W/m²) ; d'où vient l'humidité de l'air du déclencheur hygrométrie.
A58: État initial du sol | B58: Azote minéral initial par couche et fraction stable de la matière organique : fichier ou valeurs par défaut ?
A59: Climat sans hiver | B59: FREIN = 1, IS_CULTURE_HIVER, démarrage en août, stress de gel : quels réglages pour un terrain tropical ?

Sheet Cultures
A1: Qualité des données par culture et par paramètre MAELIA
A2: 0 = absente, difficile · 1 = absente, accessible · 2 = disponible, à retravailler · 3 = utilisable · – = sans objet. Les notes sont modifiables : les moyennes et la feuille Synthèse suivent.
A3: Famille | B3: Code | C3: Culture | D3: Surface 2017 (ha) | E3: Modèle MAELIA | F3: Cycle | G3: Heures hors types MAELIA | H3: Dépassements des plafonds d'un ITK (passages par an) | I3: Espèce — AqYield : rendement, phénologie, eau (especesCultivees.csv) | Z3: Espèce — AqYieldNC : azote et carbone (especesCultivees.csv) | AN3: ITK (reglesDeDecisions.csv) | AZ3: Fertilisation | BB3: Économie | BG3: Moyennes de la ligne
I4: RENDEMENT_OPTIMAL | J4: RENDEMENT_MOYEN | K4: RENDEMENT_MIN | L4: Tbase | M4: Tmax | N4: DEGRES_J_LevTbase | O4: DEGRES_J_Flor | P4: DEGRES_J_matPhyTbase | Q4: FREIN | R4: KMAX | S4: CVIG | T4: CSTO | U4: coeff_Fonction_Prod | V4: CRACINE | W4: PROF_MAX_RACINE | X4: ZonesClimatiques | Y4: especesHerbSim.csv | Z4: BESOIN_N | AA4: Type_Nacq + courbe | AB4: adil, bdil, adilmax | AC4: N_grain | AD4: Tms | AE4: HI | AF4: SR_ratio | AG4: beta | AH4: C_aer, C_rac | AI4: CN_ratio | AJ4: Pse | AK4: ABSCISSION | AL4: isLEG | AM4: especeRepousse | AN4: ID_PREC | AO4: ZONE_PEDO, TYPE_EXPL, CLIMAT, IDS_SDCS | AP4: MATERIEL | AQ4: IS_<OT> | AR4: <OT>_TEMPS | AS4: <OT>_DEBUT / _FIN | AT4: Seuils de déclenchement | AU4: TRAVAIL_SOL_EFFET_RUs | AV4: IRRIGATION_DOSE, _TD | AW4: IRRIGATION fenêtre, stades, seuils | AX4: PHYTO produits, doses | AY4: FAUCHE, PATURE | AZ4: FERTIALT produit, dose N-P-K | BA4: FERTIALT calendrier, alternatives | BB4: prixVentes.csv | BC4: primes.csv | BD4: Prix des intrants | BE4: chargesOp.csv | BF4: chargesDePassage.csv | BG4: Espèce : eau, phéno | BH4: Espèce : N et C | BI4: ITK | BJ4: Fertilisation | BK4: Économie | BL4: Score global | BM4: Paramètres à 0
A5: Canne à sucre et canne fibre | B5: CS_NGT_NIM | C5: Canne à sucre : Nord Grande-Terre, pluvial, récolte mécanisée | D5: 3365.9 | E5: AqYield / AqYieldNC | F5: plantation de 7 ans | G5: 0.12 | I5: 1 | J5: 2 | K5: 2 | L5: 1 | M5: 1 | N5: 1 | O5: 1 | P5: 1 | Q5: 3 | R5: 1 | S5: 0 | T5: 1 | U5: 1 | V5: 0 | W5: 2 | X5: 2 | Y5: – | Z5: 1 | AA5: 0 | AB5: 1 | AC5: 1 | AD5: 1 | AE5: 2 | AF5: 2 | AG5: 1 | AH5: 2 | AI5: 1 | AJ5: 1 | AK5: 1 | AL5: 3 | AM5: 0 | AN5: 2 | AO5: 2 | AP5: – | AQ5: 2 | AR5: 2 | AS5: 1 | AT5: 0 | AU5: 2 | AV5: – | AW5: – | AX5: 3 | AY5: – | AZ5: 3 | BA5: 1 | BB5: 2 | BC5: 2 | BD5: 2 | BE5: 2 | BF5: 0 | BG5: =IFERROR(AVERAGE(I5:Y5),"–") -> 1.25 | BH5: =IFERROR(AVERAGE(Z5:AM5),"–") -> 1.2142857 | BI5: =IFERROR(AVERAGE(AN5:AY5),"–") -> 1.75 | BJ5: =IFERROR(AVERAGE(AZ5:BA5),"–") -> 2 | BK5: =IFERROR(AVERAGE(BB5:BF5),"–") -> 1.6 | BL5: =IFERROR(AVERAGE(I5:BF5),"–") -> 1.4 | BM5: =COUNTIF(I5:BF5,0) -> 6
A6: Canne à sucre et canne fibre | B6: CS_BT_NIM | C6: Canne à sucre : Basse-Terre, pluvial, récolte mécanisée | D6: 3349.2 | E6: AqYield / AqYieldNC | F6: plantation de 7 ans | G6: 0.12 | I6: 1 | J6: 2 | K6: 2 | L6: 1 | M6: 1 | N6: 1 | O6: 1 | P6: 1 | Q6: 3 | R6: 1 | S6: 0 | T6: 1 | U6: 1 | V6: 0 | W6: 2 | X6: 2 | Y6: – | Z6: 1 | AA6: 0 | AB6: 1 | AC6: 1 | AD6: 1 | AE6: 2 | AF6: 2 | AG6: 1 | AH6: 2 | AI6: 1 | AJ6: 1 | AK6: 1 | AL6: 3 | AM6: 0 | AN6: 2 | AO6: 2 | AP6: – | AQ6: 2 | AR6: 2 | AS6: 1 | AT6: 0 | AU6: 2 | AV6: – | AW6: – | AX6: 3 | AY6: – | AZ6: 3 | BA6: 1 | BB6: 2 | BC6: 2 | BD6: 2 | BE6: 2 | BF6: 0 | BG6: =IFERROR(AVERAGE(I6:Y6),"–") -> 1.25 | BH6: =IFERROR(AVERAGE(Z6:AM6),"–") -> 1.2142857 | BI6: =IFERROR(AVERAGE(AN6:AY6),"–") -> 1.75 | BJ6: =IFERROR(AVERAGE(AZ6:BA6),"–") -> 2 | BK6: =IFERROR(AVERAGE(BB6:BF6),"–") -> 1.6 | BL6: =IFERROR(AVERAGE(I6:BF6),"–") -> 1.4 | BM6: =COUNTIF(I6:BF6,0) -> 6
A7: Canne à sucre et canne fibre | B7: CS_MG_NISM | C7: Canne à sucre : Marie-Galante, pluvial, récolte semi-mécanisée | D7: 2186.1 | E7: AqYield / AqYieldNC | F7: plantation de 7 ans | G7: 0.12 | I7: 1 | J7: 2 | K7: 1 | L7: 1 | M7: 1 | N7: 1 | O7: 1 | P7: 1 | Q7: 3 | R7: 1 | S7: 0 | T7: 1 | U7: 1 | V7: 0 | W7: 2 | X7: 2 | Y7: – | Z7: 1 | AA7: 0 | AB7: 1 | AC7: 1 | AD7: 1 | AE7: 2 | AF7: 2 | AG7: 1 | AH7: 2 | AI7: 1 | AJ7: 1 | AK7: 1 | AL7: 3 | AM7: 0 | AN7: 2 | AO7: 2 | AP7: – | AQ7: 2 | AR7: 2 | AS7: 1 | AT7: 0 | AU7: 2 | AV7: – | AW7: – | AX7: 3 | AY7: – | AZ7: 3 | BA7: 1 | BB7: 2 | BC7: 2 | BD7: 2 | BE7: 2 | BF7: 0 | BG7: =IFERROR(AVERAGE(I7:Y7),"–") -> 1.1875 | BH7: =IFERROR(AVERAGE(Z7:AM7),"–") -> 1.2142857 | BI7: =IFERROR(AVERAGE(AN7:AY7),"–") -> 1.75 | BJ7: =IFERROR(AVERAGE(AZ7:BA7),"–") -> 2 | BK7: =IFERROR(AVERAGE(BB7:BF7),"–") -> 1.6 | BL7: =IFERROR(AVERAGE(I7:BF7),"–") -> 1.3777778 | BM7: =COUNTIF(I7:BF7,0) -> 6
A8: Canne à sucre et canne fibre | B8: CS_EGT_NIM | C8: Canne à sucre : Est Grande-Terre, pluvial, récolte mécanisée | D8: 1964.9 | E8: AqYield / AqYieldNC | F8: plantation de 7 ans | G8: 0.12 | I8: 1 | J8: 2 | K8: 2 | L8: 1 | M8: 1 | N8: 1 | O8: 1 | P8: 1 | Q8: 3 | R8: 1 | S8: 0 | T8: 1 | U8: 1 | V8: 0 | W8: 2 | X8: 2 | Y8: – | Z8: 1 | AA8: 0 | AB8: 1 | AC8: 1 | AD8: 1 | AE8: 2 | AF8: 2 | AG8: 1 | AH8: 2 | AI8: 1 | AJ8: 1 | AK8: 1 | AL8: 3 | AM8: 0 | AN8: 2 | AO8: 2 | AP8: – | AQ8: 2 | AR8: 2 | AS8: 1 | AT8: 0 | AU8: 2 | AV8: – | AW8: – | AX8: 3 | AY8: – | AZ8: 3 | BA8: 1 | BB8: 2 | BC8: 2 | BD8: 2 | BE8: 2 | BF8: 0 | BG8: =IFERROR(AVERAGE(I8:Y8),"–") -> 1.25 | BH8: =IFERROR(AVERAGE(Z8:AM8),"–") -> 1.2142857 | BI8: =IFERROR(AVERAGE(AN8:AY8),"–") -> 1.75 | BJ8: =IFERROR(AVERAGE(AZ8:BA8),"–") -> 2 | BK8: =IFERROR(AVERAGE(BB8:BF8),"–") -> 1.6 | BL8: =IFERROR(AVERAGE(I8:BF8),"–") -> 1.4 | BM8: =COUNTIF(I8:BF8,0) -> 6
A9: Canne à sucre et canne fibre | B9: CS_CGT_NIM | C9: Canne à sucre : Centre Grande-Terre, pluvial, récolte mécanisée | D9: 773.7 | E9: AqYield / AqYieldNC | F9: plantation de 7 ans | G9: 0.12 | I9: 1 | J9: 2 | K9: 2 | L9: 1 | M9: 1 | N9: 1 | O9: 1 | P9: 1 | Q9: 3 | R9: 1 | S9: 0 | T9: 1 | U9: 1 | V9: 0 | W9: 2 | X9: 2 | Y9: – | Z9: 1 | AA9: 0 | AB9: 1 | AC9: 1 | AD9: 1 | AE9: 2 | AF9: 2 | AG9: 1 | AH9: 2 | AI9: 1 | AJ9: 1 | AK9: 1 | AL9: 3 | AM9: 0 | AN9: 2 | AO9: 2 | AP9: – | AQ9: 2 | AR9: 2 | AS9: 1 | AT9: 0 | AU9: 2 | AV9: – | AW9: – | AX9: 3 | AY9: – | AZ9: 3 | BA9: 1 | BB9: 2 | BC9: 2 | BD9: 2 | BE9: 2 | BF9: 0 | BG9: =IFERROR(AVERAGE(I9:Y9),"–") -> 1.25 | BH9: =IFERROR(AVERAGE(Z9:AM9),"–") -> 1.2142857 | BI9: =IFERROR(AVERAGE(AN9:AY9),"–") -> 1.75 | BJ9: =IFERROR(AVERAGE(AZ9:BA9),"–") -> 2 | BK9: =IFERROR(AVERAGE(BB9:BF9),"–") -> 1.6 | BL9: =IFERROR(AVERAGE(I9:BF9),"–") -> 1.4 | BM9: =COUNTIF(I9:BF9,0) -> 6
A10: Canne à sucre et canne fibre | B10: CS_NGT_NISM | C10: Canne à sucre : Nord Grande-Terre, pluvial, récolte semi-mécanisée | D10: 653.8 | E10: AqYield / AqYieldNC | F10: plantation de 7 ans | G10: 0.12 | I10: 1 | J10: 2 | K10: 2 | L10: 1 | M10: 1 | N10: 1 | O10: 1 | P10: 1 | Q10: 3 | R10: 1 | S10: 0 | T10: 1 | U10: 1 | V10: 0 | W10: 2 | X10: 2 | Y10: – | Z10: 1 | AA10: 0 | AB10: 1 | AC10: 1 | AD10: 1 | AE10: 2 | AF10: 2 | AG10: 1 | AH10: 2 | AI10: 1 | AJ10: 1 | AK10: 1 | AL10: 3 | AM10: 0 | AN10: 2 | AO10: 2 | AP10: – | AQ10: 2 | AR10: 2 | AS10: 1 | AT10: 0 | AU10: 2 | AV10: – | AW10: – | AX10: 3 | AY10: – | AZ10: 3 | BA10: 1 | BB10: 2 | BC10: 2 | BD10: 2 | BE10: 2 | BF10: 0 | BG10: =IFERROR(AVERAGE(I10:Y10),"–") -> 1.25 | BH10: =IFERROR(AVERAGE(Z10:AM10),"–") -> 1.2142857 | BI10: =IFERROR(AVERAGE(AN10:AY10),"–") -> 1.75 | BJ10: =IFERROR(AVERAGE(AZ10:BA10),"–") -> 2 | BK10: =IFERROR(AVERAGE(BB10:BF10),"–") -> 1.6 | BL10: =IFERROR(AVERAGE(I10:BF10),"–") -> 1.4 | BM10: =COUNTIF(I10:BF10,0) -> 6
A11: Canne à sucre et canne fibre | B11: CS_SBT_NIM | C11: Canne à sucre : Sud-Est Basse-Terre, pluvial, récolte mécanisée | D11: 318.7 | E11: AqYield / AqYieldNC | F11: plantation de 3 ans | G11: 0.21 | I11: 1 | J11: 2 | K11: 2 | L11: 1 | M11: 1 | N11: 1 | O11: 1 | P11: 1 | Q11: 3 | R11: 1 | S11: 0 | T11: 1 | U11: 1 | V11: 0 | W11: 2 | X11: 2 | Y11: – | Z11: 1 | AA11: 0 | AB11: 1 | AC11: 1 | AD11: 1 | AE11: 2 | AF11: 2 | AG11: 1 | AH11: 2 | AI11: 1 | AJ11: 1 | AK11: 1 | AL11: 3 | AM11: 0 | AN11: 2 | AO11: 2 | AP11: – | AQ11: 2 | AR11: 2 | AS11: 1 | AT11: 0 | AU11: 2 | AV11: – | AW11: – | AX11: 3 | AY11: – | AZ11: 3 | BA11: 1 | BB11: 2 | BC11: 2 | BD11: 2 | BE11: 2 | BF11: 0 | BG11: =IFERROR(AVERAGE(I11:Y11),"–") -> 1.25 | BH11: =IFERROR(AVERAGE(Z11:AM11),"–") -> 1.2142857 | BI11: =IFERROR(AVERAGE(AN11:AY11),"–") -> 1.75 | BJ11: =IFERROR(AVERAGE(AZ11:BA11),"–") -> 2 | BK11: =IFERROR(AVERAGE(BB11:BF11),"–") -> 1.6 | BL11: =IFERROR(AVERAGE(I11:BF11),"–") -> 1.4 | BM11: =COUNTIF(I11:BF11,0) -> 6
A12: Canne à sucre et canne fibre | B12: CS_EGT_NISM | C12: Canne à sucre : Est Grande-Terre, pluvial, récolte semi-mécanisée | D12: 186.2 | E12: AqYield / AqYieldNC | F12: plantation de 7 ans | G12: 0.12 | I12: 1 | J12: 2 | K12: 2 | L12: 1 | M12: 1 | N12: 1 | O12: 1 | P12: 1 | Q12: 3 | R12: 1 | S12: 0 | T12: 1 | U12: 1 | V12: 0 | W12: 2 | X12: 2 | Y12: – | Z12: 1 | AA12: 0 | AB12: 1 | AC12: 1 | AD12: 1 | AE12: 2 | AF12: 2 | AG12: 1 | AH12: 2 | AI12: 1 | AJ12: 1 | AK12: 1 | AL12: 3 | AM12: 0 | AN12: 2 | AO12: 2 | AP12: – | AQ12: 2 | AR12: 2 | AS12: 1 | AT12: 0 | AU12: 2 | AV12: – | AW12: – | AX12: 3 | AY12: – | AZ12: 3 | BA12: 1 | BB12: 2 | BC12: 2 | BD12: 2 | BE12: 2 | BF12: 0 | BG12: =IFERROR(AVERAGE(I12:Y12),"–") -> 1.25 | BH12: =IFERROR(AVERAGE(Z12:AM12),"–") -> 1.2142857 | BI12: =IFERROR(AVERAGE(AN12:AY12),"–") -> 1.75 | BJ12: =IFERROR(AVERAGE(AZ12:BA12),"–") -> 2 | BK12: =IFERROR(AVERAGE(BB12:BF12),"–") -> 1.6 | BL12: =IFERROR(AVERAGE(I12:BF12),"–") -> 1.4 | BM12: =COUNTIF(I12:BF12,0) -> 6
A13: Canne à sucre et canne fibre | B13: CS_BT_NISM | C13: Canne à sucre : Basse-Terre, pluvial, récolte semi-mécanisée | D13: 12.3 | E13: AqYield / AqYieldNC | F13: plantation de 7 ans | G13: 0.12 | I13: 1 | J13: 2 | K13: 2 | L13: 1 | M13: 1 | N13: 1 | O13: 1 | P13: 1 | Q13: 3 | R13: 1 | S13: 0 | T13: 1 | U13: 1 | V13: 0 | W13: 2 | X13: 2 | Y13: – | Z13: 1 | AA13: 0 | AB13: 1 | AC13: 1 | AD13: 1 | AE13: 2 | AF13: 2 | AG13: 1 | AH13: 2 | AI13: 1 | AJ13: 1 | AK13: 1 | AL13: 3 | AM13: 0 | AN13: 2 | AO13: 2 | AP13: – | AQ13: 2 | AR13: 2 | AS13: 1 | AT13: 0 | AU13: 2 | AV13: – | AW13: – | AX13: 3 | AY13: – | AZ13: 3 | BA13: 1 | BB13: 2 | BC13: 2 | BD13: 2 | BE13: 2 | BF13: 0 | BG13: =IFERROR(AVERAGE(I13:Y13),"–") -> 1.25 | BH13: =IFERROR(AVERAGE(Z13:AM13),"–") -> 1.2142857 | BI13: =IFERROR(AVERAGE(AN13:AY13),"–") -> 1.75 | BJ13: =IFERROR(AVERAGE(AZ13:BA13),"–") -> 2 | BK13: =IFERROR(AVERAGE(BB13:BF13),"–") -> 1.6 | BL13: =IFERROR(AVERAGE(I13:BF13),"–") -> 1.4 | BM13: =COUNTIF(I13:BF13,0) -> 6
A14: Canne à sucre et canne fibre | B14: CS_CGT_NISM | C14: Canne à sucre : Centre Grande-Terre, pluvial, récolte semi-mécanisée | D14: 2.1 | E14: AqYield / AqYieldNC | F14: plantation de 7 ans | G14: 0.12 | I14: 1 | J14: 2 | K14: 2 | L14: 1 | M14: 1 | N14: 1 | O14: 1 | P14: 1 | Q14: 3 | R14: 1 | S14: 0 | T14: 1 | U14: 1 | V14: 0 | W14: 2 | X14: 2 | Y14: – | Z14: 1 | AA14: 0 | AB14: 1 | AC14: 1 | AD14: 1 | AE14: 2 | AF14: 2 | AG14: 1 | AH14: 2 | AI14: 1 | AJ14: 1 | AK14: 1 | AL14: 3 | AM14: 0 | AN14: 2 | AO14: 2 | AP14: – | AQ14: 2 | AR14: 2 | AS14: 1 | AT14: 0 | AU14: 2 | AV14: – | AW14: – | AX14: 3 | AY14: – | AZ14: 3 | BA14: 1 | BB14: 2 | BC14: 2 | BD14: 2 | BE14: 2 | BF14: 0 | BG14: =IFERROR(AVERAGE(I14:Y14),"–") -> 1.25 | BH14: =IFERROR(AVERAGE(Z14:AM14),"–") -> 1.2142857 | BI14: =IFERROR(AVERAGE(AN14:AY14),"–") -> 1.75 | BJ14: =IFERROR(AVERAGE(AZ14:BA14),"–") -> 2 | BK14: =IFERROR(AVERAGE(BB14:BF14),"–") -> 1.6 | BL14: =IFERROR(AVERAGE(I14:BF14),"–") -> 1.4 | BM14: =COUNTIF(I14:BF14,0) -> 6
A15: Canne à sucre et canne fibre | B15: CF_CGT_NIM | C15: Canne fibre : Centre Grande-Terre, pluvial, récolte mécanisée | D15: 0 | E15: AqYield / AqYieldNC | F15: plantation de 6 ans | G15: 0.14 | I15: 1 | J15: 2 | K15: 2 | L15: 1 | M15: 1 | N15: 1 | O15: 1 | P15: 1 | Q15: 3 | R15: 1 | S15: 0 | T15: 1 | U15: 1 | V15: 0 | W15: 2 | X15: 2 | Y15: – | Z15: 1 | AA15: 0 | AB15: 1 | AC15: 1 | AD15: 1 | AE15: 2 | AF15: 2 | AG15: 1 | AH15: 2 | AI15: 1 | AJ15: 1 | AK15: 1 | AL15: 3 | AM15: 0 | AN15: 2 | AO15: 2 | AP15: – | AQ15: 2 | AR15: 2 | AS15: 1 | AT15: 0 | AU15: 2 | AV15: – | AW15: – | AX15: 3 | AY15: – | AZ15: 3 | BA15: 1 | BB15: 1 | BC15: 2 | BD15: 2 | BE15: 2 | BF15: 0 | BG15: =IFERROR(AVERAGE(I15:Y15),"–") -> 1.25 | BH15: =IFERROR(AVERAGE(Z15:AM15),"–") -> 1.2142857 | BI15: =IFERROR(AVERAGE(AN15:AY15),"–") -> 1.75 | BJ15: =IFERROR(AVERAGE(AZ15:BA15),"–") -> 2 | BK15: =IFERROR(AVERAGE(BB15:BF15),"–") -> 1.4 | BL15: =IFERROR(AVERAGE(I15:BF15),"–") -> 1.3777778 | BM15: =COUNTIF(I15:BF15,0) -> 6
A16: Canne à sucre et canne fibre | B16: CF_CGT_NISM | C16: Canne fibre : Centre Grande-Terre, pluvial, récolte semi-mécanisée | D16: 0 | E16: AqYield / AqYieldNC | F16: plantation de 6 ans | G16: 0.14 | I16: 1 | J16: 2 | K16: 2 | L16: 1 | M16: 1 | N16: 1 | O16: 1 | P16: 1 | Q16: 3 | R16: 1 | S16: 0 | T16: 1 | U16: 1 | V16: 0 | W16: 2 | X16: 2 | Y16: – | Z16: 1 | AA16: 0 | AB16: 1 | AC16: 1 | AD16: 1 | AE16: 2 | AF16: 2 | AG16: 1 | AH16: 2 | AI16: 1 | AJ16: 1 | AK16: 1 | AL16: 3 | AM16: 0 | AN16: 2 | AO16: 2 | AP16: – | AQ16: 2 | AR16: 2 | AS16: 1 | AT16: 0 | AU16: 2 | AV16: – | AW16: – | AX16: 3 | AY16: – | AZ16: 3 | BA16: 1 | BB16: 1 | BC16: 2 | BD16: 2 | BE16: 2 | BF16: 0 | BG16: =IFERROR(AVERAGE(I16:Y16),"–") -> 1.25 | BH16: =IFERROR(AVERAGE(Z16:AM16),"–") -> 1.2142857 | BI16: =IFERROR(AVERAGE(AN16:AY16),"–") -> 1.75 | BJ16: =IFERROR(AVERAGE(AZ16:BA16),"–") -> 2 | BK16: =IFERROR(AVERAGE(BB16:BF16),"–") -> 1.4 | BL16: =IFERROR(AVERAGE(I16:BF16),"–") -> 1.3777778 | BM16: =COUNTIF(I16:BF16,0) -> 6
A17: Canne à sucre et canne fibre | B17: CF_EGT_NIM | C17: Canne fibre : Est Grande-Terre, pluvial, récolte mécanisée | D17: 0 | E17: AqYield / AqYieldNC | F17: plantation de 6 ans | G17: 0.14 | H17: 2 récoltes (max 1) | I17: 1 | J17: 2 | K17: 2 | L17: 1 | M17: 1 | N17: 1 | O17: 1 | P17: 1 | Q17: 3 | R17: 1 | S17: 0 | T17: 1 | U17: 1 | V17: 0 | W17: 2 | X17: 2 | Y17: – | Z17: 1 | AA17: 0 | AB17: 1 | AC17: 1 | AD17: 1 | AE17: 2 | AF17: 2 | AG17: 1 | AH17: 2 | AI17: 1 | AJ17: 1 | AK17: 1 | AL17: 3 | AM17: 0 | AN17: 2 | AO17: 2 | AP17: – | AQ17: 2 | AR17: 2 | AS17: 1 | AT17: 0 | AU17: 2 | AV17: – | AW17: – | AX17: 3 | AY17: – | AZ17: 3 | BA17: 1 | BB17: 1 | BC17: 2 | BD17: 2 | BE17: 2 | BF17: 0 | BG17: =IFERROR(AVERAGE(I17:Y17),"–") -> 1.25 | BH17: =IFERROR(AVERAGE(Z17:AM17),"–") -> 1.2142857 | BI17: =IFERROR(AVERAGE(AN17:AY17),"–") -> 1.75 | BJ17: =IFERROR(AVERAGE(AZ17:BA17),"–") -> 2 | BK17: =IFERROR(AVERAGE(BB17:BF17),"–") -> 1.4 | BL17: =IFERROR(AVERAGE(I17:BF17),"–") -> 1.3777778 | BM17: =COUNTIF(I17:BF17,0) -> 6
A18: Canne à sucre et canne fibre | B18: CF_EGT_NISM | C18: Canne fibre : Est Grande-Terre, pluvial, récolte semi-mécanisée | D18: 0 | E18: AqYield / AqYieldNC | F18: plantation de 6 ans | G18: 0.14 | H18: 2 récoltes (max 1) | I18: 1 | J18: 2 | K18: 2 | L18: 1 | M18: 1 | N18: 1 | O18: 1 | P18: 1 | Q18: 3 | R18: 1 | S18: 0 | T18: 1 | U18: 1 | V18: 0 | W18: 2 | X18: 2 | Y18: – | Z18: 1 | AA18: 0 | AB18: 1 | AC18: 1 | AD18: 1 | AE18: 2 | AF18: 2 | AG18: 1 | AH18: 2 | AI18: 1 | AJ18: 1 | AK18: 1 | AL18: 3 | AM18: 0 | AN18: 2 | AO18: 2 | AP18: – | AQ18: 2 | AR18: 2 | AS18: 1 | AT18: 0 | AU18: 2 | AV18: – | AW18: – | AX18: 3 | AY18: – | AZ18: 3 | BA18: 1 | BB18: 1 | BC18: 2 | BD18: 2 | BE18: 2 | BF18: 0 | BG18: =IFERROR(AVERAGE(I18:Y18),"–") -> 1.25 | BH18: =IFERROR(AVERAGE(Z18:AM18),"–") -> 1.2142857 | BI18: =IFERROR(AVERAGE(AN18:AY18),"–") -> 1.75 | BJ18: =IFERROR(AVERAGE(AZ18:BA18),"–") -> 2 | BK18: =IFERROR(AVERAGE(BB18:BF18),"–") -> 1.4 | BL18: =IFERROR(AVERAGE(I18:BF18),"–") -> 1.3777778 | BM18: =COUNTIF(I18:BF18,0) -> 6
A19: Canne à sucre et canne fibre | B19: CF_NBT_NIM | C19: Canne fibre : Nord Basse-Terre, pluvial, récolte mécanisée | D19: 0 | E19: AqYield / AqYieldNC | F19: plantation de 6 ans | G19: 0.14 | I19: 1 | J19: 2 | K19: 2 | L19: 1 | M19: 1 | N19: 1 | O19: 1 | P19: 1 | Q19: 3 | R19: 1 | S19: 0 | T19: 1 | U19: 1 | V19: 0 | W19: 2 | X19: 2 | Y19: – | Z19: 1 | AA19: 0 | AB19: 1 | AC19: 1 | AD19: 1 | AE19: 2 | AF19: 2 | AG19: 1 | AH19: 2 | AI19: 1 | AJ19: 1 | AK19: 1 | AL19: 3 | AM19: 0 | AN19: 2 | AO19: 2 | AP19: – | AQ19: 2 | AR19: 2 | AS19: 1 | AT19: 0 | AU19: 2 | AV19: – | AW19: – | AX19: 3 | AY19: – | AZ19: 3 | BA19: 1 | BB19: 1 | BC19: 2 | BD19: 2 | BE19: 2 | BF19: 0 | BG19: =IFERROR(AVERAGE(I19:Y19),"–") -> 1.25 | BH19: =IFERROR(AVERAGE(Z19:AM19),"–") -> 1.2142857 | BI19: =IFERROR(AVERAGE(AN19:AY19),"–") -> 1.75 | BJ19: =IFERROR(AVERAGE(AZ19:BA19),"–") -> 2 | BK19: =IFERROR(AVERAGE(BB19:BF19),"–") -> 1.4 | BL19: =IFERROR(AVERAGE(I19:BF19),"–") -> 1.3777778 | BM19: =COUNTIF(I19:BF19,0) -> 6
A20: Canne à sucre et canne fibre | B20: CF_NBT_NISM | C20: Canne fibre : Nord Basse-Terre, pluvial, récolte semi-mécanisée | D20: 0 | E20: AqYield / AqYieldNC | F20: plantation de 6 ans | G20: 0.14 | I20: 1 | J20: 2 | K20: 2 | L20: 1 | M20: 1 | N20: 1 | O20: 1 | P20: 1 | Q20: 3 | R20: 1 | S20: 0 | T20: 1 | U20: 1 | V20: 0 | W20: 2 | X20: 2 | Y20: – | Z20: 1 | AA20: 0 | AB20: 1 | AC20: 1 | AD20: 1 | AE20: 2 | AF20: 2 | AG20: 1 | AH20: 2 | AI20: 1 | AJ20: 1 | AK20: 1 | AL20: 3 | AM20: 0 | AN20: 2 | AO20: 2 | AP20: – | AQ20: 2 | AR20: 2 | AS20: 1 | AT20: 0 | AU20: 2 | AV20: – | AW20: – | AX20: 3 | AY20: – | AZ20: 3 | BA20: 1 | BB20: 1 | BC20: 2 | BD20: 2 | BE20: 2 | BF20: 0 | BG20: =IFERROR(AVERAGE(I20:Y20),"–") -> 1.25 | BH20: =IFERROR(AVERAGE(Z20:AM20),"–") -> 1.2142857 | BI20: =IFERROR(AVERAGE(AN20:AY20),"–") -> 1.75 | BJ20: =IFERROR(AVERAGE(AZ20:BA20),"–") -> 2 | BK20: =IFERROR(AVERAGE(BB20:BF20),"–") -> 1.4 | BL20: =IFERROR(AVERAGE(I20:BF20),"–") -> 1.3777778 | BM20: =COUNTIF(I20:BF20,0) -> 6
A21: Canne à sucre et canne fibre | B21: CF_NGT_NIM | C21: Canne fibre : Nord Grande-Terre, pluvial, récolte mécanisée | D21: 0 | E21: AqYield / AqYieldNC | F21: plantation de 6 ans | G21: 0.14 | H21: 2 récoltes (max 1) | I21: 1 | J21: 2 | K21: 2 | L21: 1 | M21: 1 | N21: 1 | O21: 1 | P21: 1 | Q21: 3 | R21: 1 | S21: 0 | T21: 1 | U21: 1 | V21: 0 | W21: 2 | X21: 2 | Y21: – | Z21: 1 | AA21: 0 | AB21: 1 | AC21: 1 | AD21: 1 | AE21: 2 | AF21: 2 | AG21: 1 | AH21: 2 | AI21: 1 | AJ21: 1 | AK21: 1 | AL21: 3 | AM21: 0 | AN21: 2 | AO21: 2 | AP21: – | AQ21: 2 | AR21: 2 | AS21: 1 | AT21: 0 | AU21: 2 | AV21: – | AW21: – | AX21: 3 | AY21: – | AZ21: 3 | BA21: 1 | BB21: 1 | BC21: 2 | BD21: 2 | BE21: 2 | BF21: 0 | BG21: =IFERROR(AVERAGE(I21:Y21),"–") -> 1.25 | BH21: =IFERROR(AVERAGE(Z21:AM21),"–") -> 1.2142857 | BI21: =IFERROR(AVERAGE(AN21:AY21),"–") -> 1.75 | BJ21: =IFERROR(AVERAGE(AZ21:BA21),"–") -> 2 | BK21: =IFERROR(AVERAGE(BB21:BF21),"–") -> 1.4 | BL21: =IFERROR(AVERAGE(I21:BF21),"–") -> 1.3777778 | BM21: =COUNTIF(I21:BF21,0) -> 6
A22: Canne à sucre et canne fibre | B22: CF_NGT_NISM | C22: Canne fibre : Nord Grande-Terre, pluvial, récolte semi-mécanisée | D22: 0 | E22: AqYield / AqYieldNC | F22: plantation de 6 ans | G22: 0.14 | H22: 2 récoltes (max 1) | I22: 1 | J22: 2 | K22: 2 | L22: 1 | M22: 1 | N22: 1 | O22: 1 | P22: 1 | Q22: 3 | R22: 1 | S22: 0 | T22: 1 | U22: 1 | V22: 0 | W22: 2 | X22: 2 | Y22: – | Z22: 1 | AA22: 0 | AB22: 1 | AC22: 1 | AD22: 1 | AE22: 2 | AF22: 2 | AG22: 1 | AH22: 2 | AI22: 1 | AJ22: 1 | AK22: 1 | AL22: 3 | AM22: 0 | AN22: 2 | AO22: 2 | AP22: – | AQ22: 2 | AR22: 2 | AS22: 1 | AT22: 0 | AU22: 2 | AV22: – | AW22: – | AX22: 3 | AY22: – | AZ22: 3 | BA22: 1 | BB22: 1 | BC22: 2 | BD22: 2 | BE22: 2 | BF22: 0 | BG22: =IFERROR(AVERAGE(I22:Y22),"–") -> 1.25 | BH22: =IFERROR(AVERAGE(Z22:AM22),"–") -> 1.2142857 | BI22: =IFERROR(AVERAGE(AN22:AY22),"–") -> 1.75 | BJ22: =IFERROR(AVERAGE(AZ22:BA22),"–") -> 2 | BK22: =IFERROR(AVERAGE(BB22:BF22),"–") -> 1.4 | BL22: =IFERROR(AVERAGE(I22:BF22),"–") -> 1.3777778 | BM22: =COUNTIF(I22:BF22,0) -> 6
A23: Canne à sucre et canne fibre | B23: CF_SBT_NIM | C23: Canne fibre : Sud Basse-Terre, pluvial, récolte mécanisée | D23: 0 | E23: AqYield / AqYieldNC | F23: plantation de 6 ans | G23: 0.14 | I23: 1 | J23: 2 | K23: 2 | L23: 1 | M23: 1 | N23: 1 | O23: 1 | P23: 1 | Q23: 3 | R23: 1 | S23: 0 | T23: 1 | U23: 1 | V23: 0 | W23: 2 | X23: 2 | Y23: – | Z23: 1 | AA23: 0 | AB23: 1 | AC23: 1 | AD23: 1 | AE23: 2 | AF23: 2 | AG23: 1 | AH23: 2 | AI23: 1 | AJ23: 1 | AK23: 1 | AL23: 3 | AM23: 0 | AN23: 2 | AO23: 2 | AP23: – | AQ23: 2 | AR23: 2 | AS23: 1 | AT23: 0 | AU23: 2 | AV23: – | AW23: – | AX23: 3 | AY23: – | AZ23: 3 | BA23: 1 | BB23: 1 | BC23: 2 | BD23: 2 | BE23: 2 | BF23: 0 | BG23: =IFERROR(AVERAGE(I23:Y23),"–") -> 1.25 | BH23: =IFERROR(AVERAGE(Z23:AM23),"–") -> 1.2142857 | BI23: =IFERROR(AVERAGE(AN23:AY23),"–") -> 1.75 | BJ23: =IFERROR(AVERAGE(AZ23:BA23),"–") -> 2 | BK23: =IFERROR(AVERAGE(BB23:BF23),"–") -> 1.4 | BL23: =IFERROR(AVERAGE(I23:BF23),"–") -> 1.3777778 | BM23: =COUNTIF(I23:BF23,0) -> 6
A24: Canne à sucre et canne fibre | B24: CF_SBT_NISM | C24: Canne fibre : Sud Basse-Terre, pluvial, récolte semi-mécanisée | D24: 0 | E24: AqYield / AqYieldNC | F24: plantation de 6 ans | G24: 0.14 | I24: 1 | J24: 2 | K24: 2 | L24: 1 | M24: 1 | N24: 1 | O24: 1 | P24: 1 | Q24: 3 | R24: 1 | S24: 0 | T24: 1 | U24: 1 | V24: 0 | W24: 2 | X24: 2 | Y24: – | Z24: 1 | AA24: 0 | AB24: 1 | AC24: 1 | AD24: 1 | AE24: 2 | AF24: 2 | AG24: 1 | AH24: 2 | AI24: 1 | AJ24: 1 | AK24: 1 | AL24: 3 | AM24: 0 | AN24: 2 | AO24: 2 | AP24: – | AQ24: 2 | AR24: 2 | AS24: 1 | AT24: 0 | AU24: 2 | AV24: – | AW24: – | AX24: 3 | AY24: – | AZ24: 3 | BA24: 1 | BB24: 1 | BC24: 2 | BD24: 2 | BE24: 2 | BF24: 0 | BG24: =IFERROR(AVERAGE(I24:Y24),"–") -> 1.25 | BH24: =IFERROR(AVERAGE(Z24:AM24),"–") -> 1.2142857 | BI24: =IFERROR(AVERAGE(AN24:AY24),"–") -> 1.75 | BJ24: =IFERROR(AVERAGE(AZ24:BA24),"–") -> 2 | BK24: =IFERROR(AVERAGE(BB24:BF24),"–") -> 1.4 | BL24: =IFERROR(AVERAGE(I24:BF24),"–") -> 1.3777778 | BM24: =COUNTIF(I24:BF24,0) -> 6
A25: Canne à sucre et canne fibre | B25: CS_BT_IM | C25: Canne à sucre : Basse-Terre, irrigué, récolte mécanisée | D25: 0 | E25: AqYield / AqYieldNC | F25: plantation de 7 ans | G25: 0.22 | I25: 1 | J25: 2 | K25: 2 | L25: 1 | M25: 1 | N25: 1 | O25: 1 | P25: 1 | Q25: 3 | R25: 1 | S25: 0 | T25: 1 | U25: 1 | V25: 0 | W25: 2 | X25: 2 | Y25: – | Z25: 1 | AA25: 0 | AB25: 1 | AC25: 1 | AD25: 1 | AE25: 2 | AF25: 2 | AG25: 1 | AH25: 2 | AI25: 1 | AJ25: 1 | AK25: 1 | AL25: 3 | AM25: 0 | AN25: 2 | AO25: 2 | AP25: 1 | AQ25: 2 | AR25: 2 | AS25: 1 | AT25: 0 | AU25: 2 | AV25: 1 | AW25: 0 | AX25: 3 | AY25: – | AZ25: 3 | BA25: 1 | BB25: 2 | BC25: 2 | BD25: 2 | BE25: 2 | BF25: 0 | BG25: =IFERROR(AVERAGE(I25:Y25),"–") -> 1.25 | BH25: =IFERROR(AVERAGE(Z25:AM25),"–") -> 1.2142857 | BI25: =IFERROR(AVERAGE(AN25:AY25),"–") -> 1.4545455 | BJ25: =IFERROR(AVERAGE(AZ25:BA25),"–") -> 2 | BK25: =IFERROR(AVERAGE(BB25:BF25),"–") -> 1.6 | BL25: =IFERROR(AVERAGE(I25:BF25),"–") -> 1.3541667 | BM25: =COUNTIF(I25:BF25,0) -> 7
A26: Canne à sucre et canne fibre | B26: CS_CGT_IM | C26: Canne à sucre : Centre Grande-Terre, irrigué, récolte mécanisée | D26: 0 | E26: AqYield / AqYieldNC | F26: plantation de 7 ans | G26: 0.1 | I26: 1 | J26: 2 | K26: 2 | L26: 1 | M26: 1 | N26: 1 | O26: 1 | P26: 1 | Q26: 3 | R26: 1 | S26: 0 | T26: 1 | U26: 1 | V26: 0 | W26: 2 | X26: 2 | Y26: – | Z26: 1 | AA26: 0 | AB26: 1 | AC26: 1 | AD26: 1 | AE26: 2 | AF26: 2 | AG26: 1 | AH26: 2 | AI26: 1 | AJ26: 1 | AK26: 1 | AL26: 3 | AM26: 0 | AN26: 2 | AO26: 2 | AP26: 1 | AQ26: 2 | AR26: 3 | AS26: 1 | AT26: 0 | AU26: 2 | AV26: 1 | AW26: 0 | AX26: 3 | AY26: – | AZ26: 3 | BA26: 1 | BB26: 2 | BC26: 2 | BD26: 2 | BE26: 2 | BF26: 0 | BG26: =IFERROR(AVERAGE(I26:Y26),"–") -> 1.25 | BH26: =IFERROR(AVERAGE(Z26:AM26),"–") -> 1.2142857 | BI26: =IFERROR(AVERAGE(AN26:AY26),"–") -> 1.5454545 | BJ26: =IFERROR(AVERAGE(AZ26:BA26),"–") -> 2 | BK26: =IFERROR(AVERAGE(BB26:BF26),"–") -> 1.6 | BL26: =IFERROR(AVERAGE(I26:BF26),"–") -> 1.375 | BM26: =COUNTIF(I26:BF26,0) -> 7
A27: Canne à sucre et canne fibre | B27: CS_EGT_IM | C27: Canne à sucre : Est Grande-Terre, irrigué, récolte mécanisée | D27: 0 | E27: AqYield / AqYieldNC | F27: plantation de 7 ans | G27: 0.1 | I27: 1 | J27: 2 | K27: 2 | L27: 1 | M27: 1 | N27: 1 | O27: 1 | P27: 1 | Q27: 3 | R27: 1 | S27: 0 | T27: 1 | U27: 1 | V27: 0 | W27: 2 | X27: 2 | Y27: – | Z27: 1 | AA27: 0 | AB27: 1 | AC27: 1 | AD27: 1 | AE27: 2 | AF27: 2 | AG27: 1 | AH27: 2 | AI27: 1 | AJ27: 1 | AK27: 1 | AL27: 3 | AM27: 0 | AN27: 2 | AO27: 2 | AP27: 1 | AQ27: 2 | AR27: 3 | AS27: 1 | AT27: 0 | AU27: 2 | AV27: 1 | AW27: 0 | AX27: 3 | AY27: – | AZ27: 3 | BA27: 1 | BB27: 2 | BC27: 2 | BD27: 2 | BE27: 2 | BF27: 0 | BG27: =IFERROR(AVERAGE(I27:Y27),"–") -> 1.25 | BH27: =IFERROR(AVERAGE(Z27:AM27),"–") -> 1.2142857 | BI27: =IFERROR(AVERAGE(AN27:AY27),"–") -> 1.5454545 | BJ27: =IFERROR(AVERAGE(AZ27:BA27),"–") -> 2 | BK27: =IFERROR(AVERAGE(BB27:BF27),"–") -> 1.6 | BL27: =IFERROR(AVERAGE(I27:BF27),"–") -> 1.375 | BM27: =COUNTIF(I27:BF27,0) -> 7
A28: Canne à sucre et canne fibre | B28: CS_MG_IM | C28: Canne à sucre : Marie-Galante, irrigué, récolte mécanisée | D28: 0 | E28: AqYield / AqYieldNC | F28: plantation de 7 ans | G28: 0.1 | I28: 1 | J28: 2 | K28: 1 | L28: 1 | M28: 1 | N28: 1 | O28: 1 | P28: 1 | Q28: 3 | R28: 1 | S28: 0 | T28: 1 | U28: 1 | V28: 0 | W28: 2 | X28: 2 | Y28: – | Z28: 1 | AA28: 0 | AB28: 1 | AC28: 1 | AD28: 1 | AE28: 2 | AF28: 2 | AG28: 1 | AH28: 2 | AI28: 1 | AJ28: 1 | AK28: 1 | AL28: 3 | AM28: 0 | AN28: 2 | AO28: 2 | AP28: 1 | AQ28: 2 | AR28: 3 | AS28: 1 | AT28: 0 | AU28: 2 | AV28: 1 | AW28: 0 | AX28: 3 | AY28: – | AZ28: 3 | BA28: 1 | BB28: 2 | BC28: 2 | BD28: 2 | BE28: 2 | BF28: 0 | BG28: =IFERROR(AVERAGE(I28:Y28),"–") -> 1.1875 | BH28: =IFERROR(AVERAGE(Z28:AM28),"–") -> 1.2142857 | BI28: =IFERROR(AVERAGE(AN28:AY28),"–") -> 1.5454545 | BJ28: =IFERROR(AVERAGE(AZ28:BA28),"–") -> 2 | BK28: =IFERROR(AVERAGE(BB28:BF28),"–") -> 1.6 | BL28: =IFERROR(AVERAGE(I28:BF28),"–") -> 1.3541667 | BM28: =COUNTIF(I28:BF28,0) -> 7
A29: Canne à sucre et canne fibre | B29: CS_MG_NIM | C29: Canne à sucre : Marie-Galante, pluvial, récolte mécanisée | D29: 0 | E29: AqYield / AqYieldNC | F29: plantation de 7 ans | G29: 0.12 | I29: 1 | J29: 2 | K29: 1 | L29: 1 | M29: 1 | N29: 1 | O29: 1 | P29: 1 | Q29: 3 | R29: 1 | S29: 0 | T29: 1 | U29: 1 | V29: 0 | W29: 2 | X29: 2 | Y29: – | Z29: 1 | AA29: 0 | AB29: 1 | AC29: 1 | AD29: 1 | AE29: 2 | AF29: 2 | AG29: 1 | AH29: 2 | AI29: 1 | AJ29: 1 | AK29: 1 | AL29: 3 | AM29: 0 | AN29: 2 | AO29: 2 | AP29: – | AQ29: 2 | AR29: 2 | AS29: 1 | AT29: 0 | AU29: 2 | AV29: – | AW29: – | AX29: 3 | AY29: – | AZ29: 3 | BA29: 1 | BB29: 2 | BC29: 2 | BD29: 2 | BE29: 2 | BF29: 0 | BG29: =IFERROR(AVERAGE(I29:Y29),"–") -> 1.1875 | BH29: =IFERROR(AVERAGE(Z29:AM29),"–") -> 1.2142857 | BI29: =IFERROR(AVERAGE(AN29:AY29),"–") -> 1.75 | BJ29: =IFERROR(AVERAGE(AZ29:BA29),"–") -> 2 | BK29: =IFERROR(AVERAGE(BB29:BF29),"–") -> 1.6 | BL29: =IFERROR(AVERAGE(I29:BF29),"–") -> 1.3777778 | BM29: =COUNTIF(I29:BF29,0) -> 6
A30: Canne à sucre et canne fibre | B30: CS_NGT_IM | C30: Canne à sucre : Nord Grande-Terre, irrigué, récolte mécanisée | D30: 0 | E30: AqYield / AqYieldNC | F30: plantation de 7 ans | G30: 0.1 | I30: 1 | J30: 2 | K30: 2 | L30: 1 | M30: 1 | N30: 1 | O30: 1 | P30: 1 | Q30: 3 | R30: 1 | S30: 0 | T30: 1 | U30: 1 | V30: 0 | W30: 2 | X30: 2 | Y30: – | Z30: 1 | AA30: 0 | AB30: 1 | AC30: 1 | AD30: 1 | AE30: 2 | AF30: 2 | AG30: 1 | AH30: 2 | AI30: 1 | AJ30: 1 | AK30: 1 | AL30: 3 | AM30: 0 | AN30: 2 | AO30: 2 | AP30: 1 | AQ30: 2 | AR30: 3 | AS30: 1 | AT30: 0 | AU30: 2 | AV30: 1 | AW30: 0 | AX30: 3 | AY30: – | AZ30: 3 | BA30: 1 | BB30: 2 | BC30: 2 | BD30: 2 | BE30: 2 | BF30: 0 | BG30: =IFERROR(AVERAGE(I30:Y30),"–") -> 1.25 | BH30: =IFERROR(AVERAGE(Z30:AM30),"–") -> 1.2142857 | BI30: =IFERROR(AVERAGE(AN30:AY30),"–") -> 1.5454545 | BJ30: =IFERROR(AVERAGE(AZ30:BA30),"–") -> 2 | BK30: =IFERROR(AVERAGE(BB30:BF30),"–") -> 1.6 | BL30: =IFERROR(AVERAGE(I30:BF30),"–") -> 1.375 | BM30: =COUNTIF(I30:BF30,0) -> 7
A31: Canne à sucre et canne fibre | B31: CS_SBT_IM | C31: Canne à sucre : Sud-Est Basse-Terre, irrigué, récolte mécanisée | D31: 0 | E31: AqYield / AqYieldNC | F31: plantation de 3 ans | G31: 0.14 | I31: 1 | J31: 2 | K31: 2 | L31: 1 | M31: 1 | N31: 1 | O31: 1 | P31: 1 | Q31: 3 | R31: 1 | S31: 0 | T31: 1 | U31: 1 | V31: 0 | W31: 2 | X31: 2 | Y31: – | Z31: 1 | AA31: 0 | AB31: 1 | AC31: 1 | AD31: 1 | AE31: 2 | AF31: 2 | AG31: 1 | AH31: 2 | AI31: 1 | AJ31: 1 | AK31: 1 | AL31: 3 | AM31: 0 | AN31: 2 | AO31: 2 | AP31: 1 | AQ31: 2 | AR31: 2 | AS31: 1 | AT31: 0 | AU31: 2 | AV31: 1 | AW31: 0 | AX31: 3 | AY31: – | AZ31: 3 | BA31: 1 | BB31: 2 | BC31: 2 | BD31: 2 | BE31: 2 | BF31: 0 | BG31: =IFERROR(AVERAGE(I31:Y31),"–") -> 1.25 | BH31: =IFERROR(AVERAGE(Z31:AM31),"–") -> 1.2142857 | BI31: =IFERROR(AVERAGE(AN31:AY31),"–") -> 1.4545455 | BJ31: =IFERROR(AVERAGE(AZ31:BA31),"–") -> 2 | BK31: =IFERROR(AVERAGE(BB31:BF31),"–") -> 1.6 | BL31: =IFERROR(AVERAGE(I31:BF31),"–") -> 1.3541667 | BM31: =COUNTIF(I31:BF31,0) -> 7
A32: Canne à sucre et canne fibre | B32: CS_SBT_NISM | C32: Canne à sucre : Sud-Est Basse-Terre, pluvial, récolte semi-mécanisée | D32: 0 | E32: AqYield / AqYieldNC | F32: plantation de 3 ans | G32: 0.21 | I32: 1 | J32: 2 | K32: 2 | L32: 1 | M32: 1 | N32: 1 | O32: 1 | P32: 1 | Q32: 3 | R32: 1 | S32: 0 | T32: 1 | U32: 1 | V32: 0 | W32: 2 | X32: 2 | Y32: – | Z32: 1 | AA32: 0 | AB32: 1 | AC32: 1 | AD32: 1 | AE32: 2 | AF32: 2 | AG32: 1 | AH32: 2 | AI32: 1 | AJ32: 1 | AK32: 1 | AL32: 3 | AM32: 0 | AN32: 2 | AO32: 2 | AP32: – | AQ32: 2 | AR32: 2 | AS32: 1 | AT32: 0 | AU32: 2 | AV32: – | AW32: – | AX32: 3 | AY32: – | AZ32: 3 | BA32: 1 | BB32: 2 | BC32: 2 | BD32: 2 | BE32: 2 | BF32: 0 | BG32: =IFERROR(AVERAGE(I32:Y32),"–") -> 1.25 | BH32: =IFERROR(AVERAGE(Z32:AM32),"–") -> 1.2142857 | BI32: =IFERROR(AVERAGE(AN32:AY32),"–") -> 1.75 | BJ32: =IFERROR(AVERAGE(AZ32:BA32),"–") -> 2 | BK32: =IFERROR(AVERAGE(BB32:BF32),"–") -> 1.6 | BL32: =IFERROR(AVERAGE(I32:BF32),"–") -> 1.4 | BM32: =COUNTIF(I32:BF32,0) -> 6
A33: Banane dessert | B33: BA_INT | C33: Banane : intensif de plaine | D33: 1258.2 | E33: AqYield / AqYieldNC | F33: plantation de 8 ans | G33: 0.82 | H33: 34 récoltes (max 1) ; 12 apports (max 4) | I33: 1 | J33: 2 | K33: 2 | L33: 1 | M33: 1 | N33: 1 | O33: 1 | P33: 1 | Q33: 3 | R33: 1 | S33: 0 | T33: 1 | U33: 1 | V33: 0 | W33: 2 | X33: 2 | Y33: – | Z33: 1 | AA33: 0 | AB33: 1 | AC33: 1 | AD33: 1 | AE33: 2 | AF33: 2 | AG33: 1 | AH33: 2 | AI33: 1 | AJ33: 1 | AK33: 1 | AL33: 3 | AM33: – | AN33: 2 | AO33: 2 | AP33: – | AQ33: 2 | AR33: 1 | AS33: 0 | AT33: 0 | AU33: 2 | AV33: 1 | AW33: 0 | AX33: 3 | AY33: – | AZ33: 3 | BA33: 1 | BB33: 2 | BC33: 2 | BD33: 2 | BE33: 2 | BF33: 0 | BG33: =IFERROR(AVERAGE(I33:Y33),"–") -> 1.25 | BH33: =IFERROR(AVERAGE(Z33:AM33),"–") -> 1.3076923 | BI33: =IFERROR(AVERAGE(AN33:AY33),"–") -> 1.3 | BJ33: =IFERROR(AVERAGE(AZ33:BA33),"–") -> 2 | BK33: =IFERROR(AVERAGE(BB33:BF33),"–") -> 1.6 | BL33: =IFERROR(AVERAGE(I33:BF33),"–") -> 1.3478261 | BM33: =COUNTIF(I33:BF33,0) -> 7
A34: Banane dessert | B34: BA_PER | C34: Banane : extensif d'altitude | D34: 288.7 | E34: AqYield / AqYieldNC | F34: plantation de 15 ans | G34: 0.84 | H34: 8.35 récoltes (max 1) ; 8 apports (max 4) | I34: 1 | J34: 2 | K34: 2 | L34: 1 | M34: 1 | N34: 1 | O34: 1 | P34: 1 | Q34: 3 | R34: 1 | S34: 0 | T34: 1 | U34: 1 | V34: 0 | W34: 2 | X34: 2 | Y34: – | Z34: 1 | AA34: 0 | AB34: 1 | AC34: 1 | AD34: 1 | AE34: 2 | AF34: 2 | AG34: 1 | AH34: 2 | AI34: 1 | AJ34: 1 | AK34: 1 | AL34: 3 | AM34: – | AN34: 2 | AO34: 2 | AP34: – | AQ34: 2 | AR34: 1 | AS34: 0 | AT34: 0 | AU34: 2 | AV34: 1 | AW34: 0 | AX34: 3 | AY34: – | AZ34: 3 | BA34: 1 | BB34: 2 | BC34: 2 | BD34: 2 | BE34: 2 | BF34: 0 | BG34: =IFERROR(AVERAGE(I34:Y34),"–") -> 1.25 | BH34: =IFERROR(AVERAGE(Z34:AM34),"–") -> 1.3076923 | BI34: =IFERROR(AVERAGE(AN34:AY34),"–") -> 1.3 | BJ34: =IFERROR(AVERAGE(AZ34:BA34),"–") -> 2 | BK34: =IFERROR(AVERAGE(BB34:BF34),"–") -> 1.6 | BL34: =IFERROR(AVERAGE(I34:BF34),"–") -> 1.3478261 | BM34: =COUNTIF(I34:BF34,0) -> 7
A35: Banane dessert | B35: BA_SINT | C35: Banane : intensif d'altitude | D35: 204.5 | E35: AqYield / AqYieldNC | F35: plantation de 11 ans | G35: 0.83 | H35: 17 récoltes (max 1) ; 8 apports (max 4) | I35: 1 | J35: 2 | K35: 2 | L35: 1 | M35: 1 | N35: 1 | O35: 1 | P35: 1 | Q35: 3 | R35: 1 | S35: 0 | T35: 1 | U35: 1 | V35: 0 | W35: 2 | X35: 2 | Y35: – | Z35: 1 | AA35: 0 | AB35: 1 | AC35: 1 | AD35: 1 | AE35: 1 | AF35: 2 | AG35: 1 | AH35: 2 | AI35: 1 | AJ35: 1 | AK35: 1 | AL35: 3 | AM35: – | AN35: 2 | AO35: 2 | AP35: – | AQ35: 2 | AR35: 1 | AS35: 0 | AT35: 0 | AU35: 2 | AV35: 1 | AW35: 0 | AX35: 3 | AY35: – | AZ35: 3 | BA35: 1 | BB35: 2 | BC35: 2 | BD35: 2 | BE35: 2 | BF35: 0 | BG35: =IFERROR(AVERAGE(I35:Y35),"–") -> 1.25 | BH35: =IFERROR(AVERAGE(Z35:AM35),"–") -> 1.2307692 | BI35: =IFERROR(AVERAGE(AN35:AY35),"–") -> 1.3 | BJ35: =IFERROR(AVERAGE(AZ35:BA35),"–") -> 2 | BK35: =IFERROR(AVERAGE(BB35:BF35),"–") -> 1.6 | BL35: =IFERROR(AVERAGE(I35:BF35),"–") -> 1.326087 | BM35: =COUNTIF(I35:BF35,0) -> 7
A36: Banane dessert | B36: BA_IRR | C36: Banane : irrigué | D36: 169.4 | E36: AqYield / AqYieldNC | F36: plantation de 11 ans | G36: 0.85 | H36: 17 récoltes (max 1) ; 8 apports (max 4) | I36: 1 | J36: 2 | K36: 2 | L36: 1 | M36: 1 | N36: 1 | O36: 1 | P36: 1 | Q36: 3 | R36: 1 | S36: 0 | T36: 1 | U36: 1 | V36: 0 | W36: 2 | X36: 2 | Y36: – | Z36: 1 | AA36: 0 | AB36: 1 | AC36: 1 | AD36: 1 | AE36: 2 | AF36: 2 | AG36: 1 | AH36: 2 | AI36: 1 | AJ36: 1 | AK36: 1 | AL36: 3 | AM36: – | AN36: 2 | AO36: 2 | AP36: 1 | AQ36: 2 | AR36: 1 | AS36: 0 | AT36: 0 | AU36: 2 | AV36: 2 | AW36: 0 | AX36: 3 | AY36: – | AZ36: 3 | BA36: 1 | BB36: 2 | BC36: 2 | BD36: 2 | BE36: 2 | BF36: 0 | BG36: =IFERROR(AVERAGE(I36:Y36),"–") -> 1.25 | BH36: =IFERROR(AVERAGE(Z36:AM36),"–") -> 1.3076923 | BI36: =IFERROR(AVERAGE(AN36:AY36),"–") -> 1.3636364 | BJ36: =IFERROR(AVERAGE(AZ36:BA36),"–") -> 2 | BK36: =IFERROR(AVERAGE(BB36:BF36),"–") -> 1.6 | BL36: =IFERROR(AVERAGE(I36:BF36),"–") -> 1.3617021 | BM36: =COUNTIF(I36:BF36,0) -> 7
A37: Plantain | B37: BC_BT | C37: Plantain, Basse-Terre | D37: 116.9 | E37: AqYield / AqYieldNC | F37: plantation de 2 ans | G37: 0.34 | H37: 4.5 apports (max 4) ; 36 désherbages (max 5) | I37: 1 | J37: 2 | K37: 2 | L37: 1 | M37: 1 | N37: 1 | O37: 1 | P37: 1 | Q37: 3 | R37: 1 | S37: 0 | T37: 1 | U37: 1 | V37: 0 | W37: 2 | X37: 2 | Y37: – | Z37: 1 | AA37: 0 | AB37: 1 | AC37: 2 | AD37: 1 | AE37: 2 | AF37: 2 | AG37: 1 | AH37: 2 | AI37: 1 | AJ37: 1 | AK37: 1 | AL37: 3 | AM37: – | AN37: 2 | AO37: 2 | AP37: – | AQ37: 2 | AR37: 2 | AS37: 0 | AT37: 0 | AU37: 2 | AV37: 1 | AW37: 0 | AX37: 3 | AY37: – | AZ37: 3 | BA37: 1 | BB37: 2 | BC37: 2 | BD37: 2 | BE37: 2 | BF37: 0 | BG37: =IFERROR(AVERAGE(I37:Y37),"–") -> 1.25 | BH37: =IFERROR(AVERAGE(Z37:AM37),"–") -> 1.3846154 | BI37: =IFERROR(AVERAGE(AN37:AY37),"–") -> 1.4 | BJ37: =IFERROR(AVERAGE(AZ37:BA37),"–") -> 2 | BK37: =IFERROR(AVERAGE(BB37:BF37),"–") -> 1.6 | BL37: =IFERROR(AVERAGE(I37:BF37),"–") -> 1.3913043 | BM37: =COUNTIF(I37:BF37,0) -> 7
A38: Plantain | B38: BC_GTMG | C38: Plantain, Grande-Terre et Marie-Galante | D38: 30.3 | E38: AqYield / AqYieldNC | F38: plantation de 2 ans | G38: 0.33 | H38: 4.5 apports (max 4) ; 36 désherbages (max 5) | I38: 1 | J38: 2 | K38: 2 | L38: 1 | M38: 1 | N38: 1 | O38: 1 | P38: 1 | Q38: 3 | R38: 1 | S38: 0 | T38: 1 | U38: 1 | V38: 0 | W38: 2 | X38: 2 | Y38: – | Z38: 1 | AA38: 0 | AB38: 1 | AC38: 2 | AD38: 1 | AE38: 2 | AF38: 2 | AG38: 1 | AH38: 2 | AI38: 1 | AJ38: 1 | AK38: 1 | AL38: 3 | AM38: – | AN38: 2 | AO38: 2 | AP38: 1 | AQ38: 2 | AR38: 2 | AS38: 0 | AT38: 0 | AU38: 2 | AV38: 2 | AW38: 0 | AX38: 3 | AY38: – | AZ38: 3 | BA38: 1 | BB38: 2 | BC38: 2 | BD38: 2 | BE38: 2 | BF38: 0 | BG38: =IFERROR(AVERAGE(I38:Y38),"–") -> 1.25 | BH38: =IFERROR(AVERAGE(Z38:AM38),"–") -> 1.3846154 | BI38: =IFERROR(AVERAGE(AN38:AY38),"–") -> 1.4545455 | BJ38: =IFERROR(AVERAGE(AZ38:BA38),"–") -> 2 | BK38: =IFERROR(AVERAGE(BB38:BF38),"–") -> 1.6 | BL38: =IFERROR(AVERAGE(I38:BF38),"–") -> 1.4042553 | BM38: =COUNTIF(I38:BF38,0) -> 7
A39: Prairies | B39: PN_PIQ | C39: Prairie naturelle, élevage au piquet | D39: 6109.4 | E39: HerbSim / HerbSimNC | F39: annuelle | G39: 1 | I39: – | J39: – | K39: – | L39: – | M39: – | N39: – | O39: – | P39: – | Q39: – | R39: – | S39: – | T39: – | U39: – | V39: – | W39: – | X39: – | Y39: 0 | Z39: – | AA39: – | AB39: – | AC39: – | AD39: – | AE39: – | AF39: – | AG39: – | AH39: – | AI39: – | AJ39: – | AK39: – | AL39: – | AM39: – | AN39: 2 | AO39: 2 | AP39: – | AQ39: 0 | AR39: 1 | AS39: 0 | AT39: 0 | AU39: – | AV39: – | AW39: – | AX39: – | AY39: 0 | AZ39: – | BA39: – | BB39: 2 | BC39: 2 | BD39: 2 | BE39: 2 | BF39: 0 | BG39: =IFERROR(AVERAGE(I39:Y39),"–") -> 0 | BH39: =IFERROR(AVERAGE(Z39:AM39),"–") -> – | BI39: =IFERROR(AVERAGE(AN39:AY39),"–") -> 0.71428571 | BJ39: =IFERROR(AVERAGE(AZ39:BA39),"–") -> – | BK39: =IFERROR(AVERAGE(BB39:BF39),"–") -> 1.6 | BL39: =IFERROR(AVERAGE(I39:BF39),"–") -> 1 | BM39: =COUNTIF(I39:BF39,0) -> 6
A40: Prairies | B40: PN_TOUR | C40: Prairie naturelle, pâturage tournant | D40: 0 | E40: HerbSim / HerbSimNC | F40: annuelle | G40: 0.88 | I40: – | J40: – | K40: – | L40: – | M40: – | N40: – | O40: – | P40: – | Q40: – | R40: – | S40: – | T40: – | U40: – | V40: – | W40: – | X40: – | Y40: 0 | Z40: – | AA40: – | AB40: – | AC40: – | AD40: – | AE40: – | AF40: – | AG40: – | AH40: – | AI40: – | AJ40: – | AK40: – | AL40: – | AM40: – | AN40: 2 | AO40: 2 | AP40: – | AQ40: 1 | AR40: 1 | AS40: 0 | AT40: 0 | AU40: – | AV40: – | AW40: – | AX40: 3 | AY40: 0 | AZ40: 3 | BA40: 0 | BB40: 2 | BC40: 2 | BD40: 2 | BE40: 2 | BF40: 0 | BG40: =IFERROR(AVERAGE(I40:Y40),"–") -> 0 | BH40: =IFERROR(AVERAGE(Z40:AM40),"–") -> – | BI40: =IFERROR(AVERAGE(AN40:AY40),"–") -> 1.125 | BJ40: =IFERROR(AVERAGE(AZ40:BA40),"–") -> 1.5 | BK40: =IFERROR(AVERAGE(BB40:BF40),"–") -> 1.6 | BL40: =IFERROR(AVERAGE(I40:BF40),"–") -> 1.25 | BM40: =COUNTIF(I40:BF40,0) -> 6
A41: Maraîchage (dont tomate) | B41: MA_ROTA | C41: Maraîchage en rotation | D41: 735.3 | E41: AqYield / AqYieldNC | F41: annuelle | G41: 0.29 | H41: 2 récoltes (max 1) ; 12.5 apports (max 4) ; 14 désherbages (max 5) ; 5.5 préparations du sol (max 4) | I41: 0 | J41: 2 | K41: 2 | L41: 0 | M41: 0 | N41: 0 | O41: 0 | P41: 0 | Q41: 3 | R41: 1 | S41: 0 | T41: 1 | U41: 0 | V41: 0 | W41: 2 | X41: 2 | Y41: – | Z41: 0 | AA41: 0 | AB41: 1 | AC41: 2 | AD41: 1 | AE41: 2 | AF41: 2 | AG41: 1 | AH41: 2 | AI41: 0 | AJ41: 1 | AK41: 1 | AL41: 3 | AM41: – | AN41: 2 | AO41: 2 | AP41: 1 | AQ41: 2 | AR41: 2 | AS41: 0 | AT41: 0 | AU41: 2 | AV41: 2 | AW41: 0 | AX41: 3 | AY41: – | AZ41: 3 | BA41: 0 | BB41: 2 | BC41: 2 | BD41: 2 | BE41: 2 | BF41: 0 | BG41: =IFERROR(AVERAGE(I41:Y41),"–") -> 0.8125 | BH41: =IFERROR(AVERAGE(Z41:AM41),"–") -> 1.2307692 | BI41: =IFERROR(AVERAGE(AN41:AY41),"–") -> 1.4545455 | BJ41: =IFERROR(AVERAGE(AZ41:BA41),"–") -> 1.5 | BK41: =IFERROR(AVERAGE(BB41:BF41),"–") -> 1.6 | BL41: =IFERROR(AVERAGE(I41:BF41),"–") -> 1.1914894 | BM41: =COUNTIF(I41:BF41,0) -> 17
A42: Maraîchage (dont tomate) | B42: MA_TO_CO_JA | C42: Maraîchage plein champ (rotation TO/CO/JA) | D42: 351.7 | E42: AqYield / AqYieldNC | F42: annuelle | G42: 0.49 | I42: 0 | J42: 2 | K42: 2 | L42: 0 | M42: 0 | N42: 0 | O42: 0 | P42: 0 | Q42: 3 | R42: 1 | S42: 0 | T42: 1 | U42: 0 | V42: 0 | W42: 2 | X42: 2 | Y42: – | Z42: 0 | AA42: 0 | AB42: 1 | AC42: 1 | AD42: 1 | AE42: 2 | AF42: 2 | AG42: 1 | AH42: 2 | AI42: 0 | AJ42: 1 | AK42: 1 | AL42: 3 | AM42: – | AN42: 2 | AO42: 2 | AP42: – | AQ42: 2 | AR42: 2 | AS42: 0 | AT42: 0 | AU42: – | AV42: 1 | AW42: 0 | AX42: 3 | AY42: – | AZ42: 3 | BA42: 0 | BB42: 2 | BC42: 2 | BD42: 2 | BE42: 2 | BF42: 0 | BG42: =IFERROR(AVERAGE(I42:Y42),"–") -> 0.8125 | BH42: =IFERROR(AVERAGE(Z42:AM42),"–") -> 1.1538462 | BI42: =IFERROR(AVERAGE(AN42:AY42),"–") -> 1.3333333 | BJ42: =IFERROR(AVERAGE(AZ42:BA42),"–") -> 1.5 | BK42: =IFERROR(AVERAGE(BB42:BF42),"–") -> 1.6 | BL42: =IFERROR(AVERAGE(I42:BF42),"–") -> 1.1333333 | BM42: =COUNTIF(I42:BF42,0) -> 17
A43: Maraîchage (dont tomate) | B43: MA_BAG_BIO_I | C43: Maraîchage plein champ (paillage bagasse, BIO, irrigué) | D43: 0 | E43: AqYield / AqYieldNC | F43: annuelle | G43: 0.49 | I43: 0 | J43: 2 | K43: 2 | L43: 0 | M43: 0 | N43: 0 | O43: 0 | P43: 0 | Q43: 3 | R43: 1 | S43: 0 | T43: 1 | U43: 0 | V43: 0 | W43: 2 | X43: 2 | Y43: – | Z43: 0 | AA43: 0 | AB43: 1 | AC43: 1 | AD43: 1 | AE43: 2 | AF43: 2 | AG43: 1 | AH43: 2 | AI43: 0 | AJ43: 1 | AK43: 1 | AL43: 3 | AM43: – | AN43: 2 | AO43: 2 | AP43: – | AQ43: 2 | AR43: 2 | AS43: 0 | AT43: 0 | AU43: – | AV43: 1 | AW43: 0 | AX43: 3 | AY43: – | AZ43: 3 | BA43: 0 | BB43: 2 | BC43: 2 | BD43: 2 | BE43: 2 | BF43: 0 | BG43: =IFERROR(AVERAGE(I43:Y43),"–") -> 0.8125 | BH43: =IFERROR(AVERAGE(Z43:AM43),"–") -> 1.1538462 | BI43: =IFERROR(AVERAGE(AN43:AY43),"–") -> 1.3333333 | BJ43: =IFERROR(AVERAGE(AZ43:BA43),"–") -> 1.5 | BK43: =IFERROR(AVERAGE(BB43:BF43),"–") -> 1.6 | BL43: =IFERROR(AVERAGE(I43:BF43),"–") -> 1.1333333 | BM43: =COUNTIF(I43:BF43,0) -> 17
A44: Maraîchage (dont tomate) | B44: MA_BAG_BIO_NI | C44: Maraîchage plein champ (paillage bagasse, BIO, pluvial) | D44: 0 | E44: AqYield / AqYieldNC | F44: annuelle | G44: 0.49 | I44: 0 | J44: 2 | K44: 2 | L44: 0 | M44: 0 | N44: 0 | O44: 0 | P44: 0 | Q44: 3 | R44: 1 | S44: 0 | T44: 1 | U44: 0 | V44: 0 | W44: 2 | X44: 2 | Y44: – | Z44: 0 | AA44: 0 | AB44: 1 | AC44: 1 | AD44: 1 | AE44: 2 | AF44: 2 | AG44: 1 | AH44: 2 | AI44: 0 | AJ44: 1 | AK44: 1 | AL44: 3 | AM44: – | AN44: 2 | AO44: 2 | AP44: – | AQ44: 2 | AR44: 2 | AS44: 0 | AT44: 0 | AU44: – | AV44: 1 | AW44: 0 | AX44: 3 | AY44: – | AZ44: 3 | BA44: 0 | BB44: 2 | BC44: 2 | BD44: 2 | BE44: 2 | BF44: 0 | BG44: =IFERROR(AVERAGE(I44:Y44),"–") -> 0.8125 | BH44: =IFERROR(AVERAGE(Z44:AM44),"–") -> 1.1538462 | BI44: =IFERROR(AVERAGE(AN44:AY44),"–") -> 1.3333333 | BJ44: =IFERROR(AVERAGE(AZ44:BA44),"–") -> 1.5 | BK44: =IFERROR(AVERAGE(BB44:BF44),"–") -> 1.6 | BL44: =IFERROR(AVERAGE(I44:BF44),"–") -> 1.1333333 | BM44: =COUNTIF(I44:BF44,0) -> 17
A45: Maraîchage (dont tomate) | B45: MA_BAG_FER_I | C45: Maraîchage plein champ (paillage bagasse, FER, irrigué) | D45: 0 | E45: AqYield / AqYieldNC | F45: annuelle | G45: 0.49 | I45: 0 | J45: 2 | K45: 2 | L45: 0 | M45: 0 | N45: 0 | O45: 0 | P45: 0 | Q45: 3 | R45: 1 | S45: 0 | T45: 1 | U45: 0 | V45: 0 | W45: 2 | X45: 2 | Y45: – | Z45: 0 | AA45: 0 | AB45: 1 | AC45: 1 | AD45: 1 | AE45: 2 | AF45: 2 | AG45: 1 | AH45: 2 | AI45: 0 | AJ45: 1 | AK45: 1 | AL45: 3 | AM45: – | AN45: 2 | AO45: 2 | AP45: – | AQ45: 2 | AR45: 2 | AS45: 0 | AT45: 0 | AU45: – | AV45: 1 | AW45: 0 | AX45: 3 | AY45: – | AZ45: 3 | BA45: 0 | BB45: 2 | BC45: 2 | BD45: 2 | BE45: 2 | BF45: 0 | BG45: =IFERROR(AVERAGE(I45:Y45),"–") -> 0.8125 | BH45: =IFERROR(AVERAGE(Z45:AM45),"–") -> 1.1538462 | BI45: =IFERROR(AVERAGE(AN45:AY45),"–") -> 1.3333333 | BJ45: =IFERROR(AVERAGE(AZ45:BA45),"–") -> 1.5 | BK45: =IFERROR(AVERAGE(BB45:BF45),"–") -> 1.6 | BL45: =IFERROR(AVERAGE(I45:BF45),"–") -> 1.1333333 | BM45: =COUNTIF(I45:BF45,0) -> 17
A46: Maraîchage (dont tomate) | B46: MA_BAG_FER_NI | C46: Maraîchage plein champ (paillage bagasse, FER, pluvial) | D46: 0 | E46: AqYield / AqYieldNC | F46: annuelle | G46: 0.49 | I46: 0 | J46: 2 | K46: 2 | L46: 0 | M46: 0 | N46: 0 | O46: 0 | P46: 0 | Q46: 3 | R46: 1 | S46: 0 | T46: 1 | U46: 0 | V46: 0 | W46: 2 | X46: 2 | Y46: – | Z46: 0 | AA46: 0 | AB46: 1 | AC46: 1 | AD46: 1 | AE46: 2 | AF46: 2 | AG46: 1 | AH46: 2 | AI46: 0 | AJ46: 1 | AK46: 1 | AL46: 3 | AM46: – | AN46: 2 | AO46: 2 | AP46: – | AQ46: 2 | AR46: 2 | AS46: 0 | AT46: 0 | AU46: – | AV46: 1 | AW46: 0 | AX46: 3 | AY46: – | AZ46: 3 | BA46: 0 | BB46: 2 | BC46: 2 | BD46: 2 | BE46: 2 | BF46: 0 | BG46: =IFERROR(AVERAGE(I46:Y46),"–") -> 0.8125 | BH46: =IFERROR(AVERAGE(Z46:AM46),"–") -> 1.1538462 | BI46: =IFERROR(AVERAGE(AN46:AY46),"–") -> 1.3333333 | BJ46: =IFERROR(AVERAGE(AZ46:BA46),"–") -> 1.5 | BK46: =IFERROR(AVERAGE(BB46:BF46),"–") -> 1.6 | BL46: =IFERROR(AVERAGE(I46:BF46),"–") -> 1.1333333 | BM46: =COUNTIF(I46:BF46,0) -> 17
A47: Maraîchage (dont tomate) | B47: MA_BAG_NON_I | C47: Maraîchage plein champ (paillage bagasse, NON, irrigué) | D47: 0 | E47: AqYield / AqYieldNC | F47: annuelle | G47: 0.49 | I47: 0 | J47: 2 | K47: 2 | L47: 0 | M47: 0 | N47: 0 | O47: 0 | P47: 0 | Q47: 3 | R47: 1 | S47: 0 | T47: 1 | U47: 0 | V47: 0 | W47: 2 | X47: 2 | Y47: – | Z47: 0 | AA47: 0 | AB47: 1 | AC47: 1 | AD47: 1 | AE47: 2 | AF47: 2 | AG47: 1 | AH47: 2 | AI47: 0 | AJ47: 1 | AK47: 1 | AL47: 3 | AM47: – | AN47: 2 | AO47: 2 | AP47: – | AQ47: 2 | AR47: 2 | AS47: 0 | AT47: 0 | AU47: – | AV47: 1 | AW47: 0 | AX47: 3 | AY47: – | AZ47: 3 | BA47: 0 | BB47: 2 | BC47: 2 | BD47: 2 | BE47: 2 | BF47: 0 | BG47: =IFERROR(AVERAGE(I47:Y47),"–") -> 0.8125 | BH47: =IFERROR(AVERAGE(Z47:AM47),"–") -> 1.1538462 | BI47: =IFERROR(AVERAGE(AN47:AY47),"–") -> 1.3333333 | BJ47: =IFERROR(AVERAGE(AZ47:BA47),"–") -> 1.5 | BK47: =IFERROR(AVERAGE(BB47:BF47),"–") -> 1.6 | BL47: =IFERROR(AVERAGE(I47:BF47),"–") -> 1.1333333 | BM47: =COUNTIF(I47:BF47,0) -> 17
A48: Maraîchage (dont tomate) | B48: MA_BAG_NON_NI | C48: Maraîchage plein champ (paillage bagasse, NON, pluvial) | D48: 0 | E48: AqYield / AqYieldNC | F48: annuelle | G48: 0.49 | I48: 0 | J48: 2 | K48: 2 | L48: 0 | M48: 0 | N48: 0 | O48: 0 | P48: 0 | Q48: 3 | R48: 1 | S48: 0 | T48: 1 | U48: 0 | V48: 0 | W48: 2 | X48: 2 | Y48: – | Z48: 0 | AA48: 0 | AB48: 1 | AC48: 1 | AD48: 1 | AE48: 2 | AF48: 2 | AG48: 1 | AH48: 2 | AI48: 0 | AJ48: 1 | AK48: 1 | AL48: 3 | AM48: – | AN48: 2 | AO48: 2 | AP48: – | AQ48: 2 | AR48: 2 | AS48: 0 | AT48: 0 | AU48: – | AV48: 1 | AW48: 0 | AX48: 3 | AY48: – | AZ48: 3 | BA48: 0 | BB48: 2 | BC48: 2 | BD48: 2 | BE48: 2 | BF48: 0 | BG48: =IFERROR(AVERAGE(I48:Y48),"–") -> 0.8125 | BH48: =IFERROR(AVERAGE(Z48:AM48),"–") -> 1.1538462 | BI48: =IFERROR(AVERAGE(AN48:AY48),"–") -> 1.3333333 | BJ48: =IFERROR(AVERAGE(AZ48:BA48),"–") -> 1.5 | BK48: =IFERROR(AVERAGE(BB48:BF48),"–") -> 1.6 | BL48: =IFERROR(AVERAGE(I48:BF48),"–") -> 1.1333333 | BM48: =COUNTIF(I48:BF48,0) -> 17
A49: Maraîchage (dont tomate) | B49: MA_BAG_VEG_I | C49: Maraîchage plein champ (paillage bagasse, VEG, irrigué) | D49: 0 | E49: AqYield / AqYieldNC | F49: annuelle | G49: 0.49 | I49: 0 | J49: 2 | K49: 2 | L49: 0 | M49: 0 | N49: 0 | O49: 0 | P49: 0 | Q49: 3 | R49: 1 | S49: 0 | T49: 1 | U49: 0 | V49: 0 | W49: 2 | X49: 2 | Y49: – | Z49: 0 | AA49: 0 | AB49: 1 | AC49: 1 | AD49: 1 | AE49: 2 | AF49: 2 | AG49: 1 | AH49: 2 | AI49: 0 | AJ49: 1 | AK49: 1 | AL49: 3 | AM49: – | AN49: 2 | AO49: 2 | AP49: – | AQ49: 2 | AR49: 2 | AS49: 0 | AT49: 0 | AU49: – | AV49: 1 | AW49: 0 | AX49: 3 | AY49: – | AZ49: 3 | BA49: 0 | BB49: 2 | BC49: 2 | BD49: 2 | BE49: 2 | BF49: 0 | BG49: =IFERROR(AVERAGE(I49:Y49),"–") -> 0.8125 | BH49: =IFERROR(AVERAGE(Z49:AM49),"–") -> 1.1538462 | BI49: =IFERROR(AVERAGE(AN49:AY49),"–") -> 1.3333333 | BJ49: =IFERROR(AVERAGE(AZ49:BA49),"–") -> 1.5 | BK49: =IFERROR(AVERAGE(BB49:BF49),"–") -> 1.6 | BL49: =IFERROR(AVERAGE(I49:BF49),"–") -> 1.1333333 | BM49: =COUNTIF(I49:BF49,0) -> 17
A50: Maraîchage (dont tomate) | B50: MA_BAG_VEG_NI | C50: Maraîchage plein champ (paillage bagasse, VEG, pluvial) | D50: 0 | E50: AqYield / AqYieldNC | F50: annuelle | G50: 0.49 | I50: 0 | J50: 2 | K50: 2 | L50: 0 | M50: 0 | N50: 0 | O50: 0 | P50: 0 | Q50: 3 | R50: 1 | S50: 0 | T50: 1 | U50: 0 | V50: 0 | W50: 2 | X50: 2 | Y50: – | Z50: 0 | AA50: 0 | AB50: 1 | AC50: 1 | AD50: 1 | AE50: 2 | AF50: 2 | AG50: 1 | AH50: 2 | AI50: 0 | AJ50: 1 | AK50: 1 | AL50: 3 | AM50: – | AN50: 2 | AO50: 2 | AP50: – | AQ50: 2 | AR50: 2 | AS50: 0 | AT50: 0 | AU50: – | AV50: 1 | AW50: 0 | AX50: 3 | AY50: – | AZ50: 3 | BA50: 0 | BB50: 2 | BC50: 2 | BD50: 2 | BE50: 2 | BF50: 0 | BG50: =IFERROR(AVERAGE(I50:Y50),"–") -> 0.8125 | BH50: =IFERROR(AVERAGE(Z50:AM50),"–") -> 1.1538462 | BI50: =IFERROR(AVERAGE(AN50:AY50),"–") -> 1.3333333 | BJ50: =IFERROR(AVERAGE(AZ50:BA50),"–") -> 1.5 | BK50: =IFERROR(AVERAGE(BB50:BF50),"–") -> 1.6 | BL50: =IFERROR(AVERAGE(I50:BF50),"–") -> 1.1333333 | BM50: =COUNTIF(I50:BF50,0) -> 17
A51: Maraîchage (dont tomate) | B51: MA_BRF_BIO_I | C51: Maraîchage plein champ (paillage BRF, BIO, irrigué) | D51: 0 | E51: AqYield / AqYieldNC | F51: annuelle | G51: 0.49 | I51: 0 | J51: 2 | K51: 2 | L51: 0 | M51: 0 | N51: 0 | O51: 0 | P51: 0 | Q51: 3 | R51: 1 | S51: 0 | T51: 1 | U51: 0 | V51: 0 | W51: 2 | X51: 2 | Y51: – | Z51: 0 | AA51: 0 | AB51: 1 | AC51: 1 | AD51: 1 | AE51: 2 | AF51: 2 | AG51: 1 | AH51: 2 | AI51: 0 | AJ51: 1 | AK51: 1 | AL51: 3 | AM51: – | AN51: 2 | AO51: 2 | AP51: – | AQ51: 2 | AR51: 2 | AS51: 0 | AT51: 0 | AU51: – | AV51: 1 | AW51: 0 | AX51: 3 | AY51: – | AZ51: 3 | BA51: 0 | BB51: 2 | BC51: 2 | BD51: 2 | BE51: 2 | BF51: 0 | BG51: =IFERROR(AVERAGE(I51:Y51),"–") -> 0.8125 | BH51: =IFERROR(AVERAGE(Z51:AM51),"–") -> 1.1538462 | BI51: =IFERROR(AVERAGE(AN51:AY51),"–") -> 1.3333333 | BJ51: =IFERROR(AVERAGE(AZ51:BA51),"–") -> 1.5 | BK51: =IFERROR(AVERAGE(BB51:BF51),"–") -> 1.6 | BL51: =IFERROR(AVERAGE(I51:BF51),"–") -> 1.1333333 | BM51: =COUNTIF(I51:BF51,0) -> 17
A52: Maraîchage (dont tomate) | B52: MA_BRF_BIO_NI | C52: Maraîchage plein champ (paillage BRF, BIO, pluvial) | D52: 0 | E52: AqYield / AqYieldNC | F52: annuelle | G52: 0.49 | I52: 0 | J52: 2 | K52: 2 | L52: 0 | M52: 0 | N52: 0 | O52: 0 | P52: 0 | Q52: 3 | R52: 1 | S52: 0 | T52: 1 | U52: 0 | V52: 0 | W52: 2 | X52: 2 | Y52: – | Z52: 0 | AA52: 0 | AB52: 1 | AC52: 1 | AD52: 1 | AE52: 2 | AF52: 2 | AG52: 1 | AH52: 2 | AI52: 0 | AJ52: 1 | AK52: 1 | AL52: 3 | AM52: – | AN52: 2 | AO52: 2 | AP52: – | AQ52: 2 | AR52: 2 | AS52: 0 | AT52: 0 | AU52: – | AV52: 1 | AW52: 0 | AX52: 3 | AY52: – | AZ52: 3 | BA52: 0 | BB52: 2 | BC52: 2 | BD52: 2 | BE52: 2 | BF52: 0 | BG52: =IFERROR(AVERAGE(I52:Y52),"–") -> 0.8125 | BH52: =IFERROR(AVERAGE(Z52:AM52),"–") -> 1.1538462 | BI52: =IFERROR(AVERAGE(AN52:AY52),"–") -> 1.3333333 | BJ52: =IFERROR(AVERAGE(AZ52:BA52),"–") -> 1.5 | BK52: =IFERROR(AVERAGE(BB52:BF52),"–") -> 1.6 | BL52: =IFERROR(AVERAGE(I52:BF52),"–") -> 1.1333333 | BM52: =COUNTIF(I52:BF52,0) -> 17
A53: Maraîchage (dont tomate) | B53: MA_BRF_FER_I | C53: Maraîchage plein champ (paillage BRF, FER, irrigué) | D53: 0 | E53: AqYield / AqYieldNC | F53: annuelle | G53: 0.49 | I53: 0 | J53: 2 | K53: 2 | L53: 0 | M53: 0 | N53: 0 | O53: 0 | P53: 0 | Q53: 3 | R53: 1 | S53: 0 | T53: 1 | U53: 0 | V53: 0 | W53: 2 | X53: 2 | Y53: – | Z53: 0 | AA53: 0 | AB53: 1 | AC53: 1 | AD53: 1 | AE53: 2 | AF53: 2 | AG53: 1 | AH53: 2 | AI53: 0 | AJ53: 1 | AK53: 1 | AL53: 3 | AM53: – | AN53: 2 | AO53: 2 | AP53: – | AQ53: 2 | AR53: 2 | AS53: 0 | AT53: 0 | AU53: – | AV53: 1 | AW53: 0 | AX53: 3 | AY53: – | AZ53: 3 | BA53: 0 | BB53: 2 | BC53: 2 | BD53: 2 | BE53: 2 | BF53: 0 | BG53: =IFERROR(AVERAGE(I53:Y53),"–") -> 0.8125 | BH53: =IFERROR(AVERAGE(Z53:AM53),"–") -> 1.1538462 | BI53: =IFERROR(AVERAGE(AN53:AY53),"–") -> 1.3333333 | BJ53: =IFERROR(AVERAGE(AZ53:BA53),"–") -> 1.5 | BK53: =IFERROR(AVERAGE(BB53:BF53),"–") -> 1.6 | BL53: =IFERROR(AVERAGE(I53:BF53),"–") -> 1.1333333 | BM53: =COUNTIF(I53:BF53,0) -> 17
... A58: Maraîchage (dont tomate) | B58: MA_BRF_VEG_NI | C58: Maraîchage plein champ (paillage BRF, VEG, pluvial) | D58: 0 | E58: AqYield / AqYieldNC | F58: annuelle | G58: 0.49 | I58: 0 | J58: 2 | K58: 2 | L58: 0 | M58: 0 | N58: 0 | O58: 0 | P58: 0 | Q58: 3 | R58: 1 | S58: 0 | T58: 1 | U58: 0 | V58: 0 | W58: 2 | X58: 2 | Y58: – | Z58: 0 | AA58: 0 | AB58: 1 | AC58: 1 | AD58: 1 | AE58: 2 | AF58: 2 | AG58: 1 | AH58: 2 | AI58: 0 | AJ58: 1 | AK58: 1 | AL58: 3 | AM58: – | AN58: 2 | AO58: 2 | AP58: – | AQ58: 2 | AR58: 2 | AS58: 0 | AT58: 0 | AU58: – | AV58: 1 | AW58: 0 | AX58: 3 | AY58: – | AZ58: 3 | BA58: 0 | BB58: 2 | BC58: 2 | BD58: 2 | BE58: 2 | BF58: 0 | BG58: =IFERROR(AVERAGE(I58:Y58),"–") -> 0.8125 | BH58: =IFERROR(AVERAGE(Z58:AM58),"–") -> 1.1538462 | BI58: =IFERROR(AVERAGE(AN58:AY58),"–") -> 1.3333333 | BJ58: =IFERROR(AVERAGE(AZ58:BA58),"–") -> 1.5 | BK58: =IFERROR(AVERAGE(BB58:BF58),"–") -> 1.6 | BL58: =IFERROR(AVERAGE(I58:BF58),"–") -> 1.1333333 | BM58: =COUNTIF(I58:BF58,0) -> 17
A59: Maraîchage (dont tomate) | B59: MA_MOBIO | C59: Maraîchage bio monospécifique | D59: 0 | E59: AqYield / AqYieldNC | F59: annuelle | G59: 0.47 | H59: 25 désherbages (max 5) | I59: 0 | J59: 2 | K59: 2 | L59: 0 | M59: 0 | N59: 0 | O59: 0 | P59: 0 | Q59: 3 | R59: 1 | S59: 0 | T59: 1 | U59: 0 | V59: 0 | W59: 2 | X59: 2 | Y59: – | Z59: 0 | AA59: 0 | AB59: 1 | AC59: 2 | AD59: 1 | AE59: 2 | AF59: 2 | AG59: 1 | AH59: 2 | AI59: 0 | AJ59: 1 | AK59: 1 | AL59: 3 | AM59: – | AN59: 2 | AO59: 2 | AP59: – | AQ59: 2 | AR59: 2 | AS59: 0 | AT59: 0 | AU59: 2 | AV59: 1 | AW59: 0 | AX59: – | AY59: – | AZ59: 3 | BA59: 0 | BB59: 2 | BC59: 2 | BD59: 2 | BE59: 2 | BF59: 0 | BG59: =IFERROR(AVERAGE(I59:Y59),"–") -> 0.8125 | BH59: =IFERROR(AVERAGE(Z59:AM59),"–") -> 1.2307692 | BI59: =IFERROR(AVERAGE(AN59:AY59),"–") -> 1.2222222 | BJ59: =IFERROR(AVERAGE(AZ59:BA59),"–") -> 1.5 | BK59: =IFERROR(AVERAGE(BB59:BF59),"–") -> 1.6 | BL59: =IFERROR(AVERAGE(I59:BF59),"–") -> 1.1333333 | BM59: =COUNTIF(I59:BF59,0) -> 17
A60: Maraîchage (dont tomate) | B60: MA_PAI_BIO_I | C60: Maraîchage plein champ (paillage paille, BIO, irrigué) | D60: 0 | E60: AqYield / AqYieldNC | F60: annuelle | G60: 0.49 | I60: 0 | J60: 2 | K60: 2 | L60: 0 | M60: 0 | N60: 0 | O60: 0 | P60: 0 | Q60: 3 | R60: 1 | S60: 0 | T60: 1 | U60: 0 | V60: 0 | W60: 2 | X60: 2 | Y60: – | Z60: 0 | AA60: 0 | AB60: 1 | AC60: 1 | AD60: 1 | AE60: 2 | AF60: 2 | AG60: 1 | AH60: 2 | AI60: 0 | AJ60: 1 | AK60: 1 | AL60: 3 | AM60: – | AN60: 2 | AO60: 2 | AP60: – | AQ60: 2 | AR60: 2 | AS60: 0 | AT60: 0 | AU60: – | AV60: 1 | AW60: 0 | AX60: 3 | AY60: – | AZ60: 3 | BA60: 0 | BB60: 2 | BC60: 2 | BD60: 2 | BE60: 2 | BF60: 0 | BG60: =IFERROR(AVERAGE(I60:Y60),"–") -> 0.8125 | BH60: =IFERROR(AVERAGE(Z60:AM60),"–") -> 1.1538462 | BI60: =IFERROR(AVERAGE(AN60:AY60),"–") -> 1.3333333 | BJ60: =IFERROR(AVERAGE(AZ60:BA60),"–") -> 1.5 | BK60: =IFERROR(AVERAGE(BB60:BF60),"–") -> 1.6 | BL60: =IFERROR(AVERAGE(I60:BF60),"–") -> 1.1333333 | BM60: =COUNTIF(I60:BF60,0) -> 17
A61: Maraîchage (dont tomate) | B61: MA_PAI_BIO_NI | C61: Maraîchage plein champ (paillage paille, BIO, pluvial) | D61: 0 | E61: AqYield / AqYieldNC | F61: annuelle | G61: 0.49 | I61: 0 | J61: 2 | K61: 2 | L61: 0 | M61: 0 | N61: 0 | O61: 0 | P61: 0 | Q61: 3 | R61: 1 | S61: 0 | T61: 1 | U61: 0 | V61: 0 | W61: 2 | X61: 2 | Y61: – | Z61: 0 | AA61: 0 | AB61: 1 | AC61: 1 | AD61: 1 | AE61: 2 | AF61: 2 | AG61: 1 | AH61: 2 | AI61: 0 | AJ61: 1 | AK61: 1 | AL61: 3 | AM61: – | AN61: 2 | AO61: 2 | AP61: – | AQ61: 2 | AR61: 2 | AS61: 0 | AT61: 0 | AU61: – | AV61: 1 | AW61: 0 | AX61: 3 | AY61: – | AZ61: 3 | BA61: 0 | BB61: 2 | BC61: 2 | BD61: 2 | BE61: 2 | BF61: 0 | BG61: =IFERROR(AVERAGE(I61:Y61),"–") -> 0.8125 | BH61: =IFERROR(AVERAGE(Z61:AM61),"–") -> 1.1538462 | BI61: =IFERROR(AVERAGE(AN61:AY61),"–") -> 1.3333333 | BJ61: =IFERROR(AVERAGE(AZ61:BA61),"–") -> 1.5 | BK61: =IFERROR(AVERAGE(BB61:BF61),"–") -> 1.6 | BL61: =IFERROR(AVERAGE(I61:BF61),"–") -> 1.1333333 | BM61: =COUNTIF(I61:BF61,0) -> 17
A62: Maraîchage (dont tomate) | B62: MA_PAI_FER_I | C62: Maraîchage plein champ (paillage paille, FER, irrigué) | D62: 0 | E62: AqYield / AqYieldNC | F62: annuelle | G62: 0.49 | I62: 0 | J62: 2 | K62: 2 | L62: 0 | M62: 0 | N62: 0 | O62: 0 | P62: 0 | Q62: 3 | R62: 1 | S62: 0 | T62: 1 | U62: 0 | V62: 0 | W62: 2 | X62: 2 | Y62: – | Z62: 0 | AA62: 0 | AB62: 1 | AC62: 1 | AD62: 1 | AE62: 2 | AF62: 2 | AG62: 1 | AH62: 2 | AI62: 0 | AJ62: 1 | AK62: 1 | AL62: 3 | AM62: – | AN62: 2 | AO62: 2 | AP62: – | AQ62: 2 | AR62: 2 | AS62: 0 | AT62: 0 | AU62: – | AV62: 1 | AW62: 0 | AX62: 3 | AY62: – | AZ62: 3 | BA62: 0 | BB62: 2 | BC62: 2 | BD62: 2 | BE62: 2 | BF62: 0 | BG62: =IFERROR(AVERAGE(I62:Y62),"–") -> 0.8125 | BH62: =IFERROR(AVERAGE(Z62:AM62),"–") -> 1.1538462 | BI62: =IFERROR(AVERAGE(AN62:AY62),"–") -> 1.3333333 | BJ62: =IFERROR(AVERAGE(AZ62:BA62),"–") -> 1.5 | BK62: =IFERROR(AVERAGE(BB62:BF62),"–") -> 1.6 | BL62: =IFERROR(AVERAGE(I62:BF62),"–") -> 1.1333333 | BM62: =COUNTIF(I62:BF62,0) -> 17
A63: Maraîchage (dont tomate) | B63: MA_PAI_FER_NI | C63: Maraîchage plein champ (paillage paille, FER, pluvial) | D63: 0 | E63: AqYield / AqYieldNC | F63: annuelle | G63: 0.49 | I63: 0 | J63: 2 | K63: 2 | L63: 0 | M63: 0 | N63: 0 | O63: 0 | P63: 0 | Q63: 3 | R63: 1 | S63: 0 | T63: 1 | U63: 0 | V63: 0 | W63: 2 | X63: 2 | Y63: – | Z63: 0 | AA63: 0 | AB63: 1 | AC63: 1 | AD63: 1 | AE63: 2 | AF63: 2 | AG63: 1 | AH63: 2 | AI63: 0 | AJ63: 1 | AK63: 1 | AL63: 3 | AM63: – | AN63: 2 | AO63: 2 | AP63: – | AQ63: 2 | AR63: 2 | AS63: 0 | AT63: 0 | AU63: – | AV63: 1 | AW63: 0 | AX63: 3 | AY63: – | AZ63: 3 | BA63: 0 | BB63: 2 | BC63: 2 | BD63: 2 | BE63: 2 | BF63: 0 | BG63: =IFERROR(AVERAGE(I63:Y63),"–") -> 0.8125 | BH63: =IFERROR(AVERAGE(Z63:AM63),"–") -> 1.1538462 | BI63: =IFERROR(AVERAGE(AN63:AY63),"–") -> 1.3333333 | BJ63: =IFERROR(AVERAGE(AZ63:BA63),"–") -> 1.5 | BK63: =IFERROR(AVERAGE(BB63:BF63),"–") -> 1.6 | BL63: =IFERROR(AVERAGE(I63:BF63),"–") -> 1.1333333 | BM63: =COUNTIF(I63:BF63,0) -> 17
A64: Maraîchage (dont tomate) | B64: MA_PAI_NON_I | C64: Maraîchage plein champ (paillage paille, NON, irrigué) | D64: 0 | E64: AqYield / AqYieldNC | F64: annuelle | G64: 0.49 | I64: 0 | J64: 2 | K64: 2 | L64: 0 | M64: 0 | N64: 0 | O64: 0 | P64: 0 | Q64: 3 | R64: 1 | S64: 0 | T64: 1 | U64: 0 | V64: 0 | W64: 2 | X64: 2 | Y64: – | Z64: 0 | AA64: 0 | AB64: 1 | AC64: 1 | AD64: 1 | AE64: 2 | AF64: 2 | AG64: 1 | AH64: 2 | AI64: 0 | AJ64: 1 | AK64: 1 | AL64: 3 | AM64: – | AN64: 2 | AO64: 2 | AP64: – | AQ64: 2 | AR64: 2 | AS64: 0 | AT64: 0 | AU64: – | AV64: 1 | AW64: 0 | AX64: 3 | AY64: – | AZ64: 3 | BA64: 0 | BB64: 2 | BC64: 2 | BD64: 2 | BE64: 2 | BF64: 0 | BG64: =IFERROR(AVERAGE(I64:Y64),"–") -> 0.8125 | BH64: =IFERROR(AVERAGE(Z64:AM64),"–") -> 1.1538462 | BI64: =IFERROR(AVERAGE(AN64:AY64),"–") -> 1.3333333 | BJ64: =IFERROR(AVERAGE(AZ64:BA64),"–") -> 1.5 | BK64: =IFERROR(AVERAGE(BB64:BF64),"–") -> 1.6 | BL64: =IFERROR(AVERAGE(I64:BF64),"–") -> 1.1333333 | BM64: =COUNTIF(I64:BF64,0) -> 17
A65: Maraîchage (dont tomate) | B65: MA_PAI_NON_NI | C65: Maraîchage plein champ (paillage paille, NON, pluvial) | D65: 0 | E65: AqYield / AqYieldNC | F65: annuelle | G65: 0.49 | I65: 0 | J65: 2 | K65: 2 | L65: 0 | M65: 0 | N65: 0 | O65: 0 | P65: 0 | Q65: 3 | R65: 1 | S65: 0 | T65: 1 | U65: 0 | V65: 0 | W65: 2 | X65: 2 | Y65: – | Z65: 0 | AA65: 0 | AB65: 1 | AC65: 1 | AD65: 1 | AE65: 2 | AF65: 2 | AG65: 1 | AH65: 2 | AI65: 0 | AJ65: 1 | AK65: 1 | AL65: 3 | AM65: – | AN65: 2 | AO65: 2 | AP65: – | AQ65: 2 | AR65: 2 | AS65: 0 | AT65: 0 | AU65: – | AV65: 1 | AW65: 0 | AX65: 3 | AY65: – | AZ65: 3 | BA65: 0 | BB65: 2 | BC65: 2 | BD65: 2 | BE65: 2 | BF65: 0 | BG65: =IFERROR(AVERAGE(I65:Y65),"–") -> 0.8125 | BH65: =IFERROR(AVERAGE(Z65:AM65),"–") -> 1.1538462 | BI65: =IFERROR(AVERAGE(AN65:AY65),"–") -> 1.3333333 | BJ65: =IFERROR(AVERAGE(AZ65:BA65),"–") -> 1.5 | BK65: =IFERROR(AVERAGE(BB65:BF65),"–") -> 1.6 | BL65: =IFERROR(AVERAGE(I65:BF65),"–") -> 1.1333333 | BM65: =COUNTIF(I65:BF65,0) -> 17
A66: Maraîchage (dont tomate) | B66: MA_PAI_VEG_I | C66: Maraîchage plein champ (paillage paille, VEG, irrigué) | D66: 0 | E66: AqYield / AqYieldNC | F66: annuelle | G66: 0.49 | I66: 0 | J66: 2 | K66: 2 | L66: 0 | M66: 0 | N66: 0 | O66: 0 | P66: 0 | Q66: 3 | R66: 1 | S66: 0 | T66: 1 | U66: 0 | V66: 0 | W66: 2 | X66: 2 | Y66: – | Z66: 0 | AA66: 0 | AB66: 1 | AC66: 1 | AD66: 1 | AE66: 2 | AF66: 2 | AG66: 1 | AH66: 2 | AI66: 0 | AJ66: 1 | AK66: 1 | AL66: 3 | AM66: – | AN66: 2 | AO66: 2 | AP66: – | AQ66: 2 | AR66: 2 | AS66: 0 | AT66: 0 | AU66: – | AV66: 1 | AW66: 0 | AX66: 3 | AY66: – | AZ66: 3 | BA66: 0 | BB66: 2 | BC66: 2 | BD66: 2 | BE66: 2 | BF66: 0 | BG66: =IFERROR(AVERAGE(I66:Y66),"–") -> 0.8125 | BH66: =IFERROR(AVERAGE(Z66:AM66),"–") -> 1.1538462 | BI66: =IFERROR(AVERAGE(AN66:AY66),"–") -> 1.3333333 | BJ66: =IFERROR(AVERAGE(AZ66:BA66),"–") -> 1.5 | BK66: =IFERROR(AVERAGE(BB66:BF66),"–") -> 1.6 | BL66: =IFERROR(AVERAGE(I66:BF66),"–") -> 1.1333333 | BM66: =COUNTIF(I66:BF66,0) -> 17
A67: Maraîchage (dont tomate) | B67: MA_PAI_VEG_NI | C67: Maraîchage plein champ (paillage paille, VEG, pluvial) | D67: 0 | E67: AqYield / AqYieldNC | F67: annuelle | G67: 0.49 | I67: 0 | J67: 2 | K67: 2 | L67: 0 | M67: 0 | N67: 0 | O67: 0 | P67: 0 | Q67: 3 | R67: 1 | S67: 0 | T67: 1 | U67: 0 | V67: 0 | W67: 2 | X67: 2 | Y67: – | Z67: 0 | AA67: 0 | AB67: 1 | AC67: 1 | AD67: 1 | AE67: 2 | AF67: 2 | AG67: 1 | AH67: 2 | AI67: 0 | AJ67: 1 | AK67: 1 | AL67: 3 | AM67: – | AN67: 2 | AO67: 2 | AP67: – | AQ67: 2 | AR67: 2 | AS67: 0 | AT67: 0 | AU67: – | AV67: 1 | AW67: 0 | AX67: 3 | AY67: – | AZ67: 3 | BA67: 0 | BB67: 2 | BC67: 2 | BD67: 2 | BE67: 2 | BF67: 0 | BG67: =IFERROR(AVERAGE(I67:Y67),"–") -> 0.8125 | BH67: =IFERROR(AVERAGE(Z67:AM67),"–") -> 1.1538462 | BI67: =IFERROR(AVERAGE(AN67:AY67),"–") -> 1.3333333 | BJ67: =IFERROR(AVERAGE(AZ67:BA67),"–") -> 1.5 | BK67: =IFERROR(AVERAGE(BB67:BF67),"–") -> 1.6 | BL67: =IFERROR(AVERAGE(I67:BF67),"–") -> 1.1333333 | BM67: =COUNTIF(I67:BF67,0) -> 17
A68: Maraîchage (dont tomate) | B68: MA_PLBIO | C68: Maraîchage bio plurispécifique | D68: 0 | E68: AqYield / AqYieldNC | F68: annuelle | G68: 0.4 | H68: 2 récoltes (max 1) ; 12.5 apports (max 4) ; 37 désherbages (max 5) | I68: 0 | J68: 2 | K68: 2 | L68: 0 | M68: 0 | N68: 0 | O68: 0 | P68: 0 | Q68: 3 | R68: 1 | S68: 0 | T68: 1 | U68: 0 | V68: 0 | W68: 2 | X68: 2 | Y68: – | Z68: 0 | AA68: 0 | AB68: 1 | AC68: 2 | AD68: 1 | AE68: 2 | AF68: 2 | AG68: 1 | AH68: 2 | AI68: 0 | AJ68: 1 | AK68: 1 | AL68: 3 | AM68: – | AN68: 2 | AO68: 2 | AP68: 1 | AQ68: 2 | AR68: 2 | AS68: 0 | AT68: 0 | AU68: 2 | AV68: 2 | AW68: 0 | AX68: – | AY68: – | AZ68: 3 | BA68: 0 | BB68: 2 | BC68: 2 | BD68: 2 | BE68: 2 | BF68: 0 | BG68: =IFERROR(AVERAGE(I68:Y68),"–") -> 0.8125 | BH68: =IFERROR(AVERAGE(Z68:AM68),"–") -> 1.2307692 | BI68: =IFERROR(AVERAGE(AN68:AY68),"–") -> 1.3 | BJ68: =IFERROR(AVERAGE(AZ68:BA68),"–") -> 1.5 | BK68: =IFERROR(AVERAGE(BB68:BF68),"–") -> 1.6 | BL68: =IFERROR(AVERAGE(I68:BF68),"–") -> 1.1521739 | BM68: =COUNTIF(I68:BF68,0) -> 17
A69: Maraîchage (dont tomate) | B69: MA_TO_CHOU_JA | C69: Maraîchage plein champ (rotation tomate/chou/jachère) | D69: 0 | E69: AqYield / AqYieldNC | F69: annuelle | G69: 0.49 | I69: 0 | J69: 2 | K69: 2 | L69: 0 | M69: 0 | N69: 0 | O69: 0 | P69: 0 | Q69: 3 | R69: 1 | S69: 0 | T69: 1 | U69: 0 | V69: 0 | W69: 2 | X69: 2 | Y69: – | Z69: 0 | AA69: 0 | AB69: 1 | AC69: 2 | AD69: 1 | AE69: 2 | AF69: 2 | AG69: 1 | AH69: 2 | AI69: 0 | AJ69: 1 | AK69: 1 | AL69: 3 | AM69: – | AN69: 2 | AO69: 2 | AP69: – | AQ69: 2 | AR69: 2 | AS69: 0 | AT69: 0 | AU69: – | AV69: 1 | AW69: 0 | AX69: 3 | AY69: – | AZ69: 3 | BA69: 0 | BB69: 2 | BC69: 2 | BD69: 2 | BE69: 2 | BF69: 0 | BG69: =IFERROR(AVERAGE(I69:Y69),"–") -> 0.8125 | BH69: =IFERROR(AVERAGE(Z69:AM69),"–") -> 1.2307692 | BI69: =IFERROR(AVERAGE(AN69:AY69),"–") -> 1.3333333 | BJ69: =IFERROR(AVERAGE(AZ69:BA69),"–") -> 1.5 | BK69: =IFERROR(AVERAGE(BB69:BF69),"–") -> 1.6 | BL69: =IFERROR(AVERAGE(I69:BF69),"–") -> 1.1555556 | BM69: =COUNTIF(I69:BF69,0) -> 17
A70: Maraîchage (dont tomate) | B70: TH | C70: Tomate | D70: 0 | E70: AqYield / AqYieldNC | F70: annuelle | G70: 0.52 | H70: 12 apports (max 4) ; 13 traitements (max 8) | I70: 1 | J70: 2 | K70: 2 | L70: 1 | M70: 1 | N70: 1 | O70: 1 | P70: 1 | Q70: 3 | R70: 1 | S70: 0 | T70: 1 | U70: 1 | V70: 0 | W70: 2 | X70: 2 | Y70: – | Z70: 1 | AA70: 0 | AB70: 1 | AC70: 2 | AD70: 1 | AE70: 2 | AF70: 2 | AG70: 1 | AH70: 2 | AI70: 1 | AJ70: 1 | AK70: 1 | AL70: 3 | AM70: – | AN70: 2 | AO70: 2 | AP70: – | AQ70: 2 | AR70: 1 | AS70: 1 | AT70: 0 | AU70: 1 | AV70: – | AW70: – | AX70: 3 | AY70: – | AZ70: 3 | BA70: 1 | BB70: 2 | BC70: 2 | BD70: 2 | BE70: 2 | BF70: 0 | BG70: =IFERROR(AVERAGE(I70:Y70),"–") -> 1.25 | BH70: =IFERROR(AVERAGE(Z70:AM70),"–") -> 1.3846154 | BI70: =IFERROR(AVERAGE(AN70:AY70),"–") -> 1.5 | BJ70: =IFERROR(AVERAGE(AZ70:BA70),"–") -> 2 | BK70: =IFERROR(AVERAGE(BB70:BF70),"–") -> 1.6 | BL70: =IFERROR(AVERAGE(I70:BF70),"–") -> 1.4090909 | BM70: =COUNTIF(I70:BF70,0) -> 5
A71: Melon | B71: ME | C71: Melon | D71: 189.4 | E71: AqYield / AqYieldNC | F71: annuelle | G71: 0.21 | H71: 11 traitements (max 8) | I71: 1 | J71: 2 | K71: 2 | L71: 1 | M71: 1 | N71: 1 | O71: 1 | P71: 1 | Q71: 3 | R71: 1 | S71: 0 | T71: 1 | U71: 1 | V71: 0 | W71: 2 | X71: 2 | Y71: – | Z71: 1 | AA71: 0 | AB71: 1 | AC71: 2 | AD71: 1 | AE71: 2 | AF71: 2 | AG71: 1 | AH71: 2 | AI71: 1 | AJ71: 1 | AK71: 1 | AL71: 3 | AM71: – | AN71: 2 | AO71: 2 | AP71: 1 | AQ71: 2 | AR71: 2 | AS71: 1 | AT71: 0 | AU71: 2 | AV71: 2 | AW71: 0 | AX71: 3 | AY71: – | AZ71: 3 | BA71: 1 | BB71: 2 | BC71: 2 | BD71: 2 | BE71: 2 | BF71: 0 | BG71: =IFERROR(AVERAGE(I71:Y71),"–") -> 1.25 | BH71: =IFERROR(AVERAGE(Z71:AM71),"–") -> 1.3846154 | BI71: =IFERROR(AVERAGE(AN71:AY71),"–") -> 1.5454545 | BJ71: =IFERROR(AVERAGE(AZ71:BA71),"–") -> 2 | BK71: =IFERROR(AVERAGE(BB71:BF71),"–") -> 1.6 | BL71: =IFERROR(AVERAGE(I71:BF71),"–") -> 1.4255319 | BM71: =COUNTIF(I71:BF71,0) -> 6
A72: Igname | B72: IG_PLA | C72: Igname à plat | D72: 103.3 | E72: AqYield / AqYieldNC | F72: annuelle | G72: 0.07 | H72: 23 désherbages (max 5) | I72: 1 | J72: 2 | K72: 2 | L72: 1 | M72: 1 | N72: 1 | O72: 1 | P72: 1 | Q72: 3 | R72: 1 | S72: 0 | T72: 1 | U72: 0 | V72: 0 | W72: 2 | X72: 2 | Y72: – | Z72: 1 | AA72: 0 | AB72: 1 | AC72: 2 | AD72: 1 | AE72: 1 | AF72: 2 | AG72: 1 | AH72: 2 | AI72: 1 | AJ72: 1 | AK72: 1 | AL72: 3 | AM72: – | AN72: 2 | AO72: 2 | AP72: 1 | AQ72: 2 | AR72: 3 | AS72: 1 | AT72: 0 | AU72: 2 | AV72: 2 | AW72: 0 | AX72: 3 | AY72: – | AZ72: 3 | BA72: 1 | BB72: 2 | BC72: 2 | BD72: 2 | BE72: 2 | BF72: 0 | BG72: =IFERROR(AVERAGE(I72:Y72),"–") -> 1.1875 | BH72: =IFERROR(AVERAGE(Z72:AM72),"–") -> 1.3076923 | BI72: =IFERROR(AVERAGE(AN72:AY72),"–") -> 1.6363636 | BJ72: =IFERROR(AVERAGE(AZ72:BA72),"–") -> 2 | BK72: =IFERROR(AVERAGE(BB72:BF72),"–") -> 1.6 | BL72: =IFERROR(AVERAGE(I72:BF72),"–") -> 1.4042553 | BM72: =COUNTIF(I72:BF72,0) -> 7
A73: Igname | B73: IG_TUT | C73: Igname tuteurée | D73: 42.2 | E73: AqYield / AqYieldNC | F73: annuelle | G73: 0.27 | H73: 26 désherbages (max 5) | I73: 1 | J73: 2 | K73: 2 | L73: 1 | M73: 1 | N73: 1 | O73: 1 | P73: 1 | Q73: 3 | R73: 1 | S73: 0 | T73: 1 | U73: 0 | V73: 0 | W73: 2 | X73: 2 | Y73: – | Z73: 1 | AA73: 0 | AB73: 1 | AC73: 2 | AD73: 1 | AE73: 1 | AF73: 2 | AG73: 1 | AH73: 2 | AI73: 1 | AJ73: 1 | AK73: 1 | AL73: 3 | AM73: – | AN73: 2 | AO73: 2 | AP73: – | AQ73: 2 | AR73: 2 | AS73: 1 | AT73: 0 | AU73: 2 | AV73: 1 | AW73: 0 | AX73: 3 | AY73: – | AZ73: 3 | BA73: 1 | BB73: 2 | BC73: 2 | BD73: 2 | BE73: 2 | BF73: 0 | BG73: =IFERROR(AVERAGE(I73:Y73),"–") -> 1.1875 | BH73: =IFERROR(AVERAGE(Z73:AM73),"–") -> 1.3076923 | BI73: =IFERROR(AVERAGE(AN73:AY73),"–") -> 1.5 | BJ73: =IFERROR(AVERAGE(AZ73:BA73),"–") -> 2 | BK73: =IFERROR(AVERAGE(BB73:BF73),"–") -> 1.6 | BL73: =IFERROR(AVERAGE(I73:BF73),"–") -> 1.3695652 | BM73: =COUNTIF(I73:BF73,0) -> 7
A74: Ananas | B74: AN_NU | C74: Ananas sans paillage plastique | D74: 68.7 | E74: AqYield / AqYieldNC | F74: cycle de 18 mois | G74: 0 | I74: 1 | J74: 2 | K74: 2 | L74: 1 | M74: 1 | N74: 1 | O74: 1 | P74: 1 | Q74: 3 | R74: 1 | S74: 0 | T74: 1 | U74: 0 | V74: 0 | W74: 2 | X74: 2 | Y74: – | Z74: 1 | AA74: 0 | AB74: 1 | AC74: 2 | AD74: 1 | AE74: 1 | AF74: 2 | AG74: 1 | AH74: 1 | AI74: 1 | AJ74: 1 | AK74: 1 | AL74: 3 | AM74: – | AN74: 2 | AO74: 2 | AP74: – | AQ74: 3 | AR74: 3 | AS74: 1 | AT74: 0 | AU74: 2 | AV74: – | AW74: – | AX74: 3 | AY74: – | AZ74: 3 | BA74: 1 | BB74: 2 | BC74: 2 | BD74: 2 | BE74: 2 | BF74: 0 | BG74: =IFERROR(AVERAGE(I74:Y74),"–") -> 1.1875 | BH74: =IFERROR(AVERAGE(Z74:AM74),"–") -> 1.2307692 | BI74: =IFERROR(AVERAGE(AN74:AY74),"–") -> 2 | BJ74: =IFERROR(AVERAGE(AZ74:BA74),"–") -> 2 | BK74: =IFERROR(AVERAGE(BB74:BF74),"–") -> 1.6 | BL74: =IFERROR(AVERAGE(I74:BF74),"–") -> 1.4318182 | BM74: =COUNTIF(I74:BF74,0) -> 6
A75: Ananas | B75: AN_PA | C75: Ananas avec paillage plastique | D75: 64 | E75: AqYield / AqYieldNC | F75: cycle de 18 mois | G75: 0 | H75: 17.3 traitements (max 8) | I75: 1 | J75: 2 | K75: 2 | L75: 1 | M75: 1 | N75: 1 | O75: 1 | P75: 1 | Q75: 3 | R75: 1 | S75: 0 | T75: 1 | U75: 0 | V75: 0 | W75: 2 | X75: 2 | Y75: – | Z75: 1 | AA75: 0 | AB75: 1 | AC75: 2 | AD75: 1 | AE75: 1 | AF75: 2 | AG75: 1 | AH75: 1 | AI75: 1 | AJ75: 1 | AK75: 1 | AL75: 3 | AM75: – | AN75: 2 | AO75: 2 | AP75: – | AQ75: 2 | AR75: 3 | AS75: 1 | AT75: 0 | AU75: 2 | AV75: – | AW75: – | AX75: 3 | AY75: – | AZ75: 3 | BA75: 1 | BB75: 2 | BC75: 2 | BD75: 2 | BE75: 2 | BF75: 0 | BG75: =IFERROR(AVERAGE(I75:Y75),"–") -> 1.1875 | BH75: =IFERROR(AVERAGE(Z75:AM75),"–") -> 1.2307692 | BI75: =IFERROR(AVERAGE(AN75:AY75),"–") -> 1.875 | BJ75: =IFERROR(AVERAGE(AZ75:BA75),"–") -> 2 | BK75: =IFERROR(AVERAGE(BB75:BF75),"–") -> 1.6 | BL75: =IFERROR(AVERAGE(I75:BF75),"–") -> 1.4090909 | BM75: =COUNTIF(I75:BF75,0) -> 6
A76: Agrumes | B76: AG | C76: Agrumes | D76: 100.8 | E76: AqYield / AqYieldNC | F76: plantation de 15 ans | G76: 0.05 | H76: 9 apports (max 4) | I76: 1 | J76: 2 | K76: 2 | L76: 0 | M76: 0 | N76: 0 | O76: 0 | P76: 0 | Q76: 3 | R76: 1 | S76: 0 | T76: 1 | U76: 1 | V76: 0 | W76: 2 | X76: 2 | Y76: – | Z76: 1 | AA76: 0 | AB76: 1 | AC76: 2 | AD76: 1 | AE76: 1 | AF76: 1 | AG76: 1 | AH76: 1 | AI76: 1 | AJ76: 1 | AK76: 1 | AL76: 3 | AM76: – | AN76: 2 | AO76: 2 | AP76: 1 | AQ76: 2 | AR76: 3 | AS76: 1 | AT76: 0 | AU76: 1 | AV76: 2 | AW76: 0 | AX76: 3 | AY76: – | AZ76: 3 | BA76: 1 | BB76: 2 | BC76: 2 | BD76: 2 | BE76: 2 | BF76: 0 | BG76: =IFERROR(AVERAGE(I76:Y76),"–") -> 0.9375 | BH76: =IFERROR(AVERAGE(Z76:AM76),"–") -> 1.1538462 | BI76: =IFERROR(AVERAGE(AN76:AY76),"–") -> 1.5454545 | BJ76: =IFERROR(AVERAGE(AZ76:BA76),"–") -> 2 | BK76: =IFERROR(AVERAGE(BB76:BF76),"–") -> 1.6 | BL76: =IFERROR(AVERAGE(I76:BF76),"–") -> 1.2553191 | BM76: =COUNTIF(I76:BF76,0) -> 11
A77: Vergers | B77: VE_BTGT | C77: Vergers, Basse-Terre et Grande-Terre | D77: 262.4 | E77: AqYield / AqYieldNC | F77: plantation de 15 ans | G77: 0.07 | H77: 5 apports (max 4) | I77: 0 | J77: 2 | K77: 2 | L77: 0 | M77: 0 | N77: 0 | O77: 0 | P77: 0 | Q77: 3 | R77: 1 | S77: 0 | T77: 1 | U77: 0 | V77: 0 | W77: 2 | X77: 2 | Y77: – | Z77: 0 | AA77: 0 | AB77: 1 | AC77: 2 | AD77: 1 | AE77: 1 | AF77: 1 | AG77: 1 | AH77: 1 | AI77: 0 | AJ77: 1 | AK77: 1 | AL77: 3 | AM77: – | AN77: 2 | AO77: 2 | AP77: 1 | AQ77: 2 | AR77: 3 | AS77: 1 | AT77: 0 | AU77: 1 | AV77: 2 | AW77: 0 | AX77: 3 | AY77: – | AZ77: 3 | BA77: 0 | BB77: 2 | BC77: 2 | BD77: 2 | BE77: 2 | BF77: 0 | BG77: =IFERROR(AVERAGE(I77:Y77),"–") -> 0.8125 | BH77: =IFERROR(AVERAGE(Z77:AM77),"–") -> 1 | BI77: =IFERROR(AVERAGE(AN77:AY77),"–") -> 1.5454545 | BJ77: =IFERROR(AVERAGE(AZ77:BA77),"–") -> 1.5 | BK77: =IFERROR(AVERAGE(BB77:BF77),"–") -> 1.6 | BL77: =IFERROR(AVERAGE(I77:BF77),"–") -> 1.1489362 | BM77: =COUNTIF(I77:BF77,0) -> 16
A78: Vergers | B78: VE_PLUIE | C78: Vergers, zones très pluvieuses | D78: 48.5 | E78: AqYield / AqYieldNC | F78: plantation de 15 ans | G78: 0.07 | H78: 5 apports (max 4) | I78: 0 | J78: 2 | K78: 2 | L78: 0 | M78: 0 | N78: 0 | O78: 0 | P78: 0 | Q78: 3 | R78: 1 | S78: 0 | T78: 1 | U78: 0 | V78: 0 | W78: 2 | X78: 2 | Y78: – | Z78: 0 | AA78: 0 | AB78: 1 | AC78: 2 | AD78: 1 | AE78: 1 | AF78: 1 | AG78: 1 | AH78: 1 | AI78: 0 | AJ78: 1 | AK78: 1 | AL78: 3 | AM78: – | AN78: 2 | AO78: 2 | AP78: 1 | AQ78: 2 | AR78: 3 | AS78: 1 | AT78: 0 | AU78: 1 | AV78: 1 | AW78: 0 | AX78: 3 | AY78: – | AZ78: 3 | BA78: 0 | BB78: 2 | BC78: 2 | BD78: 2 | BE78: 2 | BF78: 0 | BG78: =IFERROR(AVERAGE(I78:Y78),"–") -> 0.8125 | BH78: =IFERROR(AVERAGE(Z78:AM78),"–") -> 1 | BI78: =IFERROR(AVERAGE(AN78:AY78),"–") -> 1.4545455 | BJ78: =IFERROR(AVERAGE(AZ78:BA78),"–") -> 1.5 | BK78: =IFERROR(AVERAGE(BB78:BF78),"–") -> 1.6 | BL78: =IFERROR(AVERAGE(I78:BF78),"–") -> 1.1276596 | BM78: =COUNTIF(I78:BF78,0) -> 16
A79: Jachère | B79: JA | C79: Jachère | D79: 621.5 | E79: gel (espèce existante, ITK fourni) | F79: annuelle | G79: 0 | I79: – | J79: – | K79: – | L79: – | M79: – | N79: – | O79: – | P79: – | Q79: – | R79: – | S79: – | T79: – | U79: – | V79: – | W79: – | X79: – | Y79: – | Z79: – | AA79: – | AB79: – | AC79: – | AD79: – | AE79: – | AF79: – | AG79: – | AH79: – | AI79: – | AJ79: – | AK79: – | AL79: – | AM79: – | AN79: 2 | AO79: – | AP79: – | AQ79: – | AR79: – | AS79: – | AT79: – | AU79: – | AV79: – | AW79: – | AX79: – | AY79: – | AZ79: – | BA79: – | BB79: – | BC79: 2 | BD79: 2 | BE79: 2 | BF79: 0 | BG79: =IFERROR(AVERAGE(I79:Y79),"–") -> – | BH79: =IFERROR(AVERAGE(Z79:AM79),"–") -> – | BI79: =IFERROR(AVERAGE(AN79:AY79),"–") -> 2 | BJ79: =IFERROR(AVERAGE(AZ79:BA79),"–") -> – | BK79: =IFERROR(AVERAGE(BB79:BF79),"–") -> 1.5 | BL79: =IFERROR(AVERAGE(I79:BF79),"–") -> 1.6 | BM79: =COUNTIF(I79:BF79,0) -> 1
A80: Moyenne des cultures | I80: =IFERROR(AVERAGE(I5:I79),"–") -> 0.56944444 | J80: =IFERROR(AVERAGE(J5:J79),"–") -> 2 | K80: =IFERROR(AVERAGE(K5:K79),"–") -> 1.9583333 | L80: =IFERROR(AVERAGE(L5:L79),"–") -> 0.55555556 | M80: =IFERROR(AVERAGE(M5:M79),"–") -> 0.55555556 | N80: =IFERROR(AVERAGE(N5:N79),"–") -> 0.55555556 | O80: =IFERROR(AVERAGE(O5:O79),"–") -> 0.55555556 | P80: =IFERROR(AVERAGE(P5:P79),"–") -> 0.55555556 | ... BL80: =IFERROR(AVERAGE(BL5:BL79),"–") -> 1.2759598
A81: Moyenne pondérée par la surface 2017 | I81: =IFERROR(SUMPRODUCT($D$5:$D$79,I5:I79)/SUMIF(I5:I79,">=0",$D$5:$D$79),"–") -> 0.91702662 | J81: =IFERROR(SUMPRODUCT($D$5:$D$79,J5:J79)/SUMIF(J5:J79,">=0",$D$5:$D$79),"–") -> 2 | K81: =IFERROR(SUMPRODUCT($D$5:$D$79,K5:K79)/SUMIF(K5:K79,">=0",$D$5:$D$79),"–") -> 1.8702393 | L81: =IFERROR(SUMPRODUCT($D$5:$D$79,L5:L79)/SUMIF(L5:L79,">=0",$D$5:$D$79),"–") -> 0.91104102 | M81: =IFERROR(SUMPRODUCT($D$5:$D$79,M5:M79)/SUMIF(M5:M79,">=0",$D$5:$D$79),"–") -> 0.91104102 | N81: =IFERROR(SUMPRODUCT($D$5:$D$79,N5:N79)/SUMIF(N5:N79,">=0",$D$5:$D$79),"–") -> 0.91104102 | O81: =IFERROR(SUMPRODUCT($D$5:$D$79,O5:O79)/SUMIF(O5:O79,">=0",$D$5:$D$79),"–") -> 0.91104102 | P81: =IFERROR(SUMPRODUCT($D$5:$D$79,P5:P79)/SUMIF(P5:P79,">=0",$D$5:$D$79),"–") -> 0.91104102 | ... BL81: =IFERROR(SUMPRODUCT($D$5:$D$79,BL5:BL79)/SUMIF(BL5:BL79,">=0",$D$5:$D$79),"–") -> 1.2810217
A83: Codes sans ITK, laissés de côté (en-têtes de groupe RPG) : AN, BA, BC, CS, IG, MA, NC, PN, VE

Sheet Paramètres
A1: Dictionnaire des paramètres de la feuille Cultures
A2: Une ligne par colonne notée. Les décomptes renvoient à la feuille Cultures ; les pistes de sources sont à valider.
A4: Bloc | B4: Paramètre MAELIA | C4: Signification | D4: Unité | E4: Nécessité | F4: Ce que MOSAICA a | G4: Règle de notation | H4: Pistes de sources | I4: Lien | J4: Moyenne | K4: Moyenne pondérée surface | L4: Cultures à 0 | M4: à 1 | N4: à 2 | O4: à 3 | P4: sans objet | Q4: Surface à 0 (ha) | R4: Surface à 0 ou 1 (ha)
A5: Espèce : eau, phéno | B5: RENDEMENT_OPTIMAL | C5: Rendement potentiel local, que le modèle réduit selon les stress hydrique et azoté. À adapter au terrain (obligatoire). | D5: t/ha | E5: obligatoire | F5: Aucune : Rdt_Cult est un rendement moyen atteint, pas un potentiel. | G5: 1 si des essais ou références donnent un potentiel pour la plante, 0 sinon (mélanges, prairie). | H5: Essais INRAE/CIRAD, CTCS (canne), IT2 (banane, diversification), Agreste (meilleures années). La grille d'enquête ITK le demande par culture et par type de sol. En 1.4.31 : parametres/rendements_optimaux.csv. | I5: https://daaf.guadeloupe.agriculture.gouv.fr/ | J5: =IFERROR(AVERAGE(Cultures!$I$5:$I$79),"–") -> 0.56944444 | K5: =IFERROR(SUMPRODUCT(Cultures!$D$5:$D$79,Cultures!$I$5:$I$79)/SUMIF(Cultures!$I$5:$I$79,">=0",Cultures!$D$5:$D$79),"–") -> 0.91702662 | L5: =COUNTIF(Cultures!$I$5:$I$79,0) -> 31 | M5: =COUNTIF(Cultures!$I$5:$I$79,1) -> 41 | N5: =COUNTIF(Cultures!$I$5:$I$79,2) -> 0 | O5: =COUNTIF(Cultures!$I$5:$I$79,3) -> 0 | P5: =COUNTIF(Cultures!$I$5:$I$79,"–") -> 3 | Q5: =SUMIF(Cultures!$I$5:$I$79,0,Cultures!$D$5:$D$79) -> 1397.86 | R5: =SUMIF(Cultures!$I$5:$I$79,"<=1",Cultures!$D$5:$D$79) -> 16847.09
A6: Espèce : eau, phéno | B6: RENDEMENT_MOYEN | C6: Rendement moyen, sert à la validation. | D6: t/ha | E6: optionnel | F6: Rdt_Cult_CF_<scénario>. | G6: 2 : présent, mais 1 à 4 fois le rendement du territoire (vigilance C.1). | H6: Agreste (statistique agricole annuelle), CTCS, LPG. | I6: https://daaf.guadeloupe.agriculture.gouv.fr/ | J6: =IFERROR(AVERAGE(Cultures!$J$5:$J$79),"–") -> 2 | K6: =IFERROR(SUMPRODUCT(Cultures!$D$5:$D$79,Cultures!$J$5:$J$79)/SUMIF(Cultures!$J$5:$J$79,">=0",Cultures!$D$5:$D$79),"–") -> 2 | L6: =COUNTIF(Cultures!$J$5:$J$79,0) -> 0 | M6: =COUNTIF(Cultures!$J$5:$J$79,1) -> 0 | N6: =COUNTIF(Cultures!$J$5:$J$79,2) -> 72 | O6: =COUNTIF(Cultures!$J$5:$J$79,3) -> 0 | P6: =COUNTIF(Cultures!$J$5:$J$79,"–") -> 3 | Q6: =SUMIF(Cultures!$J$5:$J$79,0,Cultures!$D$5:$D$79) -> 0 | R6: =SUMIF(Cultures!$J$5:$J$79,"<=1",Cultures!$D$5:$D$79) -> 0
A7: Espèce : eau, phéno | B7: RENDEMENT_MIN | C7: Rendement minimum, sert à la validation. | D7: t/ha | E7: optionnel | F7: Var_Rdt_Cult (une variance, pas un minimum). | G7: 2 si une variance existe (minimum à en déduire), 1 sinon. | H7: Séries Agreste par culture. | I7: https://daaf.guadeloupe.agriculture.gouv.fr/ | J7: =IFERROR(AVERAGE(Cultures!$K$5:$K$79),"–") -> 1.9583333 | K7: =IFERROR(SUMPRODUCT(Cultures!$D$5:$D$79,Cultures!$K$5:$K$79)/SUMIF(Cultures!$K$5:$K$79,">=0",Cultures!$D$5:$D$79),"–") -> 1.8702393 | L7: =COUNTIF(Cultures!$K$5:$K$79,0) -> 0 | M7: =COUNTIF(Cultures!$K$5:$K$79,1) -> 3 | N7: =COUNTIF(Cultures!$K$5:$K$79,2) -> 69 | O7: =COUNTIF(Cultures!$K$5:$K$79,3) -> 0 | P7: =COUNTIF(Cultures!$K$5:$K$79,"–") -> 3 | Q7: =SUMIF(Cultures!$K$5:$K$79,0,Cultures!$D$5:$D$79) -> 0 | R7: =SUMIF(Cultures!$K$5:$K$79,"<=1",Cultures!$D$5:$D$79) -> 2186.09
A8: Espèce : eau, phéno | B8: Tbase | C8: Température de base des degrés-jours (un entier). | D8: °C | E8: obligatoire | F8: Aucune. | G8: 1 si un modèle de culture publié paramètre la plante, 0 sinon. | H8: Modèles publiés à transposer : canne MOSICAS (CIRAD) et STICS (paramétrage R570, La Réunion) ; banane SIMBA (CIRAD, Guadeloupe) et STICS-banane (Brisson, Ozier-Lafontaine et Dorel, 1998) ; ananas SIMPIÑA (CIRAD, Queen Victoria, La Réunion) ; igname : CropSyst adapté (Marcos et al., Guadeloupe), dont le développement dépend de la photopériode, qu'AqYield ne représente pas ; tomate STICS. Melon : pas de modèle, mais des sommes de températures publiées (base 10 °C, ou 11 °C plafonnée à 25 °C). | I8: https://stics.inrae.fr/ | J8: =IFERROR(AVERAGE(Cultures!$L$5:$L$79),"–") -> 0.55555556 | K8: =IFERROR(SUMPRODUCT(Cultures!$D$5:$D$79,Cultures!$L$5:$L$79)/SUMIF(Cultures!$L$5:$L$79,">=0",Cultures!$D$5:$D$79),"–") -> 0.91104102 | L8: =COUNTIF(Cultures!$L$5:$L$79,0) -> 32 | M8: =COUNTIF(Cultures!$L$5:$L$79,1) -> 40 | N8: =COUNTIF(Cultures!$L$5:$L$79,2) -> 0 | O8: =COUNTIF(Cultures!$L$5:$L$79,3) -> 0 | P8: =COUNTIF(Cultures!$L$5:$L$79,"–") -> 3 | Q8: =SUMIF(Cultures!$L$5:$L$79,0,Cultures!$D$5:$D$79) -> 1498.7 | R8: =SUMIF(Cultures!$L$5:$L$79,"<=1",Cultures!$D$5:$D$79) -> 16847.09
A9: Espèce : eau, phéno | B9: Tmax | C9: Température maximale prise en compte dans les degrés-jours. | D9: °C | E9: obligatoire | F9: Aucune. | G9: Comme Tbase. | H9: Modèles publiés à transposer : canne MOSICAS (CIRAD) et STICS (paramétrage R570, La Réunion) ; banane SIMBA (CIRAD, Guadeloupe) et STICS-banane (Brisson, Ozier-Lafontaine et Dorel, 1998) ; ananas SIMPIÑA (CIRAD, Queen Victoria, La Réunion) ; igname : CropSyst adapté (Marcos et al., Guadeloupe), dont le développement dépend de la photopériode, qu'AqYield ne représente pas ; tomate STICS. Melon : pas de modèle, mais des sommes de températures publiées (base 10 °C, ou 11 °C plafonnée à 25 °C). | I9: https://stics.inrae.fr/ | J9: =IFERROR(AVERAGE(Cultures!$M$5:$M$79),"–") -> 0.55555556 | K9: =IFERROR(SUMPRODUCT(Cultures!$D$5:$D$79,Cultures!$M$5:$M$79)/SUMIF(Cultures!$M$5:$M$79,">=0",Cultures!$D$5:$D$79),"–") -> 0.91104102 | L9: =COUNTIF(Cultures!$M$5:$M$79,0) -> 32 | M9: =COUNTIF(Cultures!$M$5:$M$79,1) -> 40 | N9: =COUNTIF(Cultures!$M$5:$M$79,2) -> 0 | O9: =COUNTIF(Cultures!$M$5:$M$79,3) -> 0 | P9: =COUNTIF(Cultures!$M$5:$M$79,"–") -> 3 | Q9: =SUMIF(Cultures!$M$5:$M$79,0,Cultures!$D$5:$D$79) -> 1498.7 | R9: =SUMIF(Cultures!$M$5:$M$79,"<=1",Cultures!$D$5:$D$79) -> 16847.09
A10: Espèce : eau, phéno | B10: DEGRES_J_LevTbase | C10: Somme de degrés-jours à la levée. | D10: °C.j | E10: obligatoire | F10: Aucune (Duree_Cycle_Cult : 12 mois partout, 18 pour l'ananas). | G10: Comme Tbase. Pour une plantation (canne, banane) : reprise après plantation ou coupe, à définir avec l'équipe MAELIA. | H10: Modèles publiés à transposer : canne MOSICAS (CIRAD) et STICS (paramétrage R570, La Réunion) ; banane SIMBA (CIRAD, Guadeloupe) et STICS-banane (Brisson, Ozier-Lafontaine et Dorel, 1998) ; ananas SIMPIÑA (CIRAD, Queen Victoria, La Réunion) ; igname : CropSyst adapté (Marcos et al., Guadeloupe), dont le développement dépend de la photopériode, qu'AqYield ne représente pas ; tomate STICS. Melon : pas de modèle, mais des sommes de températures publiées (base 10 °C, ou 11 °C plafonnée à 25 °C). | I10: https://stics.inrae.fr/ | J10: =IFERROR(AVERAGE(Cultures!$N$5:$N$79),"–") -> 0.55555556 | K10: =IFERROR(SUMPRODUCT(Cultures!$D$5:$D$79,Cultures!$N$5:$N$79)/SUMIF(Cultures!$N$5:$N$79,">=0",Cultures!$D$5:$D$79),"–") -> 0.91104102 | L10: =COUNTIF(Cultures!$N$5:$N$79,0) -> 32 | M10: =COUNTIF(Cultures!$N$5:$N$79,1) -> 40 | N10: =COUNTIF(Cultures!$N$5:$N$79,2) -> 0 | O10: =COUNTIF(Cultures!$N$5:$N$79,3) -> 0 | P10: =COUNTIF(Cultures!$N$5:$N$79,"–") -> 3 | Q10: =SUMIF(Cultures!$N$5:$N$79,0,Cultures!$D$5:$D$79) -> 1498.7 | R10: =SUMIF(Cultures!$N$5:$N$79,"<=1",Cultures!$D$5:$D$79) -> 16847.09
A11: Espèce : eau, phéno | B11: DEGRES_J_Flor | C11: Somme de degrés-jours à la floraison (maximum du Kc). | D11: °C.j | E11: obligatoire | F11: Aucune. | G11: Comme Tbase. Sans objet agronomique strict pour la canne (récoltée avant floraison) : c'est la date du Kc maximal qu'il faut. | H11: Modèles publiés à transposer : canne MOSICAS (CIRAD) et STICS (paramétrage R570, La Réunion) ; banane SIMBA (CIRAD, Guadeloupe) et STICS-banane (Brisson, Ozier-Lafontaine et Dorel, 1998) ; ananas SIMPIÑA (CIRAD, Queen Victoria, La Réunion) ; igname : CropSyst adapté (Marcos et al., Guadeloupe), dont le développement dépend de la photopériode, qu'AqYield ne représente pas ; tomate STICS. Melon : pas de modèle, mais des sommes de températures publiées (base 10 °C, ou 11 °C plafonnée à 25 °C). | I11: https://stics.inrae.fr/ | J11: =IFERROR(AVERAGE(Cultures!$O$5:$O$79),"–") -> 0.55555556 | K11: =IFERROR(SUMPRODUCT(Cultures!$D$5:$D$79,Cultures!$O$5:$O$79)/SUMIF(Cultures!$O$5:$O$79,">=0",Cultures!$D$5:$D$79),"–") -> 0.91104102 | L11: =COUNTIF(Cultures!$O$5:$O$79,0) -> 32 | M11: =COUNTIF(Cultures!$O$5:$O$79,1) -> 40 | N11: =COUNTIF(Cultures!$O$5:$O$79,2) -> 0 | O11: =COUNTIF(Cultures!$O$5:$O$79,3) -> 0 | P11: =COUNTIF(Cultures!$O$5:$O$79,"–") -> 3 | Q11: =SUMIF(Cultures!$O$5:$O$79,0,Cultures!$D$5:$D$79) -> 1498.7 | R11: =SUMIF(Cultures!$O$5:$O$79,"<=1",Cultures!$D$5:$D$79) -> 16847.09
A12: Espèce : eau, phéno | B12: DEGRES_J_matPhyTbase | C12: Somme de degrés-jours à la maturité (Kc nul). La récolte n'est déclenchée qu'une fois cette somme atteinte. | D12: °C.j | E12: obligatoire | F12: Aucune. | G12: Comme Tbase. Fixe aussi la date de récolte : à caler sur la campagne réelle. | H12: Modèles publiés à transposer : canne MOSICAS (CIRAD) et STICS (paramétrage R570, La Réunion) ; banane SIMBA (CIRAD, Guadeloupe) et STICS-banane (Brisson, Ozier-Lafontaine et Dorel, 1998) ; ananas SIMPIÑA (CIRAD, Queen Victoria, La Réunion) ; igname : CropSyst adapté (Marcos et al., Guadeloupe), dont le développement dépend de la photopériode, qu'AqYield ne représente pas ; tomate STICS. Melon : pas de modèle, mais des sommes de températures publiées (base 10 °C, ou 11 °C plafonnée à 25 °C). | I12: https://stics.inrae.fr/ | J12: =IFERROR(AVERAGE(Cultures!$P$5:$P$79),"–") -> 0.55555556 | K12: =IFERROR(SUMPRODUCT(Cultures!$D$5:$D$79,Cultures!$P$5:$P$79)/SUMIF(Cultures!$P$5:$P$79,">=0",Cultures!$D$5:$D$79),"–") -> 0.91104102 | L12: =COUNTIF(Cultures!$P$5:$P$79,0) -> 32 | M12: =COUNTIF(Cultures!$P$5:$P$79,1) -> 40 | N12: =COUNTIF(Cultures!$P$5:$P$79,2) -> 0 | O12: =COUNTIF(Cultures!$P$5:$P$79,3) -> 0 | P12: =COUNTIF(Cultures!$P$5:$P$79,"–") -> 3 | Q12: =SUMIF(Cultures!$P$5:$P$79,0,Cultures!$D$5:$D$79) -> 1498.7 | R12: =SUMIF(Cultures!$P$5:$P$79,"<=1",Cultures!$D$5:$D$79) -> 16847.09
A13: Espèce : eau, phéno | B13: FREIN | C13: Frein hivernal au développement (1 = pas de frein). | D13: 0-1 | E13: obligatoire | F13: Sans hiver, la valeur est 1. | G13: 3 : connue sans mesure (à confirmer : les supports parlent aussi de frein photopériodique). | H13: — | J13: =IFERROR(AVERAGE(Cultures!$Q$5:$Q$79),"–") -> 3 | K13: =IFERROR(SUMPRODUCT(Cultures!$D$5:$D$79,Cultures!$Q$5:$Q$79)/SUMIF(Cultures!$Q$5:$Q$79,">=0",Cultures!$D$5:$D$79),"–") -> 3 | L13: =COUNTIF(Cultures!$Q$5:$Q$79,0) -> 0 | M13: =COUNTIF(Cultures!$Q$5:$Q$79,1) -> 0 | N13: =COUNTIF(Cultures!$Q$5:$Q$79,2) -> 0 | O13: =COUNTIF(Cultures!$Q$5:$Q$79,3) -> 72 | P13: =COUNTIF(Cultures!$Q$5:$Q$79,"–") -> 3 | Q13: =SUMIF(Cultures!$Q$5:$Q$79,0,Cultures!$D$5:$D$79) -> 0 | R13: =SUMIF(Cultures!$Q$5:$Q$79,"<=1",Cultures!$D$5:$D$79) -> 0
A14: Espèce : eau, phéno | B14: KMAX | C14: Coefficient cultural maximal. | D14: — | E14: obligatoire | F14: Aucune. Attention : KCROP de Data_Cult est le coefficient de minéralisation de MORGWANIK, pas un Kc. | G14: 1 : les tables FAO-56 donnent un Kc pour la plante ou une voisine. | H14: FAO-56, tableau 12 (canne, banane, ananas, agrumes, tomate, melon ; igname par analogie avec les tubercules tropicaux). | I14: https://www.fao.org/4/x0490e/x0490e0b.htm | J14: =IFERROR(AVERAGE(Cultures!$R$5:$R$79),"–") -> 1 | K14: =IFERROR(SUMPRODUCT(Cultures!$D$5:$D$79,Cultures!$R$5:$R$79)/SUMIF(Cultures!$R$5:$R$79,">=0",Cultures!$D$5:$D$79),"–") -> 1 | L14: =COUNTIF(Cultures!$R$5:$R$79,0) -> 0 | M14: =COUNTIF(Cultures!$R$5:$R$79,1) -> 72 | N14: =COUNTIF(Cultures!$R$5:$R$79,2) -> 0 | O14: =COUNTIF(Cultures!$R$5:$R$79,3) -> 0 | P14: =COUNTIF(Cultures!$R$5:$R$79,"–") -> 3 | Q14: =SUMIF(Cultures!$R$5:$R$79,0,Cultures!$D$5:$D$79) -> 0 | R14: =SUMIF(Cultures!$R$5:$R$79,"<=1",Cultures!$D$5:$D$79) -> 16847.09
A15: Espèce : eau, phéno | B15: CVIG | C15: Vigueur : pente de montée du Kc. | D15: — | E15: obligatoire | F15: Aucune. | G15: 0 : propre à AqYield, se cale sur une courbe de Kc ou de LAI. | H15: Calibration avec le référent MAELIA ; LAI par télédétection. | I15: https://maelia.pages-forge.inrae.fr/documentation/04-donnees_entree.html | J15: =IFERROR(AVERAGE(Cultures!$S$5:$S$79),"–") -> 0 | K15: =IFERROR(SUMPRODUCT(Cultures!$D$5:$D$79,Cultures!$S$5:$S$79)/SUMIF(Cultures!$S$5:$S$79,">=0",Cultures!$D$5:$D$79),"–") -> 0 | L15: =COUNTIF(Cultures!$S$5:$S$79,0) -> 72 | M15: =COUNTIF(Cultures!$S$5:$S$79,1) -> 0 | N15: =COUNTIF(Cultures!$S$5:$S$79,2) -> 0 | O15: =COUNTIF(Cultures!$S$5:$S$79,3) -> 0 | P15: =COUNTIF(Cultures!$S$5:$S$79,"–") -> 3 | Q15: =SUMIF(Cultures!$S$5:$S$79,0,Cultures!$D$5:$D$79) -> 16847.09 | R15: =SUMIF(Cultures!$S$5:$S$79,"<=1",Cultures!$D$5:$D$79) -> 16847.09
A16: Espèce : eau, phéno | B16: CSTO | C16: Effet de la fermeture stomatique sur le stress hydrique. | D16: — | E16: obligatoire | F16: Aucune. | G16: 1 : vaut 1 pour toutes les espèces des jeux d'exemple MAELIA. | H16: Valeur par défaut des espèces existantes. | I16: https://maelia.pages-forge.inrae.fr/documentation/04-donnees_entree.html | J16: =IFERROR(AVERAGE(Cultures!$T$5:$T$79),"–") -> 1 | K16: =IFERROR(SUMPRODUCT(Cultures!$D$5:$D$79,Cultures!$T$5:$T$79)/SUMIF(Cultures!$T$5:$T$79,">=0",Cultures!$D$5:$D$79),"–") -> 1 | L16: =COUNTIF(Cultures!$T$5:$T$79,0) -> 0 | M16: =COUNTIF(Cultures!$T$5:$T$79,1) -> 72 | N16: =COUNTIF(Cultures!$T$5:$T$79,2) -> 0 | O16: =COUNTIF(Cultures!$T$5:$T$79,3) -> 0 | P16: =COUNTIF(Cultures!$T$5:$T$79,"–") -> 3 | Q16: =SUMIF(Cultures!$T$5:$T$79,0,Cultures!$D$5:$D$79) -> 0 | R16: =SUMIF(Cultures!$T$5:$T$79,"<=1",Cultures!$D$5:$D$79) -> 16847.09
A17: Espèce : eau, phéno | B17: coeff_Fonction_Prod | C17: Forme de la fonction de production : effet du stress hydrique sur le rendement. | D17: — | E17: obligatoire | F17: Aucune. | G17: 1 si un coefficient de réponse à l'eau (Ky) est publié pour la plante, 0 sinon. Ky n'est pas le paramètre d'AqYield : point de départ seulement. | H17: FAO-33 (Doorenbos et Kassam 1979), table reprise dans FAO-66 : canne 1,2, banane 1,2-1,35, tomate 1,05, pastèque 1,1 (pour le melon). Agrumes 1,1-1,3 d'après une source secondaire. Pas d'ananas ni d'igname. | I17: https://www.fao.org/4/i2800e/i2800e.pdf | J17: =IFERROR(AVERAGE(Cultures!$U$5:$U$79),"–") -> 0.51388889 | K17: =IFERROR(SUMPRODUCT(Cultures!$D$5:$D$79,Cultures!$U$5:$U$79)/SUMIF(Cultures!$U$5:$U$79,">=0",Cultures!$D$5:$D$79),"–") -> 0.90051991 | L17: =COUNTIF(Cultures!$U$5:$U$79,0) -> 35 | M17: =COUNTIF(Cultures!$U$5:$U$79,1) -> 37 | N17: =COUNTIF(Cultures!$U$5:$U$79,2) -> 0 | O17: =COUNTIF(Cultures!$U$5:$U$79,3) -> 0 | P17: =COUNTIF(Cultures!$U$5:$U$79,"–") -> 3 | Q17: =SUMIF(Cultures!$U$5:$U$79,0,Cultures!$D$5:$D$79) -> 1675.95 | R17: =SUMIF(Cultures!$U$5:$U$79,"<=1",Cultures!$D$5:$D$79) -> 16847.09
A18: Espèce : eau, phéno | B18: CRACINE | C18: Vitesse de croissance racinaire. | D18: °C.j par mm de RU | E18: obligatoire | F18: Aucune (LONG_RAC est une profondeur, pas une vitesse). | G18: 0 : propre à AqYield. | H18: Calibration avec le référent MAELIA. | I18: https://maelia.pages-forge.inrae.fr/documentation/04-donnees_entree.html | J18: =IFERROR(AVERAGE(Cultures!$V$5:$V$79),"–") -> 0 | K18: =IFERROR(SUMPRODUCT(Cultures!$D$5:$D$79,Cultures!$V$5:$V$79)/SUMIF(Cultures!$V$5:$V$79,">=0",Cultures!$D$5:$D$79),"–") -> 0 | L18: =COUNTIF(Cultures!$V$5:$V$79,0) -> 72 | M18: =COUNTIF(Cultures!$V$5:$V$79,1) -> 0 | N18: =COUNTIF(Cultures!$V$5:$V$79,2) -> 0 | O18: =COUNTIF(Cultures!$V$5:$V$79,3) -> 0 | P18: =COUNTIF(Cultures!$V$5:$V$79,"–") -> 3 | Q18: =SUMIF(Cultures!$V$5:$V$79,0,Cultures!$D$5:$D$79) -> 16847.09 | R18: =SUMIF(Cultures!$V$5:$V$79,"<=1",Cultures!$D$5:$D$79) -> 16847.09
A19: Espèce : eau, phéno | B19: PROF_MAX_RACINE | C19: Profondeur maximale d'enracinement. | D19: cm | E19: obligatoire | F19: Data_Cult, ligne LONG_RAC (une valeur par plante). | G19: 2 : présente, commune à toutes les variantes d'une plante. | H19: FAO-56, tableau 22. | I19: https://www.fao.org/4/x0490e/x0490e00.htm | J19: =IFERROR(AVERAGE(Cultures!$W$5:$W$79),"–") -> 2 | K19: =IFERROR(SUMPRODUCT(Cultures!$D$5:$D$79,Cultures!$W$5:$W$79)/SUMIF(Cultures!$W$5:$W$79,">=0",Cultures!$D$5:$D$79),"–") -> 2 | L19: =COUNTIF(Cultures!$W$5:$W$79,0) -> 0 | M19: =COUNTIF(Cultures!$W$5:$W$79,1) -> 0 | N19: =COUNTIF(Cultures!$W$5:$W$79,2) -> 72 | O19: =COUNTIF(Cultures!$W$5:$W$79,3) -> 0 | P19: =COUNTIF(Cultures!$W$5:$W$79,"–") -> 3 | Q19: =SUMIF(Cultures!$W$5:$W$79,0,Cultures!$D$5:$D$79) -> 0 | R19: =SUMIF(Cultures!$W$5:$W$79,"<=1",Cultures!$D$5:$D$79) -> 0
A20: Espèce : eau, phéno | B20: ZonesClimatiques | C20: Zones climatiques où l'espèce peut pousser. | D20: — | E20: optionnel (choix d'assolement par MAELIA seulement) | F20: Bornes d'éligibilité ALTI_MIN/MAX et PLUVIO_MIN/MAX de Data_Cult. | G20: 2 : à traduire une fois les zones climatiques de la Guadeloupe définies. | H20: — | J20: =IFERROR(AVERAGE(Cultures!$X$5:$X$79),"–") -> 2 | K20: =IFERROR(SUMPRODUCT(Cultures!$D$5:$D$79,Cultures!$X$5:$X$79)/SUMIF(Cultures!$X$5:$X$79,">=0",Cultures!$D$5:$D$79),"–") -> 2 | L20: =COUNTIF(Cultures!$X$5:$X$79,0) -> 0 | M20: =COUNTIF(Cultures!$X$5:$X$79,1) -> 0 | N20: =COUNTIF(Cultures!$X$5:$X$79,2) -> 72 | O20: =COUNTIF(Cultures!$X$5:$X$79,3) -> 0 | P20: =COUNTIF(Cultures!$X$5:$X$79,"–") -> 3 | Q20: =SUMIF(Cultures!$X$5:$X$79,0,Cultures!$D$5:$D$79) -> 0 | R20: =SUMIF(Cultures!$X$5:$X$79,"<=1",Cultures!$D$5:$D$79) -> 0
A21: Espèce : eau, phéno | B21: especesHerbSim.csv | C21: Prairies : la trentaine de paramètres HerbSim (efficience du rayonnement, durée de vie des feuilles, digestibilité, dilution de l'azote…). | D21: — | E21: obligatoire pour les prairies | F21: Aucune. HerbSim ne connaît que 7 espèces tempérées et 5 types fonctionnels de graminées (A, B, b, C, D). | G21: 0 : aucune graminée tropicale (pangola, herbe de Guinée…) n'est paramétrée. | H21: INRAE Antilles-Guyane (URZ/ASSET, fourrages tropicaux) ; équipe MAELIA. | I21: https://maelia.pages-forge.inrae.fr/documentation/04-donnees_entree.html | J21: =IFERROR(AVERAGE(Cultures!$Y$5:$Y$79),"–") -> 0 | K21: =IFERROR(SUMPRODUCT(Cultures!$D$5:$D$79,Cultures!$Y$5:$Y$79)/SUMIF(Cultures!$Y$5:$Y$79,">=0",Cultures!$D$5:$D$79),"–") -> 0 | L21: =COUNTIF(Cultures!$Y$5:$Y$79,0) -> 2 | M21: =COUNTIF(Cultures!$Y$5:$Y$79,1) -> 0 | N21: =COUNTIF(Cultures!$Y$5:$Y$79,2) -> 0 | O21: =COUNTIF(Cultures!$Y$5:$Y$79,3) -> 0 | P21: =COUNTIF(Cultures!$Y$5:$Y$79,"–") -> 73 | Q21: =SUMIF(Cultures!$Y$5:$Y$79,0,Cultures!$D$5:$D$79) -> 6109.43 | R21: =SUMIF(Cultures!$Y$5:$Y$79,"<=1",Cultures!$D$5:$D$79) -> 6109.43
A22: Espèce : N et C | B22: BESOIN_N | C22: Besoin en azote par unité produite (ou BESOIN_Ntot, besoin total). | D22: kg N/t (ou kg N/ha) | E22: AqYieldNC | F22: Aucune : l'azote des engrais est un apport, pas un besoin. | G22: 1 si les exportations d'azote de la plante sont publiées, 0 sinon. | H22: Canne : 0,8 à 1,4 kg N/t de tiges (1 kg N/t au Brésil) ; banane : 1,3 à 1,9 kg N/t de fruits (revue Fruits, CIRAD) ; igname (D. alata) : ~2,9 kg N/t de tubercules frais, sur deux études seulement ; ananas : exportations faibles, publiées par fruit. | I22: https://stics.inrae.fr/ | J22: =IFERROR(AVERAGE(Cultures!$Z$5:$Z$79),"–") -> 0.56944444 | K22: =IFERROR(SUMPRODUCT(Cultures!$D$5:$D$79,Cultures!$Z$5:$Z$79)/SUMIF(Cultures!$Z$5:$Z$79,">=0",Cultures!$D$5:$D$79),"–") -> 0.91702662 | L22: =COUNTIF(Cultures!$Z$5:$Z$79,0) -> 31 | M22: =COUNTIF(Cultures!$Z$5:$Z$79,1) -> 41 | N22: =COUNTIF(Cultures!$Z$5:$Z$79,2) -> 0 | O22: =COUNTIF(Cultures!$Z$5:$Z$79,3) -> 0 | P22: =COUNTIF(Cultures!$Z$5:$Z$79,"–") -> 3 | Q22: =SUMIF(Cultures!$Z$5:$Z$79,0,Cultures!$D$5:$D$79) -> 1397.86 | R22: =SUMIF(Cultures!$Z$5:$Z$79,"<=1",Cultures!$D$5:$D$79) -> 16847.09
A23: Espèce : N et C | B23: Type_Nacq + courbe | C23: Type d'acquisition de l'azote et forme de la demande (DEBUT_, FREIN_, PRE_FLO_, PRE_MAT_BESOIN_N ; coef_500Mat pour le type 500Mat). | D23: — | E23: AqYieldNC | F23: Aucune. | G23: 0 : métamodèle propre à AqYield-N, à choisir avec le référent. | H23: Équipe MAELIA ; note AqYieldNC (Data INRAE). | I23: https://maelia.pages-forge.inrae.fr/documentation/04-donnees_entree.html | J23: =IFERROR(AVERAGE(Cultures!$AA$5:$AA$79),"–") -> 0 | K23: =IFERROR(SUMPRODUCT(Cultures!$D$5:$D$79,Cultures!$AA$5:$AA$79)/SUMIF(Cultures!$AA$5:$AA$79,">=0",Cultures!$D$5:$D$79),"–") -> 0 | L23: =COUNTIF(Cultures!$AA$5:$AA$79,0) -> 72 | M23: =COUNTIF(Cultures!$AA$5:$AA$79,1) -> 0 | N23: =COUNTIF(Cultures!$AA$5:$AA$79,2) -> 0 | O23: =COUNTIF(Cultures!$AA$5:$AA$79,3) -> 0 | P23: =COUNTIF(Cultures!$AA$5:$AA$79,"–") -> 3 | Q23: =SUMIF(Cultures!$AA$5:$AA$79,0,Cultures!$D$5:$D$79) -> 16847.09 | R23: =SUMIF(Cultures!$AA$5:$AA$79,"<=1",Cultures!$D$5:$D$79) -> 16847.09
A24: Espèce : N et C | B24: adil, bdil, adilmax | C24: Courbe de dilution critique (et maximale) de l'azote, comme dans STICS. | D24: — | E24: AqYieldNC | F24: Aucune. | G24: 1 : des courbes génériques sont publiées pour les plantes en C3 et en C4 (la canne est en C4), à défaut d'une courbe propre à l'espèce. | H24: Greenwood et al. (1990) : C3 5,7 W^-0,5, C4 4,1 W^-0,5 (% N) ; courbe propre à la canne : Oliveira et al. (2013). adilmax apparaît en 1.4.31. | I24: https://stics.inrae.fr/ | J24: =IFERROR(AVERAGE(Cultures!$AB$5:$AB$79),"–") -> 1 | K24: =IFERROR(SUMPRODUCT(Cultures!$D$5:$D$79,Cultures!$AB$5:$AB$79)/SUMIF(Cultures!$AB$5:$AB$79,">=0",Cultures!$D$5:$D$79),"–") -> 1 | L24: =COUNTIF(Cultures!$AB$5:$AB$79,0) -> 0 | M24: =COUNTIF(Cultures!$AB$5:$AB$79,1) -> 72 | N24: =COUNTIF(Cultures!$AB$5:$AB$79,2) -> 0 | O24: =COUNTIF(Cultures!$AB$5:$AB$79,3) -> 0 | P24: =COUNTIF(Cultures!$AB$5:$AB$79,"–") -> 3 | Q24: =SUMIF(Cultures!$AB$5:$AB$79,0,Cultures!$D$5:$D$79) -> 0 | R24: =SUMIF(Cultures!$AB$5:$AB$79,"<=1",Cultures!$D$5:$D$79) -> 16847.09
A25: Espèce : N et C | B25: N_grain | C25: Teneur en azote du produit récolté. | D25: % MS | E25: AqYieldNC | F25: Nutri_Cult, ligne Prot (protéines / 6,25) pour les cultures alimentaires. | G25: 2 si les protéines du produit sont dans Nutri_Cult, 1 sinon (tables de composition). | H25: Table Ciqual (Anses). | I25: https://ciqual.anses.fr/ | J25: =IFERROR(AVERAGE(Cultures!$AC$5:$AC$79),"–") -> 1.2083333 | K25: =IFERROR(SUMPRODUCT(Cultures!$D$5:$D$79,Cultures!$AC$5:$AC$79)/SUMIF(Cultures!$AC$5:$AC$79,">=0",Cultures!$D$5:$D$79),"–") -> 1.1045694 | L25: =COUNTIF(Cultures!$AC$5:$AC$79,0) -> 0 | M25: =COUNTIF(Cultures!$AC$5:$AC$79,1) -> 57 | N25: =COUNTIF(Cultures!$AC$5:$AC$79,2) -> 15 | O25: =COUNTIF(Cultures!$AC$5:$AC$79,3) -> 0 | P25: =COUNTIF(Cultures!$AC$5:$AC$79,"–") -> 3 | Q25: =SUMIF(Cultures!$AC$5:$AC$79,0,Cultures!$D$5:$D$79) -> 0 | R25: =SUMIF(Cultures!$AC$5:$AC$79,"<=1",Cultures!$D$5:$D$79) -> 15085.4
A26: Espèce : N et C | B26: Tms | C26: Teneur en matière sèche du produit récolté. | D26: 0-1 | E26: AqYieldNC | F26: Aucune. | G26: 1 : dans les tables de composition. | H26: Table Ciqual (Anses) : igname crue 69,6 g d'eau pour 100 g, soit Tms ≈ 0,30, et 1,3 à 1,5 g de protéines. | I26: https://ciqual.anses.fr/ | J26: =IFERROR(AVERAGE(Cultures!$AD$5:$AD$79),"–") -> 1 | K26: =IFERROR(SUMPRODUCT(Cultures!$D$5:$D$79,Cultures!$AD$5:$AD$79)/SUMIF(Cultures!$AD$5:$AD$79,">=0",Cultures!$D$5:$D$79),"–") -> 1 | L26: =COUNTIF(Cultures!$AD$5:$AD$79,0) -> 0 | M26: =COUNTIF(Cultures!$AD$5:$AD$79,1) -> 72 | N26: =COUNTIF(Cultures!$AD$5:$AD$79,2) -> 0 | O26: =COUNTIF(Cultures!$AD$5:$AD$79,3) -> 0 | P26: =COUNTIF(Cultures!$AD$5:$AD$79,"–") -> 3 | Q26: =SUMIF(Cultures!$AD$5:$AD$79,0,Cultures!$D$5:$D$79) -> 0 | R26: =SUMIF(Cultures!$AD$5:$AD$79,"<=1",Cultures!$D$5:$D$79) -> 16847.09
A27: Espèce : N et C | B27: HI | C27: Indice de récolte : produit / biomasse aérienne totale. | D27: 0-1 | E27: AqYieldNC | F27: À déduire de Rdt_Cult, Tms et BIOM_AER (résidus aériens, t/ha). | G27: 2 si BIOM_AER est renseignée (≠ 6, la valeur par défaut), 1 sinon. | H27: MORGWANIK (résidus) ; littérature par plante. | J27: =IFERROR(AVERAGE(Cultures!$AE$5:$AE$79),"–") -> 1.8888889 | K27: =IFERROR(SUMPRODUCT(Cultures!$D$5:$D$79,Cultures!$AE$5:$AE$79)/SUMIF(Cultures!$AE$5:$AE$79,">=0",Cultures!$D$5:$D$79),"–") -> 1.9469178 | L27: =COUNTIF(Cultures!$AE$5:$AE$79,0) -> 0 | M27: =COUNTIF(Cultures!$AE$5:$AE$79,1) -> 8 | N27: =COUNTIF(Cultures!$AE$5:$AE$79,2) -> 64 | O27: =COUNTIF(Cultures!$AE$5:$AE$79,3) -> 0 | P27: =COUNTIF(Cultures!$AE$5:$AE$79,"–") -> 3 | Q27: =SUMIF(Cultures!$AE$5:$AE$79,0,Cultures!$D$5:$D$79) -> 0 | R27: =SUMIF(Cultures!$AE$5:$AE$79,"<=1",Cultures!$D$5:$D$79) -> 894.28
A28: Espèce : N et C | B28: SR_ratio | C28: Rapport parties aériennes / racines après récolte (ou RootC_fixed). | D28: — | E28: AqYieldNC | F28: Data_Cult, ligne RAC (biomasse racinaire / rendement) : définition voisine. | G28: 2 : proxy à convertir ; 1 si RAC vaut 0,1, la valeur mise quand elle est inconnue. | H28: MORGWANIK ; littérature par plante. | J28: =IFERROR(AVERAGE(Cultures!$AF$5:$AF$79),"–") -> 1.9583333 | K28: =IFERROR(SUMPRODUCT(Cultures!$D$5:$D$79,Cultures!$AF$5:$AF$79)/SUMIF(Cultures!$AF$5:$AF$79,">=0",Cultures!$D$5:$D$79),"–") -> 1.9755608 | L28: =COUNTIF(Cultures!$AF$5:$AF$79,0) -> 0 | M28: =COUNTIF(Cultures!$AF$5:$AF$79,1) -> 3 | N28: =COUNTIF(Cultures!$AF$5:$AF$79,2) -> 69 | O28: =COUNTIF(Cultures!$AF$5:$AF$79,3) -> 0 | P28: =COUNTIF(Cultures!$AF$5:$AF$79,"–") -> 3 | Q28: =SUMIF(Cultures!$AF$5:$AF$79,0,Cultures!$D$5:$D$79) -> 0 | R28: =SUMIF(Cultures!$AF$5:$AF$79,"<=1",Cultures!$D$5:$D$79) -> 411.73
A29: Espèce : N et C | B29: beta | C29: Répartition des racines en profondeur (Gale et Grigal 1987). | D29: — | E29: AqYieldNC | F29: Aucune. | G29: 1 : valeurs tabulées par type de plante. | H29: Gale et Grigal (1987) ; valeurs par biome dans Jackson et al. (1996) ; espèces MAELIA voisines. | I29: https://maelia.pages-forge.inrae.fr/documentation/04-donnees_entree.html | J29: =IFERROR(AVERAGE(Cultures!$AG$5:$AG$79),"–") -> 1 | K29: =IFERROR(SUMPRODUCT(Cultures!$D$5:$D$79,Cultures!$AG$5:$AG$79)/SUMIF(Cultures!$AG$5:$AG$79,">=0",Cultures!$D$5:$D$79),"–") -> 1 | L29: =COUNTIF(Cultures!$AG$5:$AG$79,0) -> 0 | M29: =COUNTIF(Cultures!$AG$5:$AG$79,1) -> 72 | N29: =COUNTIF(Cultures!$AG$5:$AG$79,2) -> 0 | O29: =COUNTIF(Cultures!$AG$5:$AG$79,3) -> 0 | P29: =COUNTIF(Cultures!$AG$5:$AG$79,"–") -> 3 | Q29: =SUMIF(Cultures!$AG$5:$AG$79,0,Cultures!$D$5:$D$79) -> 0 | R29: =SUMIF(Cultures!$AG$5:$AG$79,"<=1",Cultures!$D$5:$D$79) -> 16847.09
A30: Espèce : N et C | B30: C_aer, C_rac | C30: Teneur en carbone des résidus aériens et racinaires. | D30: 0-1 | E30: AqYieldNC | F30: Data_Cult, ligne CARB (0,4 par défaut). | G30: 2 : une valeur, commune aux deux compartiments ; 1 si CARB vaut 0,4, la valeur mise quand elle est inconnue. | H30: MORGWANIK. | J30: =IFERROR(AVERAGE(Cultures!$AH$5:$AH$79),"–") -> 1.9305556 | K30: =IFERROR(SUMPRODUCT(Cultures!$D$5:$D$79,Cultures!$AH$5:$AH$79)/SUMIF(Cultures!$AH$5:$AH$79,">=0",Cultures!$D$5:$D$79),"–") -> 1.9676858 | L30: =COUNTIF(Cultures!$AH$5:$AH$79,0) -> 0 | M30: =COUNTIF(Cultures!$AH$5:$AH$79,1) -> 5 | N30: =COUNTIF(Cultures!$AH$5:$AH$79,2) -> 67 | O30: =COUNTIF(Cultures!$AH$5:$AH$79,3) -> 0 | P30: =COUNTIF(Cultures!$AH$5:$AH$79,"–") -> 3 | Q30: =SUMIF(Cultures!$AH$5:$AH$79,0,Cultures!$D$5:$D$79) -> 0 | R30: =SUMIF(Cultures!$AH$5:$AH$79,"<=1",Cultures!$D$5:$D$79) -> 544.4
A31: Espèce : N et C | B31: CN_ratio | C31: Rapport C/N des résidus de culture. | D31: — | E31: AqYieldNC | F31: Aucune (HRES est un coefficient d'humification). | G31: 1 si la plante est une espèce unique, 0 pour les mélanges. | H31: Paramètres résidus de STICS ; INRAE Antilles-Guyane (ASTRO). | I31: https://stics.inrae.fr/ | J31: =IFERROR(AVERAGE(Cultures!$AI$5:$AI$79),"–") -> 0.56944444 | K31: =IFERROR(SUMPRODUCT(Cultures!$D$5:$D$79,Cultures!$AI$5:$AI$79)/SUMIF(Cultures!$AI$5:$AI$79,">=0",Cultures!$D$5:$D$79),"–") -> 0.91702662 | L31: =COUNTIF(Cultures!$AI$5:$AI$79,0) -> 31 | M31: =COUNTIF(Cultures!$AI$5:$AI$79,1) -> 41 | N31: =COUNTIF(Cultures!$AI$5:$AI$79,2) -> 0 | O31: =COUNTIF(Cultures!$AI$5:$AI$79,3) -> 0 | P31: =COUNTIF(Cultures!$AI$5:$AI$79,"–") -> 3 | Q31: =SUMIF(Cultures!$AI$5:$AI$79,0,Cultures!$D$5:$D$79) -> 1397.86 | R31: =SUMIF(Cultures!$AI$5:$AI$79,"<=1",Cultures!$D$5:$D$79) -> 16847.09
A32: Espèce : N et C | B32: Pse | C32: Part des résidus aériens laissée au sol quand ils sont exportés. | D32: 0-1 | E32: AqYieldNC | F32: Aucune (le scénario RESTIT/SMART porte la pratique). | G32: 1 : à dire d'expert. | H32: Chambre d'agriculture, instituts techniques. | I32: https://guadeloupe.chambres-agriculture.fr/ | J32: =IFERROR(AVERAGE(Cultures!$AJ$5:$AJ$79),"–") -> 1 | K32: =IFERROR(SUMPRODUCT(Cultures!$D$5:$D$79,Cultures!$AJ$5:$AJ$79)/SUMIF(Cultures!$AJ$5:$AJ$79,">=0",Cultures!$D$5:$D$79),"–") -> 1 | L32: =COUNTIF(Cultures!$AJ$5:$AJ$79,0) -> 0 | M32: =COUNTIF(Cultures!$AJ$5:$AJ$79,1) -> 72 | N32: =COUNTIF(Cultures!$AJ$5:$AJ$79,2) -> 0 | O32: =COUNTIF(Cultures!$AJ$5:$AJ$79,3) -> 0 | P32: =COUNTIF(Cultures!$AJ$5:$AJ$79,"–") -> 3 | Q32: =SUMIF(Cultures!$AJ$5:$AJ$79,0,Cultures!$D$5:$D$79) -> 0 | R32: =SUMIF(Cultures!$AJ$5:$AJ$79,"<=1",Cultures!$D$5:$D$79) -> 16847.09
A33: Espèce : N et C | B33: ABSCISSION | C33: Chute des parties aériennes avant récolte. | D33: 0-1 | E33: AqYieldNC | F33: Aucune. | G33: 1 : 0 par défaut, à valider par plante. | H33: Valeurs des espèces MAELIA voisines. | I33: https://maelia.pages-forge.inrae.fr/documentation/04-donnees_entree.html | J33: =IFERROR(AVERAGE(Cultures!$AK$5:$AK$79),"–") -> 1 | K33: =IFERROR(SUMPRODUCT(Cultures!$D$5:$D$79,Cultures!$AK$5:$AK$79)/SUMIF(Cultures!$AK$5:$AK$79,">=0",Cultures!$D$5:$D$79),"–") -> 1 | L33: =COUNTIF(Cultures!$AK$5:$AK$79,0) -> 0 | M33: =COUNTIF(Cultures!$AK$5:$AK$79,1) -> 72 | N33: =COUNTIF(Cultures!$AK$5:$AK$79,2) -> 0 | O33: =COUNTIF(Cultures!$AK$5:$AK$79,3) -> 0 | P33: =COUNTIF(Cultures!$AK$5:$AK$79,"–") -> 3 | Q33: =SUMIF(Cultures!$AK$5:$AK$79,0,Cultures!$D$5:$D$79) -> 0 | R33: =SUMIF(Cultures!$AK$5:$AK$79,"<=1",Cultures!$D$5:$D$79) -> 16847.09
A34: Espèce : N et C | B34: isLEG | C34: Légumineuse fixatrice. | D34: vrai/faux | E34: AqYieldNC | F34: Agronomie : aucune des cultures n'est une légumineuse. | G34: 3. | H34: — | J34: =IFERROR(AVERAGE(Cultures!$AL$5:$AL$79),"–") -> 3 | K34: =IFERROR(SUMPRODUCT(Cultures!$D$5:$D$79,Cultures!$AL$5:$AL$79)/SUMIF(Cultures!$AL$5:$AL$79,">=0",Cultures!$D$5:$D$79),"–") -> 3 | L34: =COUNTIF(Cultures!$AL$5:$AL$79,0) -> 0 | M34: =COUNTIF(Cultures!$AL$5:$AL$79,1) -> 0 | N34: =COUNTIF(Cultures!$AL$5:$AL$79,2) -> 0 | O34: =COUNTIF(Cultures!$AL$5:$AL$79,3) -> 72 | P34: =COUNTIF(Cultures!$AL$5:$AL$79,"–") -> 3 | Q34: =SUMIF(Cultures!$AL$5:$AL$79,0,Cultures!$D$5:$D$79) -> 0 | R34: =SUMIF(Cultures!$AL$5:$AL$79,"<=1",Cultures!$D$5:$D$79) -> 0
A35: Espèce : N et C | B35: especeRepousse | C35: Couvert qui simule la repousse après récolte. | D35: — | E35: optionnel | F35: Aucune. | G35: 0 pour la canne : c'est peut-être le mécanisme des repousses, à confirmer. Sans objet ailleurs. | H35: Équipe MAELIA (question n° 1 de la formation). | I35: https://maelia.pages-forge.inrae.fr/documentation/04-donnees_entree.html | J35: =IFERROR(AVERAGE(Cultures!$AM$5:$AM$79),"–") -> 0 | K35: =IFERROR(SUMPRODUCT(Cultures!$D$5:$D$79,Cultures!$AM$5:$AM$79)/SUMIF(Cultures!$AM$5:$AM$79,">=0",Cultures!$D$5:$D$79),"–") -> 0 | L35: =COUNTIF(Cultures!$AM$5:$AM$79,0) -> 28 | M35: =COUNTIF(Cultures!$AM$5:$AM$79,1) -> 0 | N35: =COUNTIF(Cultures!$AM$5:$AM$79,2) -> 0 | O35: =COUNTIF(Cultures!$AM$5:$AM$79,3) -> 0 | P35: =COUNTIF(Cultures!$AM$5:$AM$79,"–") -> 47 | Q35: =SUMIF(Cultures!$AM$5:$AM$79,0,Cultures!$D$5:$D$79) -> 12812.93 | R35: =SUMIF(Cultures!$AM$5:$AM$79,"<=1",Cultures!$D$5:$D$79) -> 12812.93
A36: ITK | B36: ID_PREC | C36: Précédent cultural (critère de spatialisation). | D36: — | E36: obligatoire (« * » accepté) | F36: Data_RPG_Gwad_2017 : groupe RPG déclaré de 2012 à 2017, par parcelle. | G36: 2 : connu au niveau des 12 groupes RPG, pas de la culture fine. La jachère (« gel ») doit figurer parmi les précédents des ITK qui la suivent. | H36: RPG (IGN/ASP). | I36: https://geoservices.ign.fr/rpg | J36: =IFERROR(AVERAGE(Cultures!$AN$5:$AN$79),"–") -> 2 | K36: =IFERROR(SUMPRODUCT(Cultures!$D$5:$D$79,Cultures!$AN$5:$AN$79)/SUMIF(Cultures!$AN$5:$AN$79,">=0",Cultures!$D$5:$D$79),"–") -> 2 | L36: =COUNTIF(Cultures!$AN$5:$AN$79,0) -> 0 | M36: =COUNTIF(Cultures!$AN$5:$AN$79,1) -> 0 | N36: =COUNTIF(Cultures!$AN$5:$AN$79,2) -> 75 | O36: =COUNTIF(Cultures!$AN$5:$AN$79,3) -> 0 | P36: =COUNTIF(Cultures!$AN$5:$AN$79,"–") -> 0 | Q36: =SUMIF(Cultures!$AN$5:$AN$79,0,Cultures!$D$5:$D$79) -> 0 | R36: =SUMIF(Cultures!$AN$5:$AN$79,"<=1",Cultures!$D$5:$D$79) -> 0
A37: ITK | B37: ZONE_PEDO, TYPE_EXPL, CLIMAT, IDS_SDCS | C37: Sol, type d'exploitation, zone climatique et séquence de référence (IDS_SDCS, face à ID_SDC de parcelles.shp) auxquels l'ITK s'applique ; en 1.4.31 aussi un critère libre, CRIT_SPAT_ADHOC. | D37: — | E37: obligatoire (« * » accepté) | F37: Règles GAMS qui attribuent l'ITK fin à une parcelle (île, région, pente, taille d'exploitation, irrigation, sol) : ENTREES.txt:299-457. | G37: 2 : les règles existent, à réécrire en critères MAELIA. | H37: — | J37: =IFERROR(AVERAGE(Cultures!$AO$5:$AO$79),"–") -> 2 | K37: =IFERROR(SUMPRODUCT(Cultures!$D$5:$D$79,Cultures!$AO$5:$AO$79)/SUMIF(Cultures!$AO$5:$AO$79,">=0",Cultures!$D$5:$D$79),"–") -> 2 | L37: =COUNTIF(Cultures!$AO$5:$AO$79,0) -> 0 | M37: =COUNTIF(Cultures!$AO$5:$AO$79,1) -> 0 | N37: =COUNTIF(Cultures!$AO$5:$AO$79,2) -> 74 | O37: =COUNTIF(Cultures!$AO$5:$AO$79,3) -> 0 | P37: =COUNTIF(Cultures!$AO$5:$AO$79,"–") -> 1 | Q37: =SUMIF(Cultures!$AO$5:$AO$79,0,Cultures!$D$5:$D$79) -> 0 | R37: =SUMIF(Cultures!$AO$5:$AO$79,"<=1",Cultures!$D$5:$D$79) -> 0
A38: ITK | B38: MATERIEL | C38: Matériel d'irrigation. | D38: — | E38: si irrigué | F38: Variantes irriguées et drapeau IRRIG_PARC ; le type de matériel est inconnu. | G38: 1 pour les ITK irrigués (dire d'expert), sans objet sinon. | H38: Chambre d'agriculture, Conseil départemental (réseau d'irrigation). | I38: https://guadeloupe.chambres-agriculture.fr/ | J38: =IFERROR(AVERAGE(Cultures!$AP$5:$AP$79),"–") -> 1 | K38: =IFERROR(SUMPRODUCT(Cultures!$D$5:$D$79,Cultures!$AP$5:$AP$79)/SUMIF(Cultures!$AP$5:$AP$79,">=0",Cultures!$D$5:$D$79),"–") -> 1 | L38: =COUNTIF(Cultures!$AP$5:$AP$79,0) -> 0 | M38: =COUNTIF(Cultures!$AP$5:$AP$79,1) -> 15 | N38: =COUNTIF(Cultures!$AP$5:$AP$79,2) -> 0 | O38: =COUNTIF(Cultures!$AP$5:$AP$79,3) -> 0 | P38: =COUNTIF(Cultures!$AP$5:$AP$79,"–") -> 60 | Q38: =SUMIF(Cultures!$AP$5:$AP$79,0,Cultures!$D$5:$D$79) -> 0 | R38: =SUMIF(Cultures!$AP$5:$AP$79,"<=1",Cultures!$D$5:$D$79) -> 1639.31
A39: ITK | B39: IS_<OT> | C39: Quelles opérations techniques existent : TRAVAIL_SOL (ex-PREPA et REPRISE), SEMIS, DESHERBAGE_MECA (ex-BINAGE), FERTI, PHYTO, IRRIGATION, RECOLTE ; FAUCHE et PATURE pour les prairies. | D39: O/N | E39: obligatoire | F39: Matrice_OTK_Cult_<scénario>, opérations rangées dans les types MAELIA. | G39: 3 si toutes les opérations ont un type MAELIA, 2 si au moins la moitié, 1 si quelques-unes, 0 si aucune. Voir aussi la colonne Dépassements. | H39: — | J39: =IFERROR(AVERAGE(Cultures!$AQ$5:$AQ$79),"–") -> 1.972973 | K39: =IFERROR(SUMPRODUCT(Cultures!$D$5:$D$79,Cultures!$AQ$5:$AQ$79)/SUMIF(Cultures!$AQ$5:$AQ$79,">=0",Cultures!$D$5:$D$79),"–") -> 1.4707294 | L39: =COUNTIF(Cultures!$AQ$5:$AQ$79,0) -> 1 | M39: =COUNTIF(Cultures!$AQ$5:$AQ$79,1) -> 1 | N39: =COUNTIF(Cultures!$AQ$5:$AQ$79,2) -> 71 | O39: =COUNTIF(Cultures!$AQ$5:$AQ$79,3) -> 1 | P39: =COUNTIF(Cultures!$AQ$5:$AQ$79,"–") -> 1 | Q39: =SUMIF(Cultures!$AQ$5:$AQ$79,0,Cultures!$D$5:$D$79) -> 6109.43 | R39: =SUMIF(Cultures!$AQ$5:$AQ$79,"<=1",Cultures!$D$5:$D$79) -> 6109.43
A40: ITK | B40: <OT>_TEMPS | C40: Débit de chantier de chaque opération (l'application ITK le demande en h/ha, le fichier le porte en ha/h). | D40: ha/h | E40: obligatoire | F40: Data_OTK : MO_EXPL × DOSE, en h/ha. | G40: Selon la part des heures portée par des opérations sans type MAELIA (effeuillage, tuteurage, emballage, soins aux animaux…) : 3 sous 10 %, 2 sous 50 %, 1 au-delà. | H40: — | J40: =IFERROR(AVERAGE(Cultures!$AR$5:$AR$79),"–") -> 2.0405405 | K40: =IFERROR(SUMPRODUCT(Cultures!$D$5:$D$79,Cultures!$AR$5:$AR$79)/SUMIF(Cultures!$AR$5:$AR$79,">=0",Cultures!$D$5:$D$79),"–") -> 1.6784108 | L40: =COUNTIF(Cultures!$AR$5:$AR$79,0) -> 0 | M40: =COUNTIF(Cultures!$AR$5:$AR$79,1) -> 7 | N40: =COUNTIF(Cultures!$AR$5:$AR$79,2) -> 57 | O40: =COUNTIF(Cultures!$AR$5:$AR$79,3) -> 10 | P40: =COUNTIF(Cultures!$AR$5:$AR$79,"–") -> 1 | Q40: =SUMIF(Cultures!$AR$5:$AR$79,0,Cultures!$D$5:$D$79) -> 0 | R40: =SUMIF(Cultures!$AR$5:$AR$79,"<=1",Cultures!$D$5:$D$79) -> 8030.23
A41: ITK | B41: <OT>_DEBUT / _FIN | C41: Fenêtres calendaires de chaque opération (1 à 3 sous-périodes, jours juliens). La récolte attend en plus la maturité. | D41: jour | E41: obligatoire | F41: Aucune. | G41: 1 si la culture a une campagne datée connue des fiches techniques, 0 si elle est conduite en continu (banane, plantain, maraîchage, prairie). | H41: Fiches techniques Chambre d'agriculture, CTCS, IT2 ; grille d'entretien ITK de MAELIA. | I41: https://guadeloupe.chambres-agriculture.fr/ | J41: =IFERROR(AVERAGE(Cultures!$AS$5:$AS$79),"–") -> 0.5 | K41: =IFERROR(SUMPRODUCT(Cultures!$D$5:$D$79,Cultures!$AS$5:$AS$79)/SUMIF(Cultures!$AS$5:$AS$79,">=0",Cultures!$D$5:$D$79),"–") -> 0.59643666 | L41: =COUNTIF(Cultures!$AS$5:$AS$79,0) -> 37 | M41: =COUNTIF(Cultures!$AS$5:$AS$79,1) -> 37 | N41: =COUNTIF(Cultures!$AS$5:$AS$79,2) -> 0 | O41: =COUNTIF(Cultures!$AS$5:$AS$79,3) -> 0 | P41: =COUNTIF(Cultures!$AS$5:$AS$79,"–") -> 1 | Q41: =SUMIF(Cultures!$AS$5:$AS$79,0,Cultures!$D$5:$D$79) -> 9264.41 | R41: =SUMIF(Cultures!$AS$5:$AS$79,"<=1",Cultures!$D$5:$D$79) -> 22956.52
A42: ITK | B42: Seuils de déclenchement | C42: Humidité du sol, cumul de pluie, P-ETP, température, stade (ECHV) qui autorisent l'opération. | D42: divers | E42: optionnel (NA accepté) | F42: Aucune. | G42: 0 : enquête auprès d'experts. Un ITK tourne sans (NA), mais il est alors aveugle à la météo, ce qui retire l'intérêt du pas de temps journalier. | H42: Grille d'entretien ITK de MAELIA ; application ITK. | I42: https://analytics.huma-num.fr/Renaud.Misslin/maelia_itk/ | J42: =IFERROR(AVERAGE(Cultures!$AT$5:$AT$79),"–") -> 0 | K42: =IFERROR(SUMPRODUCT(Cultures!$D$5:$D$79,Cultures!$AT$5:$AT$79)/SUMIF(Cultures!$AT$5:$AT$79,">=0",Cultures!$D$5:$D$79),"–") -> 0 | L42: =COUNTIF(Cultures!$AT$5:$AT$79,0) -> 74 | M42: =COUNTIF(Cultures!$AT$5:$AT$79,1) -> 0 | N42: =COUNTIF(Cultures!$AT$5:$AT$79,2) -> 0 | O42: =COUNTIF(Cultures!$AT$5:$AT$79,3) -> 0 | P42: =COUNTIF(Cultures!$AT$5:$AT$79,"–") -> 1 | Q42: =SUMIF(Cultures!$AT$5:$AT$79,0,Cultures!$D$5:$D$79) -> 22956.52 | R42: =SUMIF(Cultures!$AT$5:$AT$79,"<=1",Cultures!$D$5:$D$79) -> 22956.52
A43: ITK | B43: TRAVAIL_SOL_EFFET_RUs | C43: Profondeur de travail du sol (ex-PREPA et REPRISE). | D43: cm | E43: si travail du sol | F43: Data_Cult, ligne PROF_SILLONS (profondeur des sillons). | G43: 2 si PROF_SILLONS est renseignée, 1 sinon ; sans objet sans travail du sol. | H43: Fiches techniques. | I43: https://guadeloupe.chambres-agriculture.fr/ | J43: =IFERROR(AVERAGE(Cultures!$AU$5:$AU$79),"–") -> 1.9130435 | K43: =IFERROR(SUMPRODUCT(Cultures!$D$5:$D$79,Cultures!$AU$5:$AU$79)/SUMIF(Cultures!$AU$5:$AU$79,">=0",Cultures!$D$5:$D$79),"–") -> 1.9750397 | L43: =COUNTIF(Cultures!$AU$5:$AU$79,0) -> 0 | M43: =COUNTIF(Cultures!$AU$5:$AU$79,1) -> 4 | N43: =COUNTIF(Cultures!$AU$5:$AU$79,2) -> 42 | O43: =COUNTIF(Cultures!$AU$5:$AU$79,3) -> 0 | P43: =COUNTIF(Cultures!$AU$5:$AU$79,"–") -> 29 | Q43: =SUMIF(Cultures!$AU$5:$AU$79,0,Cultures!$D$5:$D$79) -> 0 | R43: =SUMIF(Cultures!$AU$5:$AU$79,"<=1",Cultures!$D$5:$D$79) -> 411.73
A44: ITK | B44: IRRIGATION_DOSE, _TD | C44: Dose par tour d'eau et délai de retour. | D44: mm, jours | E44: si irrigué | F44: Opérations d'irrigation de la matrice et BESOIN_EAU_01..12 (besoin brut, plat sur l'année : vigilance C.4). | G44: 2 si opérations et besoin, 1 si l'un des deux seulement, sans objet si ni l'un ni l'autre. | H44: FAO-56 ; pratiques locales. | I44: https://www.fao.org/4/x0490e/x0490e00.htm | J44: =IFERROR(AVERAGE(Cultures!$AV$5:$AV$79),"–") -> 1.1702128 | K44: =IFERROR(SUMPRODUCT(Cultures!$D$5:$D$79,Cultures!$AV$5:$AV$79)/SUMIF(Cultures!$AV$5:$AV$79,">=0",Cultures!$D$5:$D$79),"–") -> 1.4077468 | L44: =COUNTIF(Cultures!$AV$5:$AV$79,0) -> 0 | M44: =COUNTIF(Cultures!$AV$5:$AV$79,1) -> 39 | N44: =COUNTIF(Cultures!$AV$5:$AV$79,2) -> 8 | O44: =COUNTIF(Cultures!$AV$5:$AV$79,3) -> 0 | P44: =COUNTIF(Cultures!$AV$5:$AV$79,"–") -> 28 | Q44: =SUMIF(Cultures!$AV$5:$AV$79,0,Cultures!$D$5:$D$79) -> 0 | R44: =SUMIF(Cultures!$AV$5:$AV$79,"<=1",Cultures!$D$5:$D$79) -> 2310.67
A45: ITK | B45: IRRIGATION fenêtre, stades, seuils | C45: Période d'irrigation, stades de début et de fin, pluie qui annule ou reporte un tour. | D45: jour, mm | E45: si irrigué | F45: Aucune. | G45: 0 pour les cultures irriguées, sans objet sinon. | H45: Experts ; application ITK. | I45: https://analytics.huma-num.fr/Renaud.Misslin/maelia_itk/ | J45: =IFERROR(AVERAGE(Cultures!$AW$5:$AW$79),"–") -> 0 | K45: =IFERROR(SUMPRODUCT(Cultures!$D$5:$D$79,Cultures!$AW$5:$AW$79)/SUMIF(Cultures!$AW$5:$AW$79,">=0",Cultures!$D$5:$D$79),"–") -> 0 | L45: =COUNTIF(Cultures!$AW$5:$AW$79,0) -> 47 | M45: =COUNTIF(Cultures!$AW$5:$AW$79,1) -> 0 | N45: =COUNTIF(Cultures!$AW$5:$AW$79,2) -> 0 | O45: =COUNTIF(Cultures!$AW$5:$AW$79,3) -> 0 | P45: =COUNTIF(Cultures!$AW$5:$AW$79,"–") -> 28 | Q45: =SUMIF(Cultures!$AW$5:$AW$79,0,Cultures!$D$5:$D$79) -> 3901.49 | R45: =SUMIF(Cultures!$AW$5:$AW$79,"<=1",Cultures!$D$5:$D$79) -> 3901.49
A46: ITK | B46: PHYTO produits, doses | C46: Traitements phytosanitaires. | D46: L/ha | E46: si traité | F46: Matrice et Data_OTK (IFT, propriétés PPDB). | G46: 3 si l'ITK compte des traitements, sans objet sinon. | H46: — | J46: =IFERROR(AVERAGE(Cultures!$AX$5:$AX$79),"–") -> 3 | K46: =IFERROR(SUMPRODUCT(Cultures!$D$5:$D$79,Cultures!$AX$5:$AX$79)/SUMIF(Cultures!$AX$5:$AX$79,">=0",Cultures!$D$5:$D$79),"–") -> 3 | L46: =COUNTIF(Cultures!$AX$5:$AX$79,0) -> 0 | M46: =COUNTIF(Cultures!$AX$5:$AX$79,1) -> 0 | N46: =COUNTIF(Cultures!$AX$5:$AX$79,2) -> 0 | O46: =COUNTIF(Cultures!$AX$5:$AX$79,3) -> 71 | P46: =COUNTIF(Cultures!$AX$5:$AX$79,"–") -> 4 | Q46: =SUMIF(Cultures!$AX$5:$AX$79,0,Cultures!$D$5:$D$79) -> 0 | R46: =SUMIF(Cultures!$AX$5:$AX$79,"<=1",Cultures!$D$5:$D$79) -> 0
A47: ITK | B47: FAUCHE, PATURE | C47: Prairies : FAUCHE (hauteur de coupe, hauteur ou biomasse minimale) et PATURE (dates, temps de repos, part d'herbe accessible, hauteurs d'herbe à l'entrée et à la sortie), TYPE_GESTION_PRAIRIE. | D47: cm, t/ha, jours | E47: pour les prairies | F47: Opérations de déplacement et de soins des ITK PN ; ni hauteur d'herbe ni chargement. | G47: 0. Le pâturage demande en plus les lots d'animaux (feuille Autres données). | H47: INRAE Antilles-Guyane (élevage), Chambre d'agriculture, EDE. | I47: https://guadeloupe.chambres-agriculture.fr/ | J47: =IFERROR(AVERAGE(Cultures!$AY$5:$AY$79),"–") -> 0 | K47: =IFERROR(SUMPRODUCT(Cultures!$D$5:$D$79,Cultures!$AY$5:$AY$79)/SUMIF(Cultures!$AY$5:$AY$79,">=0",Cultures!$D$5:$D$79),"–") -> 0 | L47: =COUNTIF(Cultures!$AY$5:$AY$79,0) -> 2 | M47: =COUNTIF(Cultures!$AY$5:$AY$79,1) -> 0 | N47: =COUNTIF(Cultures!$AY$5:$AY$79,2) -> 0 | O47: =COUNTIF(Cultures!$AY$5:$AY$79,3) -> 0 | P47: =COUNTIF(Cultures!$AY$5:$AY$79,"–") -> 73 | Q47: =SUMIF(Cultures!$AY$5:$AY$79,0,Cultures!$D$5:$D$79) -> 6109.43 | R47: =SUMIF(Cultures!$AY$5:$AY$79,"<=1",Cultures!$D$5:$D$79) -> 6109.43
A48: Fertilisation | B48: FERTIALT produit, dose N-P-K | C48: Produits et doses par apport (4 apports au plus par stratégie). | D48: kg d'élément/ha (minéral), t brutes/ha (organique) | E48: AqYieldNC | F48: Lignes engrais de la matrice ; N par la colonne AZOTE, P et K par la formule dans le nom du produit. | G48: 3 si l'ITK fertilise, sans objet sinon. | H48: — | J48: =IFERROR(AVERAGE(Cultures!$AZ$5:$AZ$79),"–") -> 3 | K48: =IFERROR(SUMPRODUCT(Cultures!$D$5:$D$79,Cultures!$AZ$5:$AZ$79)/SUMIF(Cultures!$AZ$5:$AZ$79,">=0",Cultures!$D$5:$D$79),"–") -> 3 | L48: =COUNTIF(Cultures!$AZ$5:$AZ$79,0) -> 0 | M48: =COUNTIF(Cultures!$AZ$5:$AZ$79,1) -> 0 | N48: =COUNTIF(Cultures!$AZ$5:$AZ$79,2) -> 0 | O48: =COUNTIF(Cultures!$AZ$5:$AZ$79,3) -> 73 | P48: =COUNTIF(Cultures!$AZ$5:$AZ$79,"–") -> 2 | Q48: =SUMIF(Cultures!$AZ$5:$AZ$79,0,Cultures!$D$5:$D$79) -> 0 | R48: =SUMIF(Cultures!$AZ$5:$AZ$79,"<=1",Cultures!$D$5:$D$79) -> 0
A49: Fertilisation | B49: FERTIALT calendrier, alternatives | C49: Dates des apports, fractionnement, stratégies de repli selon le stock d'engrais. | D49: jour | E49: AqYieldNC | F49: Aucune : la matrice donne un nombre d'apports, pas leur date. | G49: 1 si le fractionnement est décrit dans les fiches techniques de la plante, 0 sinon ; sans objet sans fertilisation. | H49: Fiches techniques Chambre d'agriculture, CTCS, IT2. | I49: https://guadeloupe.chambres-agriculture.fr/ | J49: =IFERROR(AVERAGE(Cultures!$BA$5:$BA$79),"–") -> 0.56164384 | K49: =IFERROR(SUMPRODUCT(Cultures!$D$5:$D$79,Cultures!$BA$5:$BA$79)/SUMIF(Cultures!$BA$5:$BA$79,">=0",Cultures!$D$5:$D$79),"–") -> 0.91702662 | L49: =COUNTIF(Cultures!$BA$5:$BA$79,0) -> 32 | M49: =COUNTIF(Cultures!$BA$5:$BA$79,1) -> 41 | N49: =COUNTIF(Cultures!$BA$5:$BA$79,2) -> 0 | O49: =COUNTIF(Cultures!$BA$5:$BA$79,3) -> 0 | P49: =COUNTIF(Cultures!$BA$5:$BA$79,"–") -> 2 | Q49: =SUMIF(Cultures!$BA$5:$BA$79,0,Cultures!$D$5:$D$79) -> 1397.86 | R49: =SUMIF(Cultures!$BA$5:$BA$79,"<=1",Cultures!$D$5:$D$79) -> 16847.09
A50: Économie | B50: prixVentes.csv | C50: Prix de vente par espèce et par an. | D50: €/t (le guide imprime €/ha : à confirmer) | E50: pour les sorties économiques (MAELIA tourne sans) | F50: Prix_Cult_CF_<scénario>. | G50: 2 si un prix existe : 2017 seulement, les colonnes 2018-2022 en sont des copies. 1 sinon (canne fibre : prix nul). | H50: Agreste / DAAF (conjoncture), ODEADOM. | I50: https://www.odeadom.fr/ | J50: =IFERROR(AVERAGE(Cultures!$BB$5:$BB$79),"–") -> 1.8648649 | K50: =IFERROR(SUMPRODUCT(Cultures!$D$5:$D$79,Cultures!$BB$5:$BB$79)/SUMIF(Cultures!$BB$5:$BB$79,">=0",Cultures!$D$5:$D$79),"–") -> 2 | L50: =COUNTIF(Cultures!$BB$5:$BB$79,0) -> 0 | M50: =COUNTIF(Cultures!$BB$5:$BB$79,1) -> 10 | N50: =COUNTIF(Cultures!$BB$5:$BB$79,2) -> 64 | O50: =COUNTIF(Cultures!$BB$5:$BB$79,3) -> 0 | P50: =COUNTIF(Cultures!$BB$5:$BB$79,"–") -> 1 | Q50: =SUMIF(Cultures!$BB$5:$BB$79,0,Cultures!$D$5:$D$79) -> 0 | R50: =SUMIF(Cultures!$BB$5:$BB$79,"<=1",Cultures!$D$5:$D$79) -> 0
A51: Économie | B51: primes.csv | C51: Aides couplées par espèce et par département. | D51: €/ha | E51: pour les sorties économiques (MAELIA tourne sans) | F51: POSEI à l'hectare et à la tonne, aides canne (industrie, replantation, transport, garantie de prix), MAE. | G51: 2 : les aides à la tonne sont à convertir en €/ha avec un rendement. | H51: Programme POSEI France, ODEADOM, DAAF. | I51: https://www.odeadom.fr/ | J51: =IFERROR(AVERAGE(Cultures!$BC$5:$BC$79),"–") -> 2 | K51: =IFERROR(SUMPRODUCT(Cultures!$D$5:$D$79,Cultures!$BC$5:$BC$79)/SUMIF(Cultures!$BC$5:$BC$79,">=0",Cultures!$D$5:$D$79),"–") -> 2 | L51: =COUNTIF(Cultures!$BC$5:$BC$79,0) -> 0 | M51: =COUNTIF(Cultures!$BC$5:$BC$79,1) -> 0 | N51: =COUNTIF(Cultures!$BC$5:$BC$79,2) -> 75 | O51: =COUNTIF(Cultures!$BC$5:$BC$79,3) -> 0 | P51: =COUNTIF(Cultures!$BC$5:$BC$79,"–") -> 0 | Q51: =SUMIF(Cultures!$BC$5:$BC$79,0,Cultures!$D$5:$D$79) -> 0 | R51: =SUMIF(Cultures!$BC$5:$BC$79,"<=1",Cultures!$D$5:$D$79) -> 0
A52: Économie | B52: Prix des intrants | C52: Prix unitaires des semences et plants, engrais, traitements, carburant et eau : ce que la grille d'enquête demande pour le module économique, qui calcule à l'opération technique. | D52: €/kg, €/L, €/m³ | E52: pour les sorties économiques (format du fichier à confirmer) | F52: Data_OTK : PRIX_UNIT et DOSE de chaque intrant. Pas de prix du carburant. | G52: 2 si les intrants de l'ITK sont chiffrés : le carburant manque et les produits sont à rapprocher du référentiel MAELIA. | H52: — | J52: =IFERROR(AVERAGE(Cultures!$BD$5:$BD$79),"–") -> 2 | K52: =IFERROR(SUMPRODUCT(Cultures!$D$5:$D$79,Cultures!$BD$5:$BD$79)/SUMIF(Cultures!$BD$5:$BD$79,">=0",Cultures!$D$5:$D$79),"–") -> 2 | L52: =COUNTIF(Cultures!$BD$5:$BD$79,0) -> 0 | M52: =COUNTIF(Cultures!$BD$5:$BD$79,1) -> 0 | N52: =COUNTIF(Cultures!$BD$5:$BD$79,2) -> 75 | O52: =COUNTIF(Cultures!$BD$5:$BD$79,3) -> 0 | P52: =COUNTIF(Cultures!$BD$5:$BD$79,"–") -> 0 | Q52: =SUMIF(Cultures!$BD$5:$BD$79,0,Cultures!$D$5:$D$79) -> 0 | R52: =SUMIF(Cultures!$BD$5:$BD$79,"<=1",Cultures!$D$5:$D$79) -> 0
A53: Économie | B53: chargesOp.csv | C53: Charges opérationnelles par ITK : coût cumulé des intrants, hors irrigation. | D53: €/ha | E53: pour les sorties économiques (MAELIA tourne sans) | F53: Matrice × PRIX_UNIT, plus coûts de récolte et de transport. | G53: 2 si un coût est calculable : celui de MOSAICA mêle intrants, prestations, récolte, transport et forfait d'irrigation, que MAELIA compte séparément. | H53: — | J53: =IFERROR(AVERAGE(Cultures!$BE$5:$BE$79),"–") -> 2 | K53: =IFERROR(SUMPRODUCT(Cultures!$D$5:$D$79,Cultures!$BE$5:$BE$79)/SUMIF(Cultures!$BE$5:$BE$79,">=0",Cultures!$D$5:$D$79),"–") -> 2 | L53: =COUNTIF(Cultures!$BE$5:$BE$79,0) -> 0 | M53: =COUNTIF(Cultures!$BE$5:$BE$79,1) -> 0 | N53: =COUNTIF(Cultures!$BE$5:$BE$79,2) -> 75 | O53: =COUNTIF(Cultures!$BE$5:$BE$79,3) -> 0 | P53: =COUNTIF(Cultures!$BE$5:$BE$79,"–") -> 0 | Q53: =SUMIF(Cultures!$BE$5:$BE$79,0,Cultures!$D$5:$D$79) -> 0 | R53: =SUMIF(Cultures!$BE$5:$BE$79,"<=1",Cultures!$D$5:$D$79) -> 0
A54: Économie | B54: chargesDePassage.csv | C54: Charges de mécanisation par ITK (pour la marge semi-nette). | D54: €/ha | E54: pour la marge semi-nette | F54: Aucune : AMORTI ne fait que signaler les opérations amorties. | G54: 0 : pas de barème de mécanisation pour la Guadeloupe. | H54: Chambre d'agriculture, CUMA, prestataires de récolte (SICA canne). | I54: https://guadeloupe.chambres-agriculture.fr/ | J54: =IFERROR(AVERAGE(Cultures!$BF$5:$BF$79),"–") -> 0 | K54: =IFERROR(SUMPRODUCT(Cultures!$D$5:$D$79,Cultures!$BF$5:$BF$79)/SUMIF(Cultures!$BF$5:$BF$79,">=0",Cultures!$D$5:$D$79),"–") -> 0 | L54: =COUNTIF(Cultures!$BF$5:$BF$79,0) -> 75 | M54: =COUNTIF(Cultures!$BF$5:$BF$79,1) -> 0 | N54: =COUNTIF(Cultures!$BF$5:$BF$79,2) -> 0 | O54: =COUNTIF(Cultures!$BF$5:$BF$79,3) -> 0 | P54: =COUNTIF(Cultures!$BF$5:$BF$79,"–") -> 0 | Q54: =SUMIF(Cultures!$BF$5:$BF$79,0,Cultures!$D$5:$D$79) -> 23577.99 | R54: =SUMIF(Cultures!$BF$5:$BF$79,"<=1",Cultures!$D$5:$D$79) -> 23577.99
A56: Lignes des fichiers MAELIA non notées
A57: COULEUR_R, COULEUR_V, COULEUR_B | C57: Couleur d'affichage : obligatoire, sans enjeu.
A58: isCouvert | C58: Vrai pour un couvert intermédiaire : faux pour toutes les cultures de MOSAICA.
A59: a_Ndemand_ci, b_Ndemand_ci, Dde | C59: Propres aux couverts intermédiaires.
A60: RootC_fixed, BESOIN_Ntot | C60: Variantes de SR_ratio et de BESOIN_N (apport racinaire fixe, besoin total par hectare comme pour la betterave et la pomme de terre).
A61: tgelLev10/90, tgelJuv10/90, tgelVeg10/90, tgelFlo10/90, DEGRES_J_stadeJuvenile, DEGRES_J_dureeFloraison | C61: Stress climatique (gel, échaudage), apparus en 1.4.31 ; inactif par défaut (avecStressClimatique). Le gel est sans objet aux Antilles, l'échaudage reste à instruire.
A62: ALPHA*, KC* | C62: Modèle de culture « simple » seulement.
A63: date_maj, source_projet, indice_fiabilite | C63: Traçabilité de l'espèce (1.4.31). MAELIA tient son propre indice de fiabilité par espèce.
A64: IS_CULTURE_HIVER | C64: Culture d'hiver ou de printemps : sert à choisir un ITK de repli quand le semis échoue. Sens à définir sous les tropiques.
A65: IS_CORPEN | C65: Ajuste les doses d'azote minéral aux rendements simulés (option du lanceur).
A66: <OT>_OUTIL, _AGRIW, _PASSAGES, _OPERATEUR, _NOM, _OT_PREALABLE | C66: Outil, opération faite par l'agriculteur ou par un tiers, passages, nom. Sans effet sur la simulation d'après la note de 2022 ; l'outil sert au module économique.
A67: ID_ANTE_PREC, ID_SUIV, CRIT_SPAT_ADHOC | C67: Antéprécédent, culture suivante, critère libre : critères de spatialisation apparus en 1.4.31.
A68: PHYTO_TYPE | C68: Type de traitement, pour l'IFT.
A69: IRRIGATION_SIRR1 à 3, _IS_THEORIQUE, _GROUPE | C69: Mode d'optimisation de l'irrigation (taux de satisfaction hydrique visé par stade) et tours d'eau par groupe.

Sheet Autres données
A1: Données hors cultures : climat, sols, parcellaire, exploitations, hydrologie
A2: Même échelle 0-3. La priorité dit quel usage la donnée bloque : le module agricole seul (1), la version azote et le test de robustesse (2), les modules hydrologique, normatif et filières (3). Laissés de côté, sans objet sur une île tropicale : bandes d'altitude pour la neige, îlots hors zone.
A4: Thème | B4: Donnée | C4: Fichier et champs MAELIA | D4: Nécessité | E4: Priorité | F4: Ce qu'on a aujourd'hui | G4: Qualité | H4: Sources | I4: Lien | J4: Accès, licence | K4: À faire, remarques
A5: Climat | B5: Pluie journalière | C5: meteo/observee/<année>.csv : RRmm | D5: obligatoire | E5: 1 — bloquant | F5: Normale annuelle 1981-2010 seulement (raster Météo-France krigé à 10 m, data/gis/05_Pluviométrie) et une classe par parcelle. Aucune série journalière. | G5: 1 | H5: Météo-France, données climatologiques de base quotidiennes (toutes les stations, outre-mer compris, par département) ; stations INRAE via CLIMATIK (Le Moule – Gardel y figure ; Duclos et Godet à vérifier). | I5: https://www.data.gouv.fr/datasets/donnees-climatologiques-de-base-quotidiennes | J5: Météo-France : Licence Ouverte 2.0. CLIMATIK : identifiants INRAE (intranet) | K5: Télécharger les postes du 971 ; viser 20 ans, comme le demande la formation. Liste des paramètres par poste à lire dans le descriptif des champs du jeu.
A6: Climat | B6: Températures minimale et maximale journalières | C6: meteo/observee/<année>.csv : Tmin, Tmax | D6: obligatoire | E6: 1 — bloquant | F6: Rien. | G6: 1 | H6: Mêmes sources que la pluie ; moins de postes mesurent la température. | I6: https://www.data.gouv.fr/datasets/donnees-climatologiques-de-base-quotidiennes | J6: Licence Ouverte 2.0 | K6: Vérifier la couverture en altitude (Basse-Terre).
A7: Climat | B7: Rayonnement global journalier | C7: meteo/observee/<année>.csv : RGI (MJ/m²/j d'après le guide, W/m² d'après le support de formation : à confirmer) | D7: obligatoire — une chaîne sans rayonnement est inutilisable | E7: 1 — bloquant | F7: Rien. | G7: 1 | H7: Quelques stations synoptiques et INRAE ; en repli les réanalyses ERA5-Land ou AgERA5 (Copernicus) et NASA POWER, grossières pour une île à relief. | I7: https://cds.climate.copernicus.eu/datasets/sis-agrometeorological-indicators | J7: Gratuit, compte Copernicus et licence du service ; NASA POWER libre | K7: Comparer la réanalyse à une station avant de s'y fier.
A8: Climat | B8: ETP Penman-Monteith journalière | C8: meteo/observee/<année>.csv : ETP (mm) | D8: obligatoire | E8: 1 — bloquant | F8: Rien. | G8: 1 | H8: ETP fournie par Météo-France pour certains postes ; sinon à calculer (FAO-56) à partir de T, humidité, vent et rayonnement (méthode FAO-56). | I8: https://www.fao.org/4/x0490e/x0490e00.htm | J8: Météo-France : Licence Ouverte 2.0 ; FAO-56 en libre lecture | K8: Choisir une seule méthode pour toute l'île. Le fichier météo n'a pas de colonne d'humidité de l'air, alors qu'un déclencheur de traitement s'appelle hygrométrie.
A9: Climat | B9: Grille climatique | C9: polygonesMeteoFrance.shp : ID_PDG, POSX, POSY, ALTI_MOY | D9: obligatoire | E9: 1 — bloquant | F9: Pas de maille SAFRAN outre-mer. Le raster des normales de pluie et le MNT permettent de découper des zones. | G9: 1 | H9: À construire : polygones autour des stations, recoupés par classes de pluie et d'altitude. | I9: https://maelia.pages-forge.inrae.fr/documentation/04-donnees_entree.html | J9: — | K9: Demander à l'équipe MAELIA le système de coordonnées attendu hors métropole.
A10: Climat | B10: Gradient spatial de pluie | C10: sert à construire la grille | D10: utile | E10: 1 — bloquant | F10: Pluvio_1981-2010_MF_kriging_spher_10m.tif et PLUVIO_PARC par parcelle. | G10: 2 | H10: Météo-France, normales 1981-2010 krigées (couche fournie au projet MOSAICA). | J10: Local (data/gis/, non versionné) ; conditions de réutilisation à préciser | K10: Sert à redresser les séries de station par zone ; annuel seulement.
A11: Climat | B11: Projections climatiques journalières (20 ans au moins, avec rayonnement) | C11: meteo/simulee/<scénario>/<année>.csv | D11: pour les scénarios climatiques | E11: 2 — azote, robustesse | F11: Rien en local. | G11: 1 | H11: DRIAS diffuse les projections C3AF : quotidiennes, aux stations (69 pluviomètres, 17 postes thermiques sur les Antilles), RCP 8.5 seul, 1980-2013 et 2031-2080, pluie et températures seulement. Les projections Outre-mer à 3 km (SocleOM-climat-2025) arrivent sur DRIAS au cours de 2026. En complément, NEX-GDDP-CMIP6 (0,25°, avec rayonnement). | I11: https://www.drias-climat.fr/ | J11: DRIAS : gratuit, sur compte ; NEX-GDDP : libre | K11: C3AF n'a ni rayonnement ni ETP : inutilisable seul pour MAELIA. Suivre la mise en ligne des données à 3 km ; viser deux narratifs contrastés.
A12: Sols | B12: Carte des sols et zonage | C12: typeDeSolParZH.shp : ID_SOL, STU_DOM, ZONE_PEDO | D12: obligatoire | E12: 1 — bloquant | F12: Carte Colmet-Daage–Brossard (26 unités cartographiques, 18 types simplifiés, data/gis/04_Pédologie), TYPE_SOL (5 groupes) et TYPE_SOL_INIT par parcelle. | G12: 2 | H12: Cartes Colmet-Daage numérisées par l'IRD (1/20 000, 1961, GeoTIFF) dans DataSuds-geo ; la Guadeloupe n'est pas dans la liste des référentiels régionaux du GIS Sol (mail de l'équipe MAELIA). L'équipe propose d'intégrer les données fournies à son système d'information. | I12: https://datasuds-geo.ird.fr/ | J12: Copie locale ; DataSuds : licence à vérifier par carte | K12: Traduire la légende en ZONE_PEDO et en unités de sol.
A13: Sols | B13: Lien îlot → sol | C13: ilots.shp : ID_SOL | D13: obligatoire | E13: 1 — bloquant | F13: Croisement RPG × pédologie déjà fait (RPG_2017_GC_MG_Pédologie). | G13: 2 | H13: — | J13: Local | K13: Sol dominant par îlot, une fois les ID_SOL définis.
A14: Sols | B14: Profondeurs des horizons et profondeur enracinable | C14: P1..P4, PRO, PRO_OC, CSTRU | D14: obligatoire | E14: 1 — bloquant | F14: SOL_COURT par parcelle (sol squelettique) ; Data_Sol PROF (couche de carbone). | G14: 1 | H14: Carte Colmet-Daage (ORSTOM) et ses notices ; synthèses et analyses INRAE Antilles-Guyane (UR ASTRO) ; RMQS du GIS Sol (10 sites en Guadeloupe en 2006, 42 points dans la campagne en cours : pH, carbone, azote, granulométrie, pas d'hydrodynamique) ; SoilGrids en repli | I14: https://www.gissol.fr/le-gis/programmes/rmqs-34 | J14: Publications ; données RMQS sur demande au GIS Sol | K14: CSTRU vaut 0,9 par défaut.
A15: Sols | B15: Texture et cailloux par horizon | C15: ARG, LIM, SAB, EG (CX) | D15: obligatoire | E15: 1 — bloquant | F15: Rien. | G15: 1 | H15: Carte Colmet-Daage (ORSTOM) et ses notices ; synthèses et analyses INRAE Antilles-Guyane (UR ASTRO) ; RMQS du GIS Sol (10 sites en Guadeloupe en 2006, 42 points dans la campagne en cours : pH, carbone, azote, granulométrie, pas d'hydrodynamique) ; SoilGrids en repli (250 m) | I15: https://soilgrids.org/ | J15: Publications ; RMQS sur demande ; SoilGrids CC-BY 4.0 | K15: La granulométrie classique décrit mal les andosols (allophanes).
A16: Sols | B16: Densité apparente | C16: DAH1..4, DAH_OC | D16: obligatoire | E16: 1 — bloquant | F16: Data_Sol, ligne DENS : une valeur par groupe de sol. | G16: 2 | H16: Carte Colmet-Daage (ORSTOM) et ses notices ; synthèses et analyses INRAE Antilles-Guyane (UR ASTRO) ; RMQS du GIS Sol (10 sites en Guadeloupe en 2006, 42 points dans la campagne en cours : pH, carbone, azote, granulométrie, pas d'hydrodynamique) ; SoilGrids en repli | J16: Local | K16: Par horizon dans MAELIA, par groupe de sol ici.
A17: Sols | B17: Réserve utile, capacité au champ, point de flétrissement | C17: RUPRH1..4, HCC1, HPFP1 | D17: obligatoire | E17: 1 — bloquant | F17: Rien. | G17: 1 | H17: Courbes de rétention publiées par INRAE Antilles-Guyane pour vertisols, ferralsols, andosols et nitisols. | J17: Publications | K17: Les fonctions de pédotransfert tempérées (Saxton et Rawls) ne valent ni pour les andosols ni pour les vertisols.
A18: Sols | B18: Conductivité à saturation et infiltrabilité | C18: KSAT1..4, PIRM | D18: obligatoire | E18: 1 — bloquant | F18: RUI_PARC et DRAI_PARC (ruissellement et drainage annuels par parcelle) : indices, pas des conductivités. | G18: 0 | H18: Mesures de terrain INRAE ; à défaut valeurs par type de sol avec l'équipe MAELIA. | J18: — | K18: Les vertisols gonflants sortent du cadre d'un Ksat constant.
A19: Sols | B19: Matière organique | C19: MO1 | D19: AqYieldNC | E19: 2 — azote, robustesse | F19: PART_C_INIT par parcelle (carbone organique initial, %) : MO = C × 1,72. | G19: 2 | H19: MORGWANIK ; analyses de terre. | J19: Local | K19: L'azote minéral initial du sol et la fraction stable de la matière organique (0,65 par défaut, option du lanceur) sont aussi des entrées : où les fournir, à confirmer.
A20: Sols | B20: pH, C/N, calcaire | C20: PH1, CN1, CAL1 | D20: AqYieldNC | E20: 2 — azote, robustesse | F20: Rien. | G20: 1 | H20: Carte Colmet-Daage (ORSTOM) et ses notices ; synthèses et analyses INRAE Antilles-Guyane (UR ASTRO) ; RMQS du GIS Sol (10 sites en Guadeloupe en 2006, 42 points dans la campagne en cours : pH, carbone, azote, granulométrie, pas d'hydrodynamique) ; SoilGrids en repli | I20: https://www.gissol.fr/le-gis/programmes/rmqs-34 | J20: Publications ; données RMQS sur demande au GIS Sol | K20: Calcaire : Grande-Terre et Marie-Galante surtout.
A21: Parcellaire | B21: Géométrie des îlots et des parcelles | C21: ilots.shp, parcelles.shp : ID_ILOT, ID_PARCELL, ID_EXPL, SURFACE, POURCENTAG | D21: obligatoire | E21: 1 — bloquant | F21: RPG 2017 avec pacage, pac_ilot, num_ilot, parcelle, surf_parc (data/gis/01_RPG 2017). | G21: 3 | H21: RPG (ASP, diffusé par l'IGN). La version publique est anonymisée, sans numéro d'exploitation ; sa couverture de la Guadeloupe reste à vérifier. | I21: https://geoservices.ign.fr/rpg | J21: Niveau 2 : la version avec numéro PACAGE est réservée aux administrations, sur demande à la DAAF ; vérifier la convention qui couvre la copie locale | K21: ID_PARCELL = pac_ilot + « _ » + parcelle, à confirmer avec l'équipe MAELIA.
A22: Parcellaire | B22: Séquences de cultures | C22: parcelles.shp : SEQUENCE, CULT_REF, INDEX_DEP, EXPREST, ID_SDC | D22: obligatoire | E22: 1 — bloquant | F22: Groupe RPG déclaré de 2012 à 2017 par parcelle (Data_RPG_Gwad_2017) ; ou le plan optimisé par MOSAICA. | G22: 2 | H22: Séquences RPG Explorer (INRAE), construites sur le RPG public depuis 2015, pour la France hexagonale seulement. | I22: https://entrepot.recherche.data.gouv.fr/dataset.xhtml?persistentId=doi:10.57745/W8SQPZ | J22: RPG Explorer : Licence Etalab 2.0 ; nos séquences, niveau 2 | K22: 12 groupes, pas la culture fine ; que devient une plantation de 7 ans dans une séquence annuelle ?
A23: Parcellaire | B23: Pente | C23: ilots.shp : PENTE_MOY, PENTE_SWAT | D23: obligatoire | E23: 1 — bloquant | F23: MNT de 1 à 10 m et pente par parcelle (data/gis/02_Altitude, 03_Pente). | G23: 2 | H23: RGE ALTI (IGN) : le MNT à 1 m de Guadeloupe vient des levés Litto3D (IGN-SHOM). L'origine du MNT local n'est pas documentée dans ses métadonnées. | I23: https://geoservices.ign.fr/rgealti | J23: Local ; RGE ALTI diffusé gratuitement par l'IGN (licence à lire sur la fiche) | K23: Unité de PENTE à confirmer (% ou degrés).
A24: Parcellaire | B24: Irrigabilité | C24: ilots.shp : CARACT_IRR | D24: obligatoire | E24: 1 — bloquant | F24: Réseau d'irrigation du Conseil départemental (bornes, canalisations, tampon de 800 m) et IRRIG_PARC. | G24: 2 | H24: Conseil départemental de la Guadeloupe, propriétaire du réseau ; exploitation en délégation de service public (Karukér'Ô dans le Nord Grande-Terre, contrat renouvelé en 2024). | J24: Copie locale ; mise à jour à demander au Département | K24: Date du relevé à vérifier ; MOSAICA le complète par la culture observée (vigilance G.10).
A25: Parcellaire | B25: Parcelles fauchables et pâturables | C25: parcelles.shp : IS_FAUCHE, IS_PATURAG | D25: pour les prairies | E25: 2 — azote, robustesse | F25: Rien par parcelle ; les deux ITK de prairie (piquet, pâturage tournant) disent le mode. | G25: 1 | H25: Dire d'expert ; règle simple par ITK. | J25: — | K25: Champs vus dans le jeu de la formation (1.4.31), absents du guide.
A26: Exploitations | B26: Liste et type des exploitations | C26: exploitations.csv : ID_EXPL, TYPE_EXPL | D26: obligatoire | E26: 1 — bloquant | F26: 4 638 exploitations et leur type (8 types MOSAICA, d'après Chopin et al. 2015). | G26: 2 | H26: — | J26: Niveau 2 | K26: TYPE_EXPL sert à choisir l'ITK dans MAELIA : la typologie économique de MOSAICA n'est pas forcément le bon critère.
A27: Exploitations | B27: Matériel d'irrigation | C27: materiel.csv : surface irrigable par jour, travail par jour ; ilots.shp : MATERIEL | D27: si irrigation | E27: 1 — bloquant | F27: Rien. | G27: 1 | H27: Dire d'expert : Chambre d'agriculture, Conseil départemental. | I27: https://guadeloupe.chambres-agriculture.fr/ | J27: — | K27: Aspersion, goutte-à-goutte : quelques types suffisent.
A28: Exploitations | B28: Main-d'œuvre disponible | C28: contrainte de main-d'œuvre (avecContrainteDeMainOeuvre) | D28: pour le test de robustesse | E28: 2 — azote, robustesse | F28: Budget d'heures par exploitation (MO_Expl_init, reconstruit à partir des ITK observés). | G28: 2 | H28: Recensement agricole 2020 (UTA). | I28: https://daaf.guadeloupe.agriculture.gouv.fr/ | J28: Niveau 2. RA 2020 : public à l'EPCI ; données individuelles sous secret statistique, par le CASD après avis du Comité du secret | K28: Annuel dans MOSAICA. MAELIA compte par jour : 12 h par unité de main-d'œuvre, 16 h pour finir une parcelle (paramétrable). Où déclarer le nombre d'unités par exploitation, et si les chantiers faits par un tiers comptent : à confirmer.
A29: Exploitations | B29: Outils et débits de chantier | C29: <OT>_OUTIL, <OT>_TEMPS de reglesDeDecisions.csv | D29: pour le temps de travail et l'économie | E29: 2 — azote, robustesse | F29: Temps de travail par opération (Data_OTK : MO_EXPL × DOSE) ; pas de liste d'outils. | G29: 2 | H29: Référentiel d'outils de la grille d'enquête ITK ; Chambre d'agriculture. | I29: https://guadeloupe.chambres-agriculture.fr/ | J29: — | K29: Le matériel tropical (coupeuse de canne, câble de bananeraie) est à ajouter.
A30: Exploitations | B30: Élevage : lots d'animaux et bâtiments | C30: lotsAnimaux.csv (ID_LOT, TYPE_ANIMAUX, NB_UGB, CST_ALIM, FECES, RESTITUTION_BATIMENT, ELOIGNEMENT_MIN/MAX), batiments.shp | D30: pour le pâturage | E30: 2 — azote, robustesse | F30: Rien : l'élevage n'apparaît dans MOSAICA que par les ITK de prairie. | G30: 0 | H30: Recensement agricole 2020, base nationale d'identification bovine (BDNI). | I30: https://daaf.guadeloupe.agriculture.gouv.fr/ | J30: RA : individuel par le CASD seulement ; BDNI : accès restreint | K30: À cadrer avec le projet CEDRE (élevage).
A31: Engrais et PRO | B31: Engrais minéraux | C31: engrais.csv : composition, facteurs NH₃, eqCO2, coût | D31: AqYieldNC | E31: 2 — azote, robustesse | F31: Data_OTK : teneur en N, prix unitaire ; P et K par la formule du produit. | G31: 2 | H31: Engrais.csv des jeux d'exemple MAELIA (types génériques AN, Urea, NPK…). | I31: https://maelia.pages-forge.inrae.fr/documentation/04-donnees_entree.html | J31: Local | K31: Faire correspondre chaque produit à un type MAELIA.
A32: Engrais et PRO | B32: Produits organiques locaux (fumier, compost, écumes, vinasse, bagasse) | C32: engrais.csv : C, N, humidité, paramètres de décomposition (K1, C2, kres…) | D32: AqYieldNC | E32: 2 — azote, robustesse | F32: Data_OTK : HUM, CARB, FHUM des amendements. | G32: 1 | H32: Analyses INRAE/CIRAD des produits locaux ; paramètres de décomposition par analogie avec un produit du fichier MAELIA. | I32: https://maelia.pages-forge.inrae.fr/documentation/04-donnees_entree.html | J32: Publications | K32: Les paramètres de décomposition demandent des incubations : analogie d'abord.
A33: Engrais et PRO | B33: Gisements annuels de PRO | C33: engrais.csv : QuantiteDispoAnnuelleT | D33: AqYieldNC | E33: 2 — azote, robustesse | F33: Rien. | G33: 1 | H33: Sucreries et distilleries, ADEME, Chambre d'agriculture. | I33: https://guadeloupe.chambres-agriculture.fr/ | J33: — | K33: À 0, le produit n'est jamais épandu ; 1000000000 = illimité. Stock géré au niveau du territoire ou de l'exploitation ; un délai de retour par produit. En 1.4.31 : parametres/engrais_qte_annuelle_dispo.csv.
A34: Économie | B34: Prix et redevance de l'eau | C34: prixEau.csv, redevanceEau.csv | D34: si irrigation | E34: 2 — azote, robustesse | F34: Un forfait par hectare (EAU_IRRIG, MAT_IRRIG dans Data_OTK), pas un prix au m³. | G34: 1 | H34: Tarif du réseau départemental : une part fixe et une part au m³ (0,09 € HT/m³ au total en 2012, rapport du délégataire) ; Office de l'eau Guadeloupe (redevances). | I34: https://www.cg971.fr/wp-content/uploads/2020/07/CRF-V2-RAPPORT-2012-Guadeloupe-Irrigation-modif-suite-demande-SD-19-11-13.pdf | J34: Public ; tarif en vigueur à demander au Département | K34: MAELIA attend un prix par m³ et par type de ressource (nappe, surface, retenue, canal).
A35: Économie | B35: Prix du carburant | C35: module économique (grille d'enquête : GNR, €/L) | D35: pour les sorties économiques | E35: 2 — azote, robustesse | F35: Rien. | G35: 1 | H35: Prix maximaux fixés chaque mois par arrêté préfectoral (code de l'énergie, R. 671-1 et suivants), publiés au recueil des actes administratifs de la préfecture. | J35: Public | K35: Le gazole non routier est-il dans l'arrêté ? À vérifier.
A36: Économie | B36: Séries de prix pluriannuelles | C36: prixVentes<SC>.csv : une colonne par an | D36: pour les scénarios de prix | E36: 2 — azote, robustesse | F36: 2017 ; les années 2018-2022 en sont des copies. | G36: 1 | H36: DAAF Guadeloupe (bulletins de conjoncture Agreste), ODEADOM. | I36: https://daaf.guadeloupe.agriculture.gouv.fr/ | J36: Public | K36: Les bulletins donnent des prix par filière, pas toujours par culture fine.
A37: Validation | B37: Rendements observés par culture et par an | C37: sert à caler RENDEMENT_OPTIMAL et à valider | D37: indispensable au calage | E37: 1 — bloquant | F37: Rdt_Cult, sans série annuelle. | G37: 1 | H37: Agreste Guadeloupe (mémentos, bulletins de conjoncture : surfaces, productions ; canne : tonnage broyé et rendement moyen), interprofession canne et CTCS pour le détail par bassin, LPG pour la banane. | I37: https://daaf.guadeloupe.agriculture.gouv.fr/IMG/pdf/agreste_memento_2022_guadeloupe.pdf | J37: Agreste public ; détail par bassin ou par exploitation à demander aux filières | K37: C'est ici que la vigilance C.1 se règle ou se déplace.
A38: Validation | B38: Jeux expérimentaux pour calibrer AqYield en tropical | C38: humidité et azote du sol, biomasse, LAI | D38: pour créer une espèce | E38: 1 — bloquant | F38: Rien. | G38: 0 | H38: Essais INRAE Antilles-Guyane et CIRAD ; LAI par télédétection (Sentinel-2). | J38: Essais : à demander aux équipes ; Sentinel-2 : libre | K38: Commencer par une culture pilote (igname ou melon), puis la canne.
A39: Référentiels | B39: Limites administratives | C39: communes.shp, departement.shp | D39: optionnel (un avertissement s'il manque) ; le département sert aux aides couplées | E39: 2 — azote, robustesse | F39: Code commune par parcelle ; pas la couche. | G39: 1 | H39: ADMIN EXPRESS (IGN). | I39: https://geoservices.ign.fr/adminexpress | J39: Licence Ouverte 2.0 | K39: Téléchargement direct.
A40: Référentiels | B40: Calendrier | C40: date/joursParMois.csv | D40: obligatoire | E40: 1 — bloquant | F40: Contenu fixe, donné dans le guide. | G40: 3 | H40: Guide MAELIA. | I40: https://maelia.pages-forge.inrae.fr/documentation/04-donnees_entree.html | J40: — | K40: À recopier tel quel.
A41: Référentiels | B41: Contour du terrain et zone hydrographique minimale | C41: contourZH.shp, ZH.shp ; ID_ZH dans ilots.shp et typeDeSolParZH.shp | D41: obligatoire, à confirmer | E41: 1 — bloquant | F41: Contour des îles (par le RPG ou les communes) ; 230 bassins versants. | G41: 2 | H41: — | J41: Local | K41: Les deux jeux d'exemple gardent ces fichiers alors que le module hydrologique est coupé (une seule zone dans terrainTest).
A42: Hydrologie | B42: Bassins versants élémentaires et leur chaînage | C42: ZH.shp : ID_ZH, ID_ND_EXUT | D42: module hydrologique | E42: 3 — modules optionnels | F42: 230 bassins de 50 ha et plus avec exutoires (data/gis/10_Bassins versants) et bassin de chaque parcelle. | G42: 2 | H42: Nos bassins, tirés du MNT. La BD TOPAGE Guadeloupe (Sandre) donne cours d'eau, plans d'eau et tronçons, mais pas encore de bassins versants. | I42: https://www.data.gouv.fr/datasets/bd-topage-r-guadeloupe-2026 | J42: Local ; BD TOPAGE : Licence Ouverte 2.0 | K42: La table de chaînage amont-aval reste à écrire.
A43: Hydrologie | B43: Relief | C43: MNT, pente (alti25m, pente_percent) | D43: module hydrologique | E43: 3 — modules optionnels | F43: MNT de 1 à 10 m. | G43: 3 | H43: RGE ALTI (IGN). | I43: https://geoservices.ign.fr/rgealti | J43: Local | K43: —
A44: Hydrologie | B44: Géomorphologie SWAT et HRU | C44: donneesMNT_ZH.csv, hru_*.shp | D44: module hydrologique | E44: 3 — modules optionnels | F44: Rien. | G44: 1 | H44: À produire avec ArcSWAT ou QSWAT. | I44: https://maelia.pages-forge.inrae.fr/documentation/04-donnees_entree.html | J44: — | K44: Un projet en soi.
A45: Hydrologie | B45: Occupation du sol | C45: clc/ | D45: module hydrologique | E45: 3 — modules optionnels | F45: Rien. | G45: 1 | H45: KaruCover (KaruGéo) : occupation du sol à grande échelle, 77 postes, 2004, 2010, 2017 et 2022, compatible OCS GE. En repli, Corine Land Cover (DOM couverts, unité minimale 25 ha). | I45: https://www.karugeo.fr/accueil/actualites/92_224/karucover_ocs2d__une_donnee_de_reference | J45: KaruGéo : consultation libre, conditions de téléchargement à vérifier ; CLC libre | K45: KaruCover 2017 est contemporain du RPG utilisé par MOSAICA.
A46: Hydrologie | B46: Réseau hydrographique, retenues, canaux | C46: troncons/, retenuesCollinaires/, canaux/ | D46: module hydrologique | E46: 3 — modules optionnels | F46: Ouvrages et canalisations du réseau d'irrigation. | G46: 1 | H46: BD TOPO (IGN), BD TOPAGE Guadeloupe, Conseil départemental (ouvrages d'irrigation). | I46: https://geoservices.ign.fr/bdtopo | J46: Licence Ouverte 2.0 | K46: —
A47: Hydrologie | B47: Prélèvements et rejets | C47: equipements/ (points de prélèvement) | D47: module hydrologique | E47: 3 — modules optionnels | F47: Périmètres de protection des captages (PPE, PPI, PPR). | G47: 1 | H47: Banque nationale des prélèvements en eau (BNPE), qui couvre les DOM : volumes annuels par ouvrage et par usage. | I47: https://bnpe.eaufrance.fr/ | J47: Libre | K47: Annuel seulement.
A48: Hydrologie | B48: Débits observés | C48: calage du module hydrologique | D48: module hydrologique | E48: 3 — modules optionnels | F48: Rien. | G48: 1 | H48: Réseau hydrométrique de la DEAL (HydroPortail, bulletins hydrologiques) ; Observatoire de l'eau de Guadeloupe. | I48: https://www.hydro.eaufrance.fr/ | J48: Libre | K48: La DEAL signale des courbes de tarage en consolidation et des lacunes en 2024.
A49: Normatif | B49: Débits de référence, restrictions, règles des barrages | C49: pointsDeReference.shp, seuilsDeRestriction.csv, barrage.csv | D49: module normatif | E49: 3 — modules optionnels | F49: Rien. | G49: 2 | H49: Arrêté cadre sécheresse (DEAL/RN n° 971-2023-07-06-0009) : seuils de vigilance, d'alerte et de crise à 7 stations ; SDAGE Guadeloupe. | I49: https://www.guadeloupe.developpement-durable.gouv.fr/ | J49: Public | K49: Les règles de gestion des retenues restent à obtenir.
A50: Indicateurs | B50: Biodiversité (i-Bio) et érosion | C50: parcelles.shp : IBIO_LCD, IBIO_HSN, IBIO_CONN ; texture, matière organique et pente pour l'érosion | D50: optionnel | E50: 3 — modules optionnels | F50: ZNIEFF, pente ; pas d'indicateur de paysage. | G50: 1 | H50: À calculer par SIG. | J50: — | K50: Modules présentés à la formation ; champs IBIO vus dans le jeu 1.4.31.
A51: Indicateurs | B51: Zonages réglementaires | C51: plan d'épandage (engrais.csv : plan_epandage), zones vulnérables, captages | D51: optionnel | E51: 3 — modules optionnels | F51: Périmètres de protection des captages, ZNIEFF, risque chlordécone par parcelle. | G51: 2 | H51: DEAL Guadeloupe ; KaruGéo diffuse les cartes de chlordécone dans les sols. | I51: https://www.karugeo.fr/ | J51: Local ; KaruGéo en consultation libre | K51: La grille d'enquête ITK demande les réglementations du territoire.
A52: Filières | B52: Unités de transformation, recettes, transport | C52: UT.shp, UP.shp, recettes.csv, produits.csv, routes.shp | D52: module filières | E52: 3 — modules optionnels | F52: Quotas et capacités par filière dans les contraintes de MOSAICA. | G52: 1 | H52: Sucreries, distilleries, centrale bagasse-biomasse ; OpenStreetMap (routes). | I52: https://www.openstreetmap.org/ | J52: — | K52: —
